Workbook

Sheet Informe Semanal
D3: Reporte Semanal de Proyectos | P3: Fecha corte: | Q3: 46128
G4: 477-PRI24045-000-083-RS-0054 | P4: Emitido : | Q4: =+Q3+1 -> 46129
B6: Proyecto: | C6: EIA Proyecto ACP - Contrato PRI24045 “Ampliación Capacidad Productiva Collahuasi”
B8: Apreciación Gerencial del Proyecto Semanal | J8: Hechos Relevantes de la Semana y Próxima Semana | S8: =900*0.07 -> 63
S15: 
S16: 
B18: Alertas y Oportunidades | S18: 
B19: Área | D19: Alertas | H19: Impacto | L19: Plan de Acción | O19: Responsable | Q19: Plan | R19: Forecast | S19: 
B20: Medio Ambiente y Permisos | C20: 0 | D20: En función de la nueva "Guía para la predicción y evaluación de impactos sobre ecosistemas terrestres" (agosto, 2025), se requiere incorporar mediciones de MPS en el sector cordillera, ductos alto (por Metharme lanata y vegetación azonal) y sector pampa tamarugal. | H20: Posible cuestionamiento de la evaluación de impactos del Proyecto, por falta de antecedentes de línea de base. | L20: 1.- WSP enviará un presupuesto de instalación de MPS de la empresa EMS. 2.-Solicitar a Teck la obtención de datos de MPS. 3.- Instalación de estaciones de monitoreo de MPS en los sectores de las áreas sensibles de flora y vegetación identificadas a través de la línea de base ejecutada. | O20: 1.- WSP 2.- Collahuasi 3.- WSP /Collahuasi | Q20: 1.- mar-2026 2.- abr-2026 3.- dic-2025 4.- jun-2026 | R20: 1.-abr-2026 2.- abr-2026 3.- jun-2026
C21: 0 | D21: Geología, Geomorfología y Riesgo Geológico: Información insuficiente para la elaboración de la línea de base de Geología, Geomorfología y Riesgos Geológicos. | H21: Cuestionamientos por parte de la Autoridad en proceso de tramitación del Proyecto. | L21: 1.- WSP envió la Propuesta técnica y económica sobre las brechas de información para la ldb de GGR (03/02). 2.- Se espera la revisión y definición de la propuesta técnica y económica compartida por WSP. | O21: 1.- WSP 2.- Collahuasi | Q21: 1.- 03-feb-2026 2.- feb-2026 | R21: 1.- 03-feb-2026 2.- abr-2026
C22: 2 | D22: Campaña de áreas pendientes y adicionales de Arqueología: Se necesita definir la fecha de ejecución de la campaña de arqueología para las áreas pendientes y adicionales. | H22: Potencial requerimiento de elaboración, tramitación y ejecución de un FSA 4, lo que podría impactar en el Programa del servicio. | L22: 1.- WSP debe enviar Plan de Trabajo sobre áreas pendientes, una vez contemos con la actualización del Layout del Proyecto, se estima que esta campaña se retomará posterior a la las campañas de pozos de sondeo. | O22: 1.- WSP 2.- WSP | Q22: 1.- 20-mar-2026 2.- 17-abr-2026
C23: -1 | D23: Levantamiento de información para elaborar DIN y PAS 150 | H23: Ejecutar un método para definir y delimitar el BNP cuestionado en etapas de evaluación ambiental | L23: 1.- A la espera de comentarios por parte de Collahuasi sobre el ppt enviada el día viernes 10/04. 2.- Collahuasi debe gestionar reunión con CONAF (vía Lobby) programada para segunda quincena de abril. El objetivo es validar la metodología para la delimitación del BNP. | O23: 1. Collahuasi 2. Collahuasi | Q23: 1.- 22-abr-2026 2.- 13-05-2026
C24: 0 | D24: Atraso de la ejecución de las campañas de Medio Humano y Participación Ciudadana Temprana | H24: Atraso en el avance del Proyecto, que podría pegar en la fecha de ingreso del EIA, ya que corresponden a actividades que se encuentran en la ruta crítica, además involucra el atraso en la elaboración de líneas de base como: - Atractivos Naturales o culturales y sus interacciones | L24: 1.- Se encuentra en proceso de validación la reprogramación del EIA (R2), no obstante, el componente se mantiene en ruta crítica. 2.- Se requiere habilitación por parte de Collahuasi previo a la ejecución de los terrenos. | O24: 1.- Collahuasi 2.- WSP | Q24: 1.- abril-2026 2.- De acuerdo a programa R2
C25: 2 | D25: Seguimiento de los compromisos establecidos durante el proceso de ejecución de los Hitos 4, 8, 9 y 10 | H25: Falta de información relevante para el desarrollo del EIA, debido a ausencia de seguimiento de acciones requeridas para aspectos críticos del proyecto | L25: 1.- Agendar reuniones de seguimiento por componente para revisar el desarrollo del compromiso y fechas de implementación. 2.- Identificar las acciones requeridas en el corto plazo (Abril - Mayo) y enviar correo a Collahuasi. | O25: WSP | Q25: 46101 | R25: 46113
B29: Indicadores de Planificación (Programa del Servicio R1) | F29: Curva "S" del Proyecto
B31: % Av. Real | C31: % Av. Prog. | D31: M
B32: ACUMULADO
B33: =+EPR!L7 -> 0.4473832 | C33: =+'Curva S R1'!BE34/100 -> 0.49978764 | D33: =+B33-C33 -> -0.052404438 | E33: 0
B34: PARCIAL
B35: =+'Curva S R1'!BE35/100 -> 0.0043510811 | C35: =+'Curva S R1'!BE33/100 -> 0.016323917 | D35: =+B35-C35 -> -0.011972836
B37: HH Proyecto | C37: Ganadas | D37: Planificadas | E37: SPI
B38: Semanal | C38: =+'Curva S R1'!BE61 -> 545.73 | D38: =+'Curva S R1'!BE55 -> 2047.4 | E38: =+C38/D38 -> 0.26654782
B39: Acumulado | C39: =+'Curva S R1'!BE62 -> 50288.4 | D39: =+'Curva S R1'!BE56 -> 62685.03 | E39: =+C39/D39 -> 0.80223939
B41: Hitos Relevantes (Incluidos Contractuales)
G53: Motivo Desviación: 1.- Actividades de Gestión del Proyecto (-0,6%): Hasta la fecha se han realizado 17 reuniones técnicas, lo que representa un avance del 23,6% en esta actividad, considerando que el total programado es de 72 reuniones a ejecutarse hasta diciembre de 2026 y llevamos 45 reuniones contractuales, lo que representa un 36% de avance, de un total de 125 reuniones programadas. 2.- Cap. 10 - Plan de cumplimiento de la legislación ambiental aplicable y PAS 119 Pesca investig. Aguas Marinas (-0,1%): La fecha de elaboración de estos documentos fue actualizada en el programa R2 preliminar 3.- Estudio de Olores - (-0,2%): Inicio pendiente a la espera del proyecto definitivo. 4.- Estudios Específicos - levantamiento en terreno solicitud excepcional cuenca 1 y 2, Definición sitios de compensación y/o relocalización (-1,5%): Actividad proyectada para ser ejecutada con posterioridad. 5.- Clima y Meteorología / Calidad del Aire (-0,6%): Atraso en el desarrollo de informes (RA), por falta de antecedentes necesarios para el inicio del documento. 6.- Suelos (-0,1%): Trabajos de terreno iniciará el 21/abr/26. 7.- Animales Silvestres (0,1%): Elaboración y envío de informes sobre campañas estacionales bióticas. 8.- Paisaje (-0,2%): Segunda parte de la campaña ejecutada, inicia elaboración de informe. 9.- Atractivos Naturales o Culturales y sus Interrelaciones (Turismo) (-0,4%): Campaña detenida ya que requiere interacción con operadores turísticos que potencialmente podrían ser parte de alguna comunidad, por lo que se encuentra sujeta a la activación de la campaña de Medio Humano. 10.- Geología, Geomorfología, Riesgos Geológicos y Geomorfológicos (-0,1%): Esta actividad se atrasó en su inicio debido a la falta de información para su elaboración. Se encuentra en desarrollo. 11.- Arqueología (-1,0%): Está pendiente trabajos de terreno arqueología (campaña prospecciones - 3) y el inicio de la ejecución de pozos de sondeo. 12.- Ecosistemas Acuáticos Marinos - Informe (RB) - Recursos hídricos marinos (campaña invierno y verano) (-0,3%): Informe de campañas en desarrollo. 13.- Medio Humano - Estudio Antropológico (por GHPPI) (-2,0%): Los trabajos de Medio Humano se encuentran suspendidos hasta contar con un relato que integre la DIA 3 y el EIA ACP. 14.- Medio Humano - Grupos Humanos no Indígenas (-1,3%): Los trabajos de Medio Humano se encuentran suspendidos hasta contar con un relato que integre la DIA 3 y el EIA ACP. 15.- Caracterización Vial (-0,4%): Terreno detenido por definición de proyecto definitivo 16.- Proceso de Consulta Temprana (PCT) (-1,2%): Esta actividad se encuentra pendiente de reprogramación, sin embargo, se dio inicio a la elaboración de la Estrategia. 17.- Tendencia 5 - Esfuerzos de Terreno Adicional (Aspectos Bióticos), Campaña 2025 / Tendencia 6 - Trazado Alternativo LTE / Tendencia 8 - Control Operacional en Terreno / Tendencia 9 - Brigada Canina / Tendencia 10 Campaña de Verano Área de Estudio / Tendencia N°12 - Campaña Biótica Complementaria Otoño (4,7%): Se incluye tendencias con HH ganadas de tareas ejecutadas a la fecha.
B56: Indicadores de Costos | I56: Tendencias
I65: 1.- Tendencia N°11: Estudio de Capacidad de Carga - Rechazado por CMDIC (01/abr). Se emite TD11 R1 el 10/abr (TRN-000191). En actualización para clarificar cantidad de entregables. Se envía corregida el 16/abr/26. 2.- Tendencia N°12: Campaña Adicional de Otoño - Aprobada el 14/abr/26. 3.- Orden de Cambio N°1: Firmada por representantes legales de WSP en el portal “CloudSigner”. 4.- Tendencia administrativa: Se envió borrador de Tendencia por extensión del servicio el 09/abr/26. 5.- Tendencia 13: Ruta A97B (Biota y Arqueología + Áreas Adicionales Arqueología), emitida el 16/abr/26. 6.- Se incluyen Tendencias Potenciales en el Log de Tendencias con valores aproximados. 7.- Emisión tendencia estaciones MPS
B71: Resumen Entregables
G72: Comentarios:
S81:  | T81: Entrega Estudio Antropológicos, incluyendo fuentes primarias:
B82: (*) Se actualiza cantidad de entregables de acuerdo a nueva línea de base | P82: FIRMA | S82: o | T82: GHPPI Segovia-Jauregui (WSP).
S83: o | T83: GHPPI Familia Vicentelo de Tamentica (WSP).
S84:  | T84: Avance fuentes secundarias línea base medio humano.
S85: o | T85: Recorrido GHPPI Chusquina-Huari Plaza (GEO).
T86: Avance fuentes secundarias línea base medio humano.

Sheet EPR
K3: Ppto HH | L3: % Avance | N3: HH Ganadas
H4: Contrato Original | K4: =SUM(K11:K659)-27 -> 117644.55 | L4: =+N4/K4 -> 0.36773751 | N4: =SUM(N11:N659) -> 43262.313 | Q4: Data Date | R4: =+'Informe Semanal'!$Q$3 -> 46128
H5: Contrato + Tend | K5: =+K660+L724 -> 125408.55 | L5: =+N5/K5 -> 0.40100881 | N5: =+N660+N724 -> 50289.933
H6: PROGRAMA_R1 | K6: =+K5+15 -> 125423.55 | L6: =+N6/K6 -> 0.40096085 | N6: =+N5 -> 50289.933 | R6: 0.4 | S6: 0.2 | T6: 0.1 | U6: 0.2 | V6: 0.1 | X6: 0.4 | Y6: 0.2 | Z6: 0.1 | AA6: 0 | AB6: 0 | AC6: 0.2 | AD6: 0.1 | AF6: 0.4 | AG6: 0.2 | AH6: 0.1 | AI6: 0.2 | AJ6: 0.1
H7: PR1+TD5+6+8+9+10+12 | K7: =+K6+M871 -> 146397.95 | L7: =+N7/K7 -> 0.4473832 | N7: =+N6+N871 -> 65495.983
H9: Tipo Entregable | Q9: PLANIFICADO PROGRAMA REV_1 | W9: REAL | AE9: FORECAST
B10: ITEM | C10: Origen Programa P6 (Activity ID) Rev.0 | D10: Status (Rev.0) | E10: Cód. CMDIC | F10: DESCRIPCIÓN | G10: DISCIPLINA | H10: DOC | I10: PLA | J10: ACT | K10: HH CO | L10: HH TD | M10: HH Total Ppto | N10: HH Total Ganadas | O10: % Avance Programado | P10: % Avance Real | Q10: Inicio | R10: Emisión RevA | S10: Emisión RevB | T10: Aprobación RevB | U10: Emisión RevP | V10: Aprobación RevP (Término Actividades) | W10: Inicio | X10: Emisión RevA | Y10: Emisión RevB | Z10: Aprobación RevB | AA10: Emisión RevC | AB10: Aprobación RevC | AC10: Emisión RevP | AD10: Aprobación RevP (Término Actividades) | AE10: Inicio | AF10: Emisión RevA | AG10: Emisión RevB | AH10: Aprobación RevB | AI10: Emisión RevP | AJ10: Aprobación RevP (Término Actividades) | AK10: 44620 | AL10: =+AK10+7 -> 44627 | AM10: =+AL10+7 -> 44634 | AN10: =+AM10+7 -> 44641 | AO10: =+AN10+7 -> 44648 | AP10: =+AO10+7 -> 44655 | AQ10: =+AP10+7 -> 44662 | AR10: =+AQ10+7 -> 44669 | AS10: =+AR10+7 -> 44676 | ... CP10: =+CO10+7 -> 45019
B11: 1 | F11: GENERAL (Activ. de Coodinación y Supervisión)
B12: 1.1 | F12: ACTIVIDADES | M12: =+K12+L12 -> 0 | N12: =+M12*P12 -> 0
A13: =+TRIM(C13) -> 477-010-40-0001 | B13: 1.1.1 | C13: 477-010-40-0001 | D13: Semanal (35 de 49) | E13: 477-PRI24045-000-010-ME-1001 a 1049 | F13: Reunión Ejecutiva | J13: 1 | K13: 294 | M13: =+K13+L13 -> 294 | N13: =+M13*P13 -> 210 | O13: =IFERROR(VLOOKUP(C13,'Programa P6 Excel R1'!$B$4:$N$1142,8,FALSE),"-") -> 0.646 | P13: =35/49 -> 0.71428571 | Q13: 45827 | V13: 46295 | W13: 45817 | AJ13: 46295
A14: =+TRIM(C14) -> 477-010-40-0002 | B14: 1.1.2 | C14: 477-010-40-0002 | D14: Semanal (45 de 125) | E14: 477-PRI24045-000-035-ME-0001 a 0125 | F14: Reunión Contractual Semanal | J14: 1 | K14: 1000 | M14: =+K14+L14 -> 1000 | N14: =+M14*P14 -> 360 | O14: =IFERROR(VLOOKUP(C14,'Programa P6 Excel R1'!$B$4:$N$1142,8,FALSE),"-") -> 0.4185 | P14: =45/125 -> 0.36 | Q14: 45751 | V14: 46659 | W14: 45819 | AJ14: 46659
A15: =+TRIM(C15) -> 477-010-40-0003 | B15: 1.1.3 | C15: 477-010-40-0003 | D15: Semanal (17 de 72) | E15: 477-PRI24045-000-010-ME-2001 a 2072 | F15: Reunión Técnica | J15: 1 | K15: 1383.84 | M15: =+K15+L15 -> 1383.84 | N15: =+M15*P15 -> 326.74 | O15: =IFERROR(VLOOKUP(C15,'Programa P6 Excel R1'!$B$4:$N$1142,8,FALSE),"-") -> 0.5968 | P15: =17/72 -> 0.23611111 | Q15: 45751 | V15: 46387 | W15: 45819 | AJ15: 46387
A16: =+TRIM(C16) -> 477-010-40-0004 | B16: 1.1.4 | C16: 477-010-40-0004 | E16: 477-PRI24045-000-010-ME-3001 a 3020 | F16: Reuniones con autoridades | J16: 1 | K16: 490 | M16: =+K16+L16 -> 490 | N16: =+M16*P16 -> 0 | O16: =IFERROR(VLOOKUP(C16,'Programa P6 Excel R1'!$B$4:$N$1142,8,FALSE),"-") -> 0.2533 | P16: 0 | Q16: 46048 | V16: 46378 | AE16: 46048 | AJ16: 46378
A17: =+TRIM(C17) -> 477-010-40-0005 | B17: 1.1.5 | C17: 477-010-40-0005 | D17: Semanal (54 de 125) | E17: 477-PRI24045-000-083-RS-0001 a 0125 | F17: Reportes Semanales | H17: 1 | K17: 2125 | M17: =+K17+L17 -> 2125 | N17: =+M17*P17 -> 918 | O17: =IFERROR(VLOOKUP(C17,'Programa P6 Excel R1'!$B$4:$N$1142,8,FALSE),"-") -> 0.4072 | P17: =54/125 -> 0.432 | Q17: 45769 | V17: 46659 | W17: 45821 | AJ17: 46659
B18: 1.1.6 | F18: Programa de Ejecución del Servicio | O18: =IFERROR(VLOOKUP(C18,'Programa P6 Excel R1'!$B$4:$N$1142,8,FALSE),"-") -> - | Q18: - | V18: - | AE18: - | AJ18: -
A19: =+TRIM(C19) -> 477-010-40-0006 | B19: 1.1.7 | C19: 477-010-40-0006 | D19: Rev.0 | E19: 477-PRI24045-000-083-PG-0001 | F19: Programa de Ejecución del Servicio | H19: 1 | K19: 303 | M19: =+K19+L19 -> 303 | N19: =+M19*P19 -> 303 | O19: =IFERROR(VLOOKUP(C19,'Programa P6 Excel R1'!$B$4:$N$1142,8,FALSE),"-") -> 1 | P19: 1 | Q19: 45751 | V19: 45819 | W19: 45751 | X19: 45771 | Y19: 45771 | Z19: - | AA19: 45793 | AB19: 45803 | AC19: 45820 | AD19: 45820
A20: =+TRIM(C20) -> 477-010-40-0007 | B20: 1.1.8 | C20: 477-010-40-0007 | D20: En desarrollo | F20: Control de Documentos | J20: 1 | K20: 1425 | M20: =+K20+L20 -> 1425 | N20: =+M20*P20 -> 842.46 | O20: =IFERROR(VLOOKUP(C20,'Programa P6 Excel R1'!$B$4:$N$1142,8,FALSE),"-") -> 0.5912 | P20: =+'Programa P6 Excel R1'!J39 -> 0.5912 | Q20: 45761 | V20: 46387 | W20: 45751 | AE20: 45761 | AJ20: 46387
B21: 1.1.9 | F21: Acreditación | O21: =IFERROR(VLOOKUP(C21,'Programa P6 Excel R1'!$B$4:$N$1142,8,FALSE),"-") -> - | Q21: - | V21: - | AE21: - | AJ21: -
A22: =+TRIM(C22) -> 477-010-40-0008 | B22: 1.1.10 | C22: 477-010-40-0008 | D22: En desarrollo | F22: Carpeta de arranque | J22: 1 | K22: 270 | M22: =+K22+L22 -> 270 | N22: =+M22*P22 -> 249.075 | O22: =IFERROR(VLOOKUP(C22,'Programa P6 Excel R1'!$B$4:$N$1142,8,FALSE),"-") -> 0.9225 | P22: =+'Programa P6 Excel R1'!J40 -> 0.9225 | Q22: 45751 | V22: 46161 | W22: 45754 | AJ22: 46161
A23: =+TRIM(C23) -> 477-010-40-0009 | B23: 1.1.11 | C23: 477-010-40-0009 | D23: En desarrollo | F23: Carpeta de arranque SC | J23: 1 | K23: 415 | M23: =+K23+L23 -> 415 | N23: =+M23*P23 -> 382.8375 | O23: =IFERROR(VLOOKUP(C23,'Programa P6 Excel R1'!$B$4:$N$1142,8,FALSE),"-") -> 0.9225 | P23: =+P22 -> 0.9225 | Q23: 45751 | V23: 46161 | W23: 45754 | AJ23: 46161
A24: =+TRIM(C24) -> 477-010-40-0010 | B24: 1.1.12 | C24: 477-010-40-0010 | D24: En desarrollo | F24: Acreditación de personas | J24: 1 | K24: 1527 | M24: =+K24+L24 -> 1527 | N24: =+M24*P24 -> 1408.6575 | O24: =IFERROR(VLOOKUP(C24,'Programa P6 Excel R1'!$B$4:$N$1142,8,FALSE),"-") -> 0.9225 | P24: =+P23 -> 0.9225 | Q24: 45751 | V24: 46161 | W24: 45754 | AJ24: 46161
A25: =+TRIM(C25) -> 477-010-40-0011 | B25: 1.1.13 | C25: 477-010-40-0011 | D25: En desarrollo | F25: Acreditación vehículos | J25: 1 | K25: 782 | M25: =+K25+L25 -> 782 | N25: =+M25*P25 -> 721.395 | O25: =IFERROR(VLOOKUP(C25,'Programa P6 Excel R1'!$B$4:$N$1142,8,FALSE),"-") -> 0.9225 | P25: =+P24 -> 0.9225 | Q25: 45751 | V25: 46161 | W25: 45754 | AJ25: 46161
A26: =+TRIM(C26) -> 477-010-40-0012 | B26: 1.1.14 | C26: 477-010-40-0012 | D26: Rev.P1 (emitido) | E26: 477-PRI24045-000-010-EL-0001 | F26: Listado de Entregables | H26: 1 | K26: 60 | M26: =+K26+L26 -> 60 | N26: =+M26*P26 -> 60 | O26: =IFERROR(VLOOKUP(C26,'Programa P6 Excel R1'!$B$4:$N$1142,8,FALSE),"-") -> 1 | P26: 1 | Q26: 45751 | V26: 45814 | W26: 45751 | X26: 45758 | Y26: 45758 | Z26: 45769 | AA26: - | AB26: - | AC26: P 30-04-2025 P1 06/06/25 | AD26: 45821
A27: =+TRIM(C27) -> 477-010-40-0013 | B27: 1.1.15 | C27: 477-010-40-0013 | E27: 477-PRI24045-000-010-ME-4001 a 4010 | F27: Talleres (accionistas, CMDIC y GMAP) | J27: 1 | K27: 1280 | M27: =+K27+L27 -> 1280 | N27: =+M27*P27 -> 0 | O27: =+'Programa P6 Excel R1'!I45 -> 0.1 | P27: 0 | Q27: 46120 | V27: 46126 | AE27: 46120 | AJ27: 46126
A28: =+TRIM(C28) -> 477-010-40-0014 | B28: 1.1.16 | C28: 477-010-40-0014 | E28: 477-PRI24045-000-010-ME-5001 a 5010 | F28: Talleres de definición estratégicas | J28: 1 | K28: 1230 | M28: =+K28+L28 -> 1230 | N28: =+M28*P28 -> 0 | O28: =+'Programa P6 Excel R1'!I56 -> 0 | P28: 0 | Q28: 46134 | V28: 46140 | AE28: 46134 | AJ28: 46140
M29: =+K29+L29 -> 0 | N29: =+M29*P29 -> 0
B30: 2 | F30: Elaboración EIA | M30: =+K30+L30 -> 0 | N30: =+M30*P30 -> 0
A31: =+TRIM(C31) -> 477-010-40-0019 | B31: 2.1 | C31: 477-010-40-0019 | D31: Rev.P (Aprobado) | E31: 477-PRI24045-001-010-IN-0001 | F31: Definición de los aspectos críticos del Proyecto y estrategia para abordarlos | H31: 1 | K31: 832 | M31: =+K31+L31 -> 832 | N31: =+M31*P31 -> 832 | O31: =IFERROR(VLOOKUP(E31,'Programa P6 Excel R1'!$A$4:$N$1135,9,FALSE),"-") -> 1 | P31: 1 | Q31: 45775 | R31: =+S31-7 -> 45875 | S31: 45882 | T31: 45895 | U31: 45904 | V31: 45960 | W31: 45796 | X31: 45806 | Y31: 45882 | Z31: 45895 | AC31: 45904 | AD31: 45989
A32: =+TRIM(C32) -> 477-010-40-0023 | B32: 2.2 | C32: 477-010-40-0023 | D32: Rev.P (Aprobado) | E32: 477-PRI24045-001-010-IN-0002 | F32: Brechas de información existente | H32: 1 | K32: 1663 | M32: =+K32+L32 -> 1663 | N32: =+M32*P32 -> 1663 | O32: =IFERROR(VLOOKUP(E32,'Programa P6 Excel R1'!$A$4:$N$1135,9,FALSE),"-") -> 1 | P32: 1 | Q32: 45761 | R32: =+S32-7 -> 45777 | S32: 45784 | T32: 45847 | U32: 45855 | V32: 45861 | W32: 45775 | X32: 45782 | Y32: 45784 | Z32: - | AA32: 45803 | AC32: 45855 | AD32: 45861
A33: =+TRIM(C33) -> 477-010-40-0027 | B33: 2.3 | C33: 477-010-40-0027 | D33: Rev.P (Aprobado) | E33: 477-PRI24045-001-010-IN-0003 | F33: Análisis y verificación propuesta de gestión compromisos ambientales instrumentos anteriores | H33: 1 | K33: 876 | M33: =+K33+L33 -> 876 | N33: =+M33*P33 -> 876 | O33: =IFERROR(VLOOKUP(E33,'Programa P6 Excel R1'!$A$4:$N$1135,9,FALSE),"-") -> 1 | P33: 1 | Q33: 45804 | R33: =+S33-7 -> 45884 | S33: 45891 | T33: 45898 | U33: 45909 | V33: 45960 | W33: 45800 | X33: =+Y33-7 -> 45884 | Y33: 45891 | Z33: 45898 | AC33: 45909 | AD33: 46008
A34: =+TRIM(C34) -> 477-010-40-0031 | B34: 2.4 | C34: 477-010-40-0031 | D34: Rev.P (Aprobado) | E34: 477-PRI24045-001-010-IN-0004 | F34: Identificación preliminar de los Impactos Significativos y estrategia para abordarlos | H34: 1 | K34: 908.5 | M34: =+K34+L34 -> 908.5 | N34: =+M34*P34 -> 908.5 | O34: =IFERROR(VLOOKUP(E34,'Programa P6 Excel R1'!$A$4:$N$1135,9,FALSE),"-") -> 1 | P34: =+'Programa P6 Excel R1'!J87 -> 1 | Q34: 45817 | R34: =+S34-7 -> 45903 | S34: 45910 | T34: 45960 | U34: 45968 | V34: 45975 | W34: 45800 | X34: 45902 | Y34: 45910 | Z34: 45964 | AC34: 45981 | AD34: 46063
B35: 2.5 | F35: Elaboración Capitulos | K35: 0 | M35: =+K35+L35 -> 0 | N35: =+M35*P35 -> 0 | O35: 0 | P35: 0
A36: =+TRIM(C36) -> 477-010-40-0035 | B36: 2.5.1 | C36: 477-010-40-0035 | E36: 477-PRI24045-001-010-IN-0100 | F36: Resumen Ejecutivo | H36: 1 | K36: 196 | M36: =+K36+L36 -> 196 | N36: =+M36*P36 -> 0 | O36: 0 | P36: 0 | Q36: 46317 | R36: =+S36-7 -> 46338 | S36: 46345 | T36: 46352 | U36: 46359 | V36: 46367 | AE36: 46317 | AF36: =+AG36-7 -> 46338 | AG36: 46345 | AH36: 46352 | AI36: 46359 | AJ36: 46367
A37: =+TRIM(C37) -> 477-010-40-0039 | B37: 2.5.2 | C37: 477-010-40-0039 | E37: 477-PRI24045-001-010-IN-0101 | F37: Cap. 1 - Descripción de Proyecto | H37: 1 | K37: 1902 | M37: =+K37+L37 -> 1902 | N37: =+M37*P37 -> 0 | O37: 0 | P37: 0 | Q37: 46216 | R37: =+S37-7 -> 46254 | S37: 46261 | T37: 46268 | U37: 46275 | V37: 46282 | AE37: 46216 | AF37: =+AG37-7 -> 46254 | AG37: 46261 | AH37: 46268 | AI37: 46275 | AJ37: 46282
A38: =+TRIM(C38) -> 477-010-40-0043 | B38: 2.5.3 | C38: 477-010-40-0043 | E38: 477-PRI24045-001-010-IN-0201 | F38: Cap. 2 - Determinación y Justificación Área de Influencia | H38: 1 | K38: 1119.5 | M38: =+K38+L38 -> 1119.5 | N38: =+M38*P38 -> 0 | O38: 0 | P38: 0 | Q38: 46287 | R38: =+S38-7 -> 46322 | S38: 46329 | T38: 46337 | U38: 46345 | V38: 46352 | AE38: 46287 | AF38: =+AG38-7 -> 46322 | AG38: 46329 | AH38: 46337 | AI38: 46345 | AJ38: 46352
A39: =+TRIM(C39) -> 477-010-40-0047 | B39: 2.5.4 | C39: 477-010-40-0047 | E39: 477-PRI24045-001-010-IN-0301 | F39: Cap. 3 - Línea de Base Ambiental | H39: 1 | K39: 314 | M39: =+K39+L39 -> 314 | N39: =+M39*P39 -> 0 | O39: 0 | P39: 0 | Q39: 46287 | R39: =+S39-7 -> 46322 | S39: 46329 | T39: 46342 | U39: 46352 | V39: 46365 | AE39: 46287 | AF39: =+AG39-7 -> 46322 | AG39: 46329 | AH39: 46342 | AI39: 46352 | AJ39: 46365
A40: =+TRIM(C40) -> 477-010-40-0051 | B40: 2.5.5 | C40: 477-010-40-0051 | E40: 477-PRI24045-001-010-IN-0401 | F40: Cap. 4 - Predicción y evaluación de impactos | H40: 1 | K40: 2963 | M40: =+K40+L40 -> 2963 | N40: =+M40*P40 -> 0 | O40: 0 | P40: 0 | Q40: 46287 | R40: =+S40-7 -> 46309 | S40: 46316 | T40: 46329 | U40: 46342 | V40: 46352 | AE40: 46287 | AF40: =+AG40-7 -> 46309 | AG40: 46316 | AH40: 46329 | AI40: 46342 | AJ40: 46352
A41: =+TRIM(C41) -> 477-010-40-0055 | B41: 2.5.6 | C41: 477-010-40-0055 | E41: 477-PRI24045-001-010-IN-0501 | F41: Cap. 5 - Descripción pormenorizada ECC Art.11 | H41: 1 | K41: 331 | M41: =+K41+L41 -> 331 | N41: =+M41*P41 -> 0 | O41: 0 | P41: 0 | Q41: 46287 | R41: =+S41-7 -> 46318 | S41: 46325 | T41: 46336 | U41: 46344 | V41: 46352 | AE41: 46287 | AF41: =+AG41-7 -> 46318 | AG41: 46325 | AH41: 46336 | AI41: 46344 | AJ41: 46352
A42: =+TRIM(C42) -> 477-010-40-0059 | B42: 2.5.7 | C42: 477-010-40-0059 | E42: 477-PRI24045-001-010-IN-0601 | F42: Cap. 6 - Potenciales riesgos para la salud de la población | H42: 1 | K42: 72 | M42: =+K42+L42 -> 72 | N42: =+M42*P42 -> 0 | Q42: 46216 | R42: =+S42-7 -> 46247 | S42: 46254 | T42: 46261 | U42: 46268 | V42: 46275 | AE42: 46216 | AF42: =+AG42-7 -> 46247 | AG42: 46254 | AH42: 46261 | AI42: 46268 | AJ42: 46275
A43: =+TRIM(C43) -> 477-010-40-0063 | B43: 2.5.8 | C43: 477-010-40-0063 | E43: 477-PRI24045-001-010-IN-0701 | F43: Cap. 7 - Plan de medidas de mitigación, reparación y compensación | H43: 1 | K43: 2021 | M43: =+K43+L43 -> 2021 | N43: =+M43*P43 -> 0 | O43: 0 | P43: 0 | Q43: 46287 | R43: =+S43-7 -> 46322 | S43: 46329 | T43: 46337 | U43: 46345 | V43: 46352 | AE43: 46287 | AF43: =+AG43-7 -> 46322 | AG43: 46329 | AH43: 46337 | AI43: 46345 | AJ43: 46352
A44: =+TRIM(C44) -> 477-010-40-0067 | B44: 2.5.9 | C44: 477-010-40-0067 | D44: Iniciado | E44: 477-PRI24045-001-010-IN-0801 | F44: Cap. 8 - Plan de prevención de contingencias y de emergencias | H44: 1 | K44: 69 | M44: =+K44+L44 -> 69 | N44: =+M44*P44 -> 4.14 | O44: =+'Programa P6 Excel R1'!I133 -> 0.1059 | P44: =+'Programa P6 Excel R1'!J133 -> 0.06 | Q44: 46112 | R44: =+S44-7 -> 46204 | S44: 46211 | T44: 46218 | U44: 46226 | V44: 46233 | W44: =+'Programa P6 Excel R1'!G134 -> 46122 | AF44: =+AG44-7 -> 46216 | AG44: =+'Programa P6 Excel R1'!H134 -> 46223 | AH44: =+'Programa P6 Excel R1'!H135 -> 46230 | AI44: =+'Programa P6 Excel R1'!H136 -> 46237 | AJ44: =+'Programa P6 Excel R1'!H137 -> 46244
A45: =+TRIM(C45) -> 477-010-40-0071 | B45: 2.5.10 | C45: 477-010-40-0071 | E45: 477-PRI24045-001-010-IN-0901 | F45: Cap. 9 - Plan de seguimiento de las variables ambientales relevantes | H45: 1 | K45: 1254 | M45: =+K45+L45 -> 1254 | N45: =+M45*P45 -> 0 | O45: 0 | P45: 0 | Q45: 46317 | R45: =+S45-7 -> 46338 | S45: 46345 | T45: 46352 | U45: 46359 | V45: 46367 | AE45: 46317 | AF45: =+AG45-7 -> 46338 | AG45: 46345 | AH45: 46352 | AI45: 46359 | AJ45: 46367
A46: =+TRIM(C46) -> 477-010-40-0075 | B46: 2.5.11 | C46: 477-010-40-0075 | E46: 477-PRI24045-001-010-IN-1001 | F46: Cap. 10 - Plan de cumplimiento de la legislación ambiental aplicable y PAS | H46: 1 | K46: 156 | M46: =+K46+L46 -> 156 | N46: =+M46*P46 -> 0 | O46: =+'Programa P6 Excel R1'!I143 -> 0.0144 | Q46: 46112 | R46: =+S46-7 -> 46129 | S46: 46136 | T46: 46150 | U46: 46162 | V46: 46176 | AE46: 46112 | AF46: =+AG46-7 -> 46129 | AG46: 46136 | AH46: 46150 | AI46: 46162 | AJ46: 46176
A47: =+TRIM(C47) -> 477-010-40-0079 | B47: 2.5.11.1 | C47: 477-010-40-0079 | E47: 477-PRI24045-001-010-IN-1011 | F47: PAS114 Instalación terminal marítimo | H47: 1 | K47: 286 | M47: =+K47+L47 -> 286 | N47: =+M47*P47 -> 0 | O47: 0 | P47: 0 | Q47: 46216 | R47: =+S47-7 -> 46237 | S47: 46244 | T47: 46251 | U47: 46258 | V47: 46265 | AE47: 46216 | AF47: =+AG47-7 -> 46237 | AG47: 46244 | AH47: 46251 | AI47: 46258 | AJ47: 46265
A48: =+TRIM(C48) -> 477-010-40-0083 | B48: 2.5.11.2 | C48: 477-010-40-0083 | E48: 477-PRI24045-001-010-IN-1012 | F48: PAS115 Introducir material a aguas | H48: 1 | K48: 216 | M48: =+K48+L48 -> 216 | N48: =+M48*P48 -> 0 | O48: 0 | P48: 0 | Q48: 46245 | R48: =+S48-7 -> 46265 | S48: 46272 | T48: 46279 | U48: 46287 | V48: 46294 | AE48: 46245 | AF48: =+AG48-7 -> 46265 | AG48: 46272 | AH48: 46279 | AI48: 46287 | AJ48: 46294
A49: =+TRIM(C49) -> 477-010-40-0087 | B49: 2.5.11.3 | C49: 477-010-40-0087 | E49: 477-PRI24045-001-010-IN-1013 | F49: PAS119 Pesca investig. Aguas Marinas | H49: 1 | K49: 136 | M49: =+K49+L49 -> 136 | N49: =+M49*P49 -> 0 | O49: =+'Programa P6 Excel R1'!I158 -> 0.06 | P49: 0 | Q49: 46127 | R49: =+S49-7 -> 46148 | S49: 46155 | T49: 46162 | U49: 46170 | V49: 46177 | AE49: 46127 | AF49: =+AG49-7 -> 46148 | AG49: 46155 | AH49: 46162 | AI49: 46170 | AJ49: 46177
A50: =+TRIM(C50) -> 477-010-40-0091 | B50: 2.5.11.4 | C50: 477-010-40-0091 | E50: 477-PRI24045-001-010-IN-1014 | F50: PAS119 Pesca investig. Aguas Continentales | H50: 1 | K50: 125 | M50: =+K50+L50 -> 125 | N50: =+M50*P50 -> 0 | O50: 0 | P50: 0 | Q50: 46238 | R50: =+S50-7 -> 46273 | S50: 46280 | T50: 46288 | U50: 46295 | V50: 46302 | AE50: 46238 | AF50: =+AG50-7 -> 46273 | AG50: 46280 | AH50: 46288 | AI50: 46295 | AJ50: 46302
A51: =+TRIM(C51) -> 477-010-40-0095 | B51: 2.5.11.5 | C51: 477-010-40-0095 | E51: 477-PRI24045-001-010-IN-1015 | F51: PAS126 Instalación Manejo lodos PTAS | H51: 1 | K51: 151 | M51: =+K51+L51 -> 151 | N51: =+M51*P51 -> 0 | O51: 0 | P51: 0 | Q51: 46216 | R51: =+S51-7 -> 46234 | S51: 46241 | T51: 46248 | U51: 46255 | V51: 46262 | AE51: 46216 | AF51: =+AG51-7 -> 46234 | AG51: 46241 | AH51: 46248 | AI51: 46255 | AJ51: 46262
A52: =+TRIM(C52) -> 477-010-40-0099 | B52: 2.5.11.6 | C52: 477-010-40-0099 | E52: 477-PRI24045-001-010-IN-1016 | F52: PAS132 Arqueología | H52: 1 | K52: 158 | M52: =+K52+L52 -> 158 | N52: =+M52*P52 -> 0 | Q52: 46216 | R52: =+S52-7 -> 46245 | S52: 46252 | T52: 46259 | U52: 46266 | V52: 46273 | AE52: 46216 | AF52: =+AG52-7 -> 46245 | AG52: 46252 | AH52: 46259 | AI52: 46266 | AJ52: 46273
A53: =+TRIM(C53) -> 477-010-40-0103 | B53: 2.5.11.7 | C53: 477-010-40-0103 | E53: 477-PRI24045-001-010-IN-1017 | F53: PAS132 Paleontología | H53: 1 | K53: 54 | M53: =+K53+L53 -> 54 | N53: =+M53*P53 -> 0 | O53: 0 | P53: 0 | Q53: 46216 | R53: =+S53-7 -> 46245 | S53: 46252 | T53: 46259 | U53: 46266 | V53: 46273 | AE53: 46216 | AF53: =+AG53-7 -> 46245 | AG53: 46252 | AH53: 46259 | AI53: 46266 | AJ53: 46273
A54: =+TRIM(C54) -> 477-010-40-0107 | B54: 2.5.11.8 | C54: 477-010-40-0107 | E54: 477-PRI24045-001-010-IN-1018 | F54: PAS135 Depósitos de Relave | H54: 1 | K54: 193 | M54: =+K54+L54 -> 193 | N54: =+M54*P54 -> 0 | O54: 0 | P54: 0 | Q54: 46216 | R54: =+S54-7 -> 46281 | S54: 46288 | T54: 46295 | U54: 46302 | V54: 46310 | AE54: 46216 | AF54: =+AG54-7 -> 46281 | AG54: 46288 | AH54: 46295 | AI54: 46302 | AJ54: 46310
A55: =+TRIM(C55) -> 477-010-40-0111 | B55: 2.5.11.9 | C55: 477-010-40-0111 | E55: 477-PRI24045-001-010-IN-1019 | F55: PAS136 Bot. estériles o acumulación mineral | H55: 1 | K55: 193 | M55: =+K55+L55 -> 193 | N55: =+M55*P55 -> 0 | O55: 0 | P55: 0 | Q55: 46246 | R55: =+S55-7 -> 46311 | S55: 46318 | T55: 46325 | U55: 46332 | V55: 46339 | AE55: 46246 | AF55: =+AG55-7 -> 46311 | AG55: 46318 | AH55: 46325 | AI55: 46332 | AJ55: 46339
A56: =+TRIM(C56) -> 477-010-40-0115 | B56: 2.5.11.10 | C56: 477-010-40-0115 | E56: 477-PRI24045-001-010-IN-1020 | F56: PAS137 Plan de Cierre | H56: 1 | K56: 193 | M56: =+K56+L56 -> 193 | N56: =+M56*P56 -> 0 | O56: 0 | P56: 0 | Q56: 46216 | R56: =+S56-7 -> 46281 | S56: 46288 | T56: 46295 | U56: 46302 | V56: 46310 | AE56: 46216 | AF56: =+AG56-7 -> 46281 | AG56: 46288 | AH56: 46295 | AI56: 46302 | AJ56: 46310
A57: =+TRIM(C57) -> 477-010-40-0119 | B57: 2.5.11.11 | C57: 477-010-40-0119 | E57: 477-PRI24045-001-010-IN-1021 | F57: PAS138 PTAS | H57: 1 | K57: 156 | M57: =+K57+L57 -> 156 | N57: =+M57*P57 -> 0 | O57: 0 | P57: 0 | Q57: 46216 | R57: =+S57-7 -> 46281 | S57: 46288 | T57: 46295 | U57: 46302 | V57: 46310 | AE57: 46216 | AF57: =+AG57-7 -> 46281 | AG57: 46288 | AH57: 46295 | AI57: 46302 | AJ57: 46310
A58: =+TRIM(C58) -> 477-010-40-0123 | B58: 2.5.11.12 | C58: 477-010-40-0123 | E58: 477-PRI24045-001-010-IN-1022 | F58: PAS139 Residuos industriales o mineros | H58: 1 | K58: 176 | M58: =+K58+L58 -> 176 | N58: =+M58*P58 -> 0 | O58: 0 | P58: 0 | Q58: 46245 | R58: =+S58-7 -> 46310 | S58: 46317 | T58: 46324 | U58: 46331 | V58: 46338 | AE58: 46245 | AF58: =+AG58-7 -> 46310 | AG58: 46317 | AH58: 46324 | AI58: 46331 | AJ58: 46338
A59: =+TRIM(C59) -> 477-010-40-0127 | B59: 2.5.11.13 | C59: 477-010-40-0127 | E59: 477-PRI24045-001-010-IN-1023 | F59: PAS140 Residuos no peligrosos | H59: 1 | K59: 151 | M59: =+K59+L59 -> 151 | N59: =+M59*P59 -> 0 | O59: 0 | P59: 0 | Q59: 46216 | R59: =+S59-7 -> 46281 | S59: 46288 | T59: 46295 | U59: 46302 | V59: 46310 | AE59: 46216 | AF59: =+AG59-7 -> 46281 | AG59: 46288 | AH59: 46295 | AI59: 46302 | AJ59: 46310
A60: =+TRIM(C60) -> 477-010-40-0131 | B60: 2.5.11.14 | C60: 477-010-40-0131 | E60: 477-PRI24045-001-010-IN-1024 | F60: PAS141 Relleno Sanitario | H60: 1 | K60: 186 | M60: =+K60+L60 -> 186 | N60: =+M60*P60 -> 0 | Q60: 46216 | R60: =+S60-7 -> 46281 | S60: 46288 | T60: 46295 | U60: 46302 | V60: 46310 | AE60: 46216 | AF60: =+AG60-7 -> 46281 | AG60: 46288 | AH60: 46295 | AI60: 46302 | AJ60: 46310
A61: =+TRIM(C61) -> 477-010-40-0135 | B61: 2.5.11.15 | C61: 477-010-40-0135 | E61: 477-PRI24045-001-010-IN-1025 | F61: PAS142 Residuos Peligrosos | H61: 1 | K61: 151 | M61: =+K61+L61 -> 151 | N61: =+M61*P61 -> 0 | O61: 0 | P61: 0 | Q61: 46216 | R61: =+S61-7 -> 46281 | S61: 46288 | T61: 46295 | U61: 46302 | V61: 46310 | AE61: 46216 | AF61: =+AG61-7 -> 46281 | AG61: 46288 | AH61: 46295 | AI61: 46302 | AJ61: 46310
A62: =+TRIM(C62) -> 477-010-40-0139 | B62: 2.5.11.16 | C62: 477-010-40-0139 | E62: 477-PRI24045-001-010-IN-1026 | F62: PAS146 Caza o captura de fauna (vertebrados) | H62: 1 | K62: 104 | M62: =+K62+L62 -> 104 | N62: =+M62*P62 -> 0 | O62: 0 | P62: 0 | Q62: 46189 | R62: =+S62-7 -> 46254 | S62: 46261 | T62: 46268 | U62: 46275 | V62: 46282 | AE62: 46189 | AF62: =+AG62-7 -> 46254 | AG62: 46261 | AH62: 46268 | AI62: 46275 | AJ62: 46282
A63: =+TRIM(C63) -> 477-010-40-0143 | B63: 2.5.11.17 | C63: 477-010-40-0143 | E63: 477-PRI24045-001-010-IN-1027 | F63: PAS150 - Bosque de preservación | H63: 1 | K63: 385 | M63: =+K63+L63 -> 385 | N63: =+M63*P63 -> 0 | O63: 0 | P63: 0 | Q63: 46251 | R63: =+S63-7 -> 46316 | S63: 46323 | T63: 46336 | U63: 46349 | V63: 46360 | AE63: 46251 | AF63: =+AG63-7 -> 46316 | AG63: 46323 | AH63: 46336 | AI63: 46349 | AJ63: 46360
A64: =+TRIM(C64) -> 477-010-40-0147 | B64: 2.5.11.18 | C64: 477-010-40-0147 | E64: 477-PRI24045-001-010-IN-1028 | F64: PAS151 - Formaciones Xerofíticas | H64: 1 | K64: 156 | M64: =+K64+L64 -> 156 | N64: =+M64*P64 -> 0 | O64: 0 | P64: 0 | Q64: 46216 | R64: =+S64-7 -> 46281 | S64: 46288 | T64: 46295 | U64: 46302 | V64: 46310 | AE64: 46216 | AF64: =+AG64-7 -> 46281 | AG64: 46288 | AH64: 46295 | AI64: 46302 | AJ64: 46310
A65: =+TRIM(C65) -> 477-010-40-0151 | B65: 2.5.11.19 | C65: 477-010-40-0151 | E65: 477-PRI24045-001-010-IN-1029 | F65: PAS155 Nuevo sistema transporte relaves | H65: 1 | K65: 184 | M65: =+K65+L65 -> 184 | N65: =+M65*P65 -> 0 | O65: 0 | P65: 0 | Q65: 46216 | R65: =+S65-7 -> 46281 | S65: 46288 | T65: 46295 | U65: 46302 | V65: 46310 | AE65: 46216 | AF65: =+AG65-7 -> 46281 | AG65: 46288 | AH65: 46295 | AI65: 46302 | AJ65: 46310
A66: =+TRIM(C66) -> 477-010-40-0155 | B66: 2.5.11.20 | C66: 477-010-40-0155 | E66: 477-PRI24045-001-010-IN-1030 | F66: PAS155 Ampliación Dep. Relaves | H66: 1 | K66: 238 | M66: =+K66+L66 -> 238 | N66: =+M66*P66 -> 0 | Q66: 46216 | R66: =+S66-7 -> 46281 | S66: 46288 | T66: 46295 | U66: 46302 | V66: 46310 | AE66: 46216 | AF66: =+AG66-7 -> 46281 | AG66: 46288 | AH66: 46295 | AI66: 46302 | AJ66: 46310
A67: =+TRIM(C67) -> 477-010-40-0159 | B67: 2.5.11.21 | C67: 477-010-40-0159 | E67: 477-PRI24045-001-010-IN-1031 | F67: PAS155 Canales de contorno Dep. Relaves | H67: 1 | K67: 181 | M67: =+K67+L67 -> 181 | N67: =+M67*P67 -> 0 | O67: 0 | P67: 0 | Q67: 46216 | R67: =+S67-7 -> 46281 | S67: 46288 | T67: 46295 | U67: 46302 | V67: 46310 | AE67: 46216 | AF67: =+AG67-7 -> 46281 | AG67: 46288 | AH67: 46295 | AI67: 46302 | AJ67: 46310
A68: =+TRIM(C68) -> 477-010-40-0163 | B68: 2.5.11.22 | C68: 477-010-40-0163 | E68: 477-PRI24045-001-010-IN-1032 | F68: PAS156 Ampliación bot. exist. y BR Rosario | H68: 1 | K68: 158 | M68: =+K68+L68 -> 158 | N68: =+M68*P68 -> 0 | O68: 0 | P68: 0 | Q68: 46216 | R68: =+S68-7 -> 46237 | S68: 46244 | T68: 46251 | U68: 46258 | V68: 46265 | AE68: 46216 | AF68: =+AG68-7 -> 46237 | AG68: 46244 | AH68: 46251 | AI68: 46258 | AJ68: 46265
A69: =+TRIM(C69) -> 477-010-40-0167 | B69: 2.5.11.23 | C69: 477-010-40-0167 | E69: 477-PRI24045-001-010-IN-1033 | F69: PAS155 Acueducto de agua desalada | H69: 1 | K69: 196 | M69: =+K69+L69 -> 196 | N69: =+M69*P69 -> 0 | O69: 0 | P69: 0 | Q69: 46216 | R69: =+S69-7 -> 46234 | S69: 46241 | T69: 46248 | U69: 46255 | V69: 46262 | AE69: 46216 | AF69: =+AG69-7 -> 46234 | AG69: 46241 | AH69: 46248 | AI69: 46255 | AJ69: 46262
A70: =+TRIM(C70) -> 477-010-40-0171 | B70: 2.5.11.24 | C70: 477-010-40-0171 | E70: 477-PRI24045-001-010-IN-1034 | F70: PAS156 Ampliación Botaderos Ujina | H70: 1 | K70: 163 | M70: =+K70+L70 -> 163 | N70: =+M70*P70 -> 0 | O70: 0 | P70: 0 | Q70: 46216 | R70: =+S70-7 -> 46252 | S70: 46259 | T70: 46266 | U70: 46273 | V70: 46280 | AE70: 46216 | AF70: =+AG70-7 -> 46252 | AG70: 46259 | AH70: 46266 | AI70: 46273 | AJ70: 46280
A71: =+TRIM(C71) -> 477-010-40-0175 | B71: 2.5.11.25 | C71: 477-010-40-0175 | E71: 477-PRI24045-001-010-IN-1035 | F71: PAS160 IFC | H71: 1 | K71: 229 | M71: =+K71+L71 -> 229 | N71: =+M71*P71 -> 0 | O71: 0 | P71: 0 | Q71: 46237 | R71: =+S71-7 -> 46272 | S71: 46279 | T71: 46287 | U71: 46294 | V71: 46301 | AE71: 46237 | AF71: =+AG71-7 -> 46272 | AG71: 46279 | AH71: 46287 | AI71: 46294 | AJ71: 46301
A72: =+TRIM(C72) -> 477-010-40-0179 | B72: 2.5.11.26 | C72: 477-010-40-0179 | E72: 477-PRI24045-001-010-IN-1036 | F72: PAS161 Calificación Industrial | H72: 1 | K72: 229 | M72: =+K72+L72 -> 229 | N72: =+M72*P72 -> 0 | O72: 0 | P72: 0 | Q72: 46216 | R72: =+S72-7 -> 46234 | S72: 46241 | T72: 46252 | U72: 46259 | V72: 46266 | AE72: 46216 | AF72: =+AG72-7 -> 46234 | AG72: 46241 | AH72: 46252 | AI72: 46259 | AJ72: 46266
A73: =+TRIM(C73) -> 477-010-40-0183 | B73: 2.5.12 | C73: 477-010-40-0183 | E73: 477-PRI24045-001-010-IN-1101 | F73: Cap. 11- Compromisos ambientales voluntarios | H73: 1 | K73: 208 | M73: =+K73+L73 -> 208 | N73: =+M73*P73 -> 0 | O73: 0 | P73: 0 | Q73: 46287 | R73: =+S73-7 -> 46322 | S73: 46329 | T73: 46345 | U73: 46357 | V73: 46367 | AE73: 46287 | AF73: =+AG73-7 -> 46322 | AG73: 46329 | AH73: 46345 | AI73: 46357 | AJ73: 46367
A74: =+TRIM(C74) -> 477-010-40-0187 | B74: 2.5.13 | C74: 477-010-40-0187 | D74: Iniciado | E74: 477-PRI24045-001-010-IN-1201 | F74: Cap. 12 - Relación proyecto con políticas y planes evaluados estratégicamente | H74: 1 | K74: 27 | M74: =+K74+L74 -> 27 | N74: =+M74*P74 -> 1.62 | O74: 0 | P74: =+'Programa P6 Excel R1'!J283 -> 0.06 | Q74: 46216 | R74: =+S74-7 -> 46262 | S74: 46269 | T74: 46276 | U74: 46286 | V74: 46293 | W74: =+'Programa P6 Excel R1'!G284 -> 46122 | AF74: =+AG74-7 -> 46188 | AG74: =+'Programa P6 Excel R1'!H284 -> 46195 | AH74: =+'Programa P6 Excel R1'!H285 -> 46203 | AI74: =+'Programa P6 Excel R1'!H286 -> 46210 | AJ74: =+'Programa P6 Excel R1'!H287 -> 46217
A75: =+TRIM(C75) -> 477-010-40-0191 | B75: 2.5.14 | C75: 477-010-40-0191 | D75: Iniciado | E75: 477-PRI24045-001-010-IN-1301 | F75: Cap. 13 - Relación Proyecto Programas desarrollo Regionales y Comunales | H75: 1 | K75: 27 | M75: =+K75+L75 -> 27 | N75: =+M75*P75 -> 1.62 | O75: 0 | P75: =+'Programa P6 Excel R1'!J288 -> 0.06 | Q75: 46216 | R75: =+S75-7 -> 46262 | S75: 46269 | T75: 46276 | U75: 46286 | V75: 46293 | W75: =+'Programa P6 Excel R1'!G289 -> 46122 | AF75: =+AG75-7 -> 46188 | AG75: =+'Programa P6 Excel R1'!H289 -> 46195 | AH75: =+'Programa P6 Excel R1'!H290 -> 46203 | AI75: =+'Programa P6 Excel R1'!H291 -> 46210 | AJ75: =+'Programa P6 Excel R1'!H292 -> 46217
A76: =+TRIM(C76) -> 477-010-40-0195 | B76: 2.5.15 | C76: 477-010-40-0195 | E76: 477-PRI24045-001-010-IN-1401 | F76: Cap. 14- Fichas resumen | H76: 1 | K76: 121 | M76: =+K76+L76 -> 121 | N76: =+M76*P76 -> 0 | Q76: 46330 | R76: =+S76-7 -> 46352 | S76: 46359 | T76: 46367 | U76: 46374 | V76: 46384 | AE76: 46330 | AF76: =+AG76-7 -> 46352 | AG76: 46359 | AH76: 46367 | AI76: 46374 | AJ76: 46384
A77: =+TRIM(C77) -> 477-010-40-0199 | B77: 2.5.16 | C77: 477-010-40-0199 | E77: 477-PRI24045-001-010-IN-1501 | F77: Cap. 15 - Descripción de las acciones previas a la presentación del EIA (PACA y Documento) | H77: 1 | K77: 215 | M77: =+K77+L77 -> 215 | N77: =+M77*P77 -> 0 | O77: 0 | P77: 0 | Q77: 46265 | R77: =+S77-7 -> 46309 | S77: 46316 | T77: 46329 | U77: 46342 | V77: 46352 | AE77: 46265 | AF77: =+AG77-7 -> 46309 | AG77: 46316 | AH77: 46329 | AI77: 46342 | AJ77: 46352
A78: =+TRIM(C78) -> 477-010-40-0203 | B78: 2.5.17 | C78: 477-010-40-0203 | E78: 477-PRI24045-001-010-IN-1601 | F78: Cap. 16 - Información de acuerdos y/o negociaciones | H78: 1 | K78: 60 | M78: =+K78+L78 -> 60 | N78: =+M78*P78 -> 0 | O78: 0 | P78: 0 | Q78: 46265 | R78: =+S78-7 -> 46309 | S78: 46316 | T78: 46329 | U78: 46342 | V78: 46352 | AE78: 46265 | AF78: =+AG78-7 -> 46309 | AG78: 46316 | AH78: 46329 | AI78: 46342 | AJ78: 46352
A79: =+TRIM(C79) -> 477-010-40-0207 | B79: 2.5.18 | C79: 477-010-40-0207 | E79: 477-PRI24045-001-010-IN-1701 | F79: Extracto | H79: 1 | K79: 27 | M79: =+K79+L79 -> 27 | N79: =+M79*P79 -> 0 | O79: 0 | P79: 0 | Q79: 46346 | R79: =+S79-7 -> 46352 | S79: 46359 | T79: 46367 | U79: 46374 | V79: 46384 | AE79: 46346 | AF79: =+AG79-7 -> 46352 | AG79: 46359 | AH79: 46367 | AI79: 46374 | AJ79: 46384
A80: =+TRIM(C80) -> 477-010-40-0211 | B80: 2.5.19 | C80: 477-010-40-0211 | E80: 477-PRI24045-001-010-IN-1801 | F80: Listado de profesionales | H80: 1 | K80: 18 | M80: =+K80+L80 -> 18 | N80: =+M80*P80 -> 0 | O80: 0 | P80: 0 | Q80: 46317 | R80: =+S80-7 -> 46317 | S80: 46324 | T80: 46331 | U80: 46338 | V80: 46345 | AE80: 46317 | AF80: =+AG80-7 -> 46317 | AG80: 46324 | AH80: 46331 | AI80: 46338 | AJ80: 46345
A81: =+TRIM(C81) -> 477-010-40-0215 | B81: 2.5.20 | C81: 477-010-40-0215 | E81: 477-PRI24045-001-010-IN-1901 | F81: Texto de Aviso radial | H81: 1 | K81: 15 | M81: =+K81+L81 -> 15 | N81: =+M81*P81 -> 0 | O81: 0 | P81: 0 | Q81: 46346 | R81: =+S81-7 -> 46353 | S81: 46360 | T81: 46370 | U81: 46377 | V81: 46385 | AE81: 46346 | AF81: =+AG81-7 -> 46353 | AG81: 46360 | AH81: 46370 | AI81: 46377 | AJ81: 46385
M82: =+K82+L82 -> 0 | N82: =+M82*P82 -> 0 | O82: 0 | P82: 0
B83: 2.6 | F83: Modelos hidrogeológicos | K83: 0 | M83: =+K83+L83 -> 0 | N83: =+M83*P83 -> 0 | O83: 0 | P83: 0
A84: =+TRIM(C84) -> 477-010-40-0219 | B84: 2.6.1 | C84: 477-010-40-0219 | E84: 477-PRI24045-001-010-IN-0402 | F84: Modelo Conceptual (Actualización) | H84: 1 | K84: 439 | M84: =+K84+L84 -> 439 | N84: =+M84*P84 -> 0 | O84: 0 | P84: 0 | Q84: 46147 | R84: =+S84-7 -> 46171 | S84: 46178 | T84: 46185 | U84: 46192 | V84: 46199 | AE84: 46147 | AF84: =+AG84-7 -> 46171 | AG84: 46178 | AH84: 46185 | AI84: 46192 | AJ84: 46199
A85: =+TRIM(C85) -> 477-010-40-0223 | B85: 2.6.2 | C85: 477-010-40-0223 | E85: 477-PRI24045-001-010-IN-0403 | F85: Modelo Leapfrog (Actualización) | H85: 1 | K85: 201 | M85: =+K85+L85 -> 201 | N85: =+M85*P85 -> 0 | O85: 0 | P85: 0 | Q85: 46139 | R85: =+S85-7 -> 46142 | S85: 46149 | T85: 46156 | U85: 46164 | V85: 46171 | AE85: 46139 | AF85: =+AG85-7 -> 46142 | AG85: 46149 | AH85: 46156 | AI85: 46164 | AJ85: 46171
A86: =+TRIM(C86) -> 477-010-40-0227 | B86: 2.6.3 | C86: 477-010-40-0227 | E86: 477-PRI24045-001-010-IN-0404 | F86: Modelo hidrológico de recarga por precipitaciones (Actualización/reconceptualización) | H86: 1 | K86: 194 | M86: =+K86+L86 -> 194 | N86: =+M86*P86 -> 0 | O86: 0 | P86: 0 | Q86: 46139 | R86: =+S86-7 -> 46164 | S86: 46171 | T86: 46178 | U86: 46185 | V86: 46192 | AE86: 46139 | AF86: =+AG86-7 -> 46164 | AG86: 46171 | AH86: 46178 | AI86: 46185 | AJ86: 46192
B87: 2.7 | F87: Modelo numérico Coposa-Michincha-Rosario | K87: 0 | M87: =+K87+L87 -> 0 | N87: =+M87*P87 -> 0 | O87: 0 | P87: 0 | AE87: - | AG87: -
A88: =+TRIM(C88) -> 477-010-40-0231 | B88: 2.7.1 | C88: 477-010-40-0231 | F88: Actualización y recalibración | J88: 1 | K88: 319 | M88: =+K88+L88 -> 319 | N88: =+M88*P88 -> 0 | O88: 0 | P88: 0 | Q88: 46203 | V88: 46213 | AE88: 46203 | AG88: 46213
A89: =+TRIM(C89) -> 477-010-40-0232 | B89: 2.7.2 | C89: 477-010-40-0232 | F89: Simulación de escenarios | J89: 1 | K89: 200 | M89: =+K89+L89 -> 200 | N89: =+M89*P89 -> 0 | O89: 0 | P89: 0 | Q89: 46216 | V89: 46218 | AE89: 46216 | AG89: 46218
A90: =+TRIM(C90) -> 477-010-40-0232_2 | B90: 2.7.3 | C90: 477-010-40-0232_2 | E90: 477-PRI24045-001-010-IN-0405 | F90: Informe | H90: 1 | K90: 108 | M90: =+K90+L90 -> 108 | N90: =+M90*P90 -> 0 | O90: 0 | P90: 0 | Q90: 46220 | R90: =+S90-7 -> 46217 | S90: 46224 | T90: 46227 | U90: 46232 | V90: 46239 | AE90: 46220 | AF90: =+AG90-7 -> 46217 | AG90: 46224 | AH90: 46227 | AI90: 46232 | AJ90: 46239
B91: 2.8 | F91: Caracterización de materiales y potencial de drenaje ácido | K91: 0 | M91: =+K91+L91 -> 0 | N91: =+M91*P91 -> 0 | O91: 0 | P91: 0 | AE91: - | AG91: -
A92: =+TRIM(C92) -> 477-010-40-0237 | B92: 2.8.1 | C92: 477-010-40-0237 | E92: 477-PRI24045-001-010-IN-0406 | F92: Memorando revisión estudio de brechas y plan de caracterización | H92: 1 | K92: 245 | M92: =+K92+L92 -> 245 | N92: =+M92*P92 -> 0 | O92: 0 | P92: 0 | Q92: 46220 | R92: =+S92-7 -> 46226 | S92: 46233 | T92: 46240 | U92: 46247 | V92: 46254 | AE92: 46220 | AF92: =+AG92-7 -> 46226 | AG92: 46233 | AH92: 46240 | AI92: 46247 | AJ92: 46254
A93: =+TRIM(C93) -> 477-010-40-0241 | B93: 2.8.2 | C93: 477-010-40-0241 | E93: 477-PRI24045-001-010-IN-0407 | F93: Informe | H93: 1 | K93: 309 | M93: =+K93+L93 -> 309 | N93: =+M93*P93 -> 0 | O93: 0 | P93: 0 | Q93: 46232 | R93: =+S93-7 -> 46238 | S93: 46245 | T93: 46252 | U93: 46259 | V93: 46266 | AE93: 46232 | AF93: =+AG93-7 -> 46238 | AG93: 46245 | AH93: 46252 | AI93: 46259 | AJ93: 46266
A94: =+TRIM(C94) -> 477-010-40-0245 | B94: 2.8.3 | C94: 477-010-40-0245 | E94: 477-PRI24045-001-010-IN-0408 | F94: Diseño medidas estabilidad química | H94: 1 | K94: 275 | M94: =+K94+L94 -> 275 | N94: =+M94*P94 -> 0 | O94: 0 | P94: 0 | Q94: 46220 | R94: =+S94-7 -> 46260 | S94: 46267 | T94: 46274 | U94: 46281 | V94: 46289 | AE94: 46220 | AF94: =+AG94-7 -> 46260 | AG94: 46267 | AH94: 46274 | AI94: 46281 | AJ94: 46289
B95: 2.9 | F95: Modelo infiltración de botaderos para Rosario | K95: 0 | M95: =+K95+L95 -> 0 | N95: =+M95*P95 -> 0 | O95: 0 | P95: 0 | S95: - | AE95: - | AG95: -
A96: =+TRIM(C96) -> 477-010-40-0249 | B96: 2.9.1 | C96: 477-010-40-0249 | F96: Actualización y recalibración | J96: 1 | K96: 221 | M96: =+K96+L96 -> 221 | N96: =+M96*P96 -> 0 | O96: 0 | P96: 0 | Q96: 46139 | V96: 46157 | AE96: 46139 | AG96: 46157
A97: =+TRIM(C97) -> 477-010-40-0250 | B97: 2.9.2 | C97: 477-010-40-0250 | F97: Simulación de escenarios | J97: 1 | K97: 304 | M97: =+K97+L97 -> 304 | N97: =+M97*P97 -> 0 | O97: 0 | P97: 0 | Q97: 46160 | V97: 46167 | AE97: 46160 | AG97: 46167
A98: =+TRIM(C98) -> 477-010-40-0250_2 | B98: 2.9.3 | C98: 477-010-40-0250_2 | E98: 477-PRI24045-001-010-IN-0409 | F98: Informe | H98: 1 | K98: 101 | M98: =+K98+L98 -> 101 | N98: =+M98*P98 -> 0 | O98: 0 | P98: 0 | Q98: 46168 | R98: =+S98-7 -> 46167 | S98: 46174 | T98: 46181 | U98: 46188 | V98: 46216 | AE98: 46168 | AF98: =+AG98-7 -> 46167 | AG98: 46174 | AH98: 46181 | AI98: 46188 | AJ98: 46216
B99: 2.10 | F99: Modelo infiltración de botaderos para Ujina | K99: 0 | M99: =+K99+L99 -> 0 | N99: =+M99*P99 -> 0 | Q99: - | S99: - | AE99: - | AG99: -
A100: =+TRIM(C100) -> 477-010-40-0255 | B100: 2.10.1 | C100: 477-010-40-0255 | F100: Actualización y recalibración | J100: 1 | K100: 183.8 | M100: =+K100+L100 -> 183.8 | N100: =+M100*P100 -> 0 | O100: 0 | P100: 0 | Q100: 46139 | V100: 46153 | AE100: 46139 | AG100: 46153
A101: =+TRIM(C101) -> 477-010-40-0256 | B101: 2.10.2 | C101: 477-010-40-0256 | F101: Simulación de escenarios | J101: 1 | K101: 254.4 | M101: =+K101+L101 -> 254.4 | N101: =+M101*P101 -> 0 | O101: 0 | P101: 0 | Q101: 46154 | V101: 46160 | AE101: 46154 | AG101: 46160
A102: =+TRIM(C102) -> 477-010-40-0256_2 | B102: 2.10.3 | C102: 477-010-40-0256_2 | E102: 477-PRI24045-001-010-IN-0410 | F102: Informe | H102: 1 | K102: 88.6 | M102: =+K102+L102 -> 88.6 | N102: =+M102*P102 -> 0 | O102: 0 | P102: 0 | Q102: 46161 | R102: =+S102-7 -> 46161 | S102: 46168 | T102: 46175 | U102: 46182 | V102: 46217 | AE102: 46161 | AF102: =+AG102-7 -> 46161 | AG102: 46168 | AH102: 46175 | AI102: 46182 | AJ102: 46217
B103: 2.11 | F103: Modelo infiltración depósito de relaves Pampa Pabellón | K103: 0 | M103: =+K103+L103 -> 0 | N103: =+M103*P103 -> 0 | O103: 0 | P103: 0 | Q103: - | S103: - | AE103: - | AG103: -
...

Sheet Curva S R1
D3: CURVA S
D6: 2025 | AP6: 2026 | CQ6: 2027 | EF6: HH | EG6: Fact. | EH6: Avance %
C7: FASE | D7: =+D144 -> 45757 | E7: =+D7+7 -> 45764 | F7: =+E7+7 -> 45771 | G7: =+F7+7 -> 45778 | H7: =+G7+7 -> 45785 | I7: =+H7+7 -> 45792 | J7: =+I7+7 -> 45799 | K7: =+J7+7 -> 45806 | L7: =+K7+7 -> 45813 | ... EC7: =+EB7+7 -> 46660 | EG7: Peso % | EH7: Prog | EI7: Real
EG9: =+#REF!*100 -> #REF! | EH9: =+#REF!/#REF!*100 -> #REF! | EI9: =+#REF!/#REF!*100 -> #REF!
C10: EIA
C11: PROGRAMADO
C12: REAL + FORECAST
EG13: =+#REF!*100 -> #REF! | EH13: =+#REF!/#REF!*100 -> #REF! | EI13: =+#REF!/#REF!*100 -> #REF!
EG17: =+#REF!*100 -> #REF! | EH17: =+#REF!/#REF!*100 -> #REF! | EI17: =+#REF!/#REF!*100 -> #REF!
EG21: =+#REF!*100 -> #REF! | EH21: =+#REF!/#REF!*100 -> #REF! | EI21: =+#REF!/#REF!*100 -> #REF!
EG25: =+#REF!*100 -> #REF! | EH25: =+#REF!/#REF!*100 -> #REF! | EI25: =+#REF!/#REF!*100 -> #REF!
C31: Av. Prog. Parcial (%) - R0 | D31: =+D32 -> 0.22559452 | E31: =+E32-D32 -> 0.48306469 | F31: =+F32-E32 -> 0.37655755 | G31: =+G32-F32 -> 0.44098884 | H31: =+H32-G32 -> 0.47116445 | I31: =+I32-H32 -> 0.7531151 | J31: =+J32-I32 -> 0.59025183 | K31: =+K32-J32 -> 1.1595932 | L31: =+L32-K32 -> 1.3114913 | ... EC31: =+EC32-EB32 -> 0.037145745 | EF31: =SUM(EF13:EF30) -> 0
C32: Av. Prog. Acum. (%) - R0 | D32: =+D46/$EC$46*100 -> 0.22559452 | E32: =+E46/$EC$46*100 -> 0.70865921 | F32: =+F46/$EC$46*100 -> 1.0852168 | G32: =+G46/$EC$46*100 -> 1.5262056 | H32: =+H46/$EC$46*100 -> 1.99737 | I32: =+I46/$EC$46*100 -> 2.7504851 | J32: =+J46/$EC$46*100 -> 3.340737 | K32: =+K46/$EC$46*100 -> 4.5003302 | ... EC32: =+EC46/$EC$46*100 -> 100 | EG32: =SUM(EG8:EG30) -> #REF! | EH32: =SUMPRODUCT(EH8:EH30,EG8:EG30)/100 -> #REF! | EI32: =SUMPRODUCT(EI8:EI30,EG8:EG30)/100 -> #REF!
C33: Av. Prog. Parcial (%) - R1 | D33: =+D34 -> 0.090812451 | E33: =+E34-D34 -> 0.28527388 | F33: =+F34-E34 -> 0.3421692 | G33: =+G34-F34 -> 0.36809739 | H33: =+H34-G34 -> 0.33194781 | I33: =+I34-H34 -> 0.27832143 | J33: =+J34-I34 -> 0.46709013 | K33: =+K34-J34 -> 1.055314 | L33: =+L34-K34 -> 1.1416457 | ... V33: =+V34-U34 -> 1.6474447 | AE33: =+AE34-AD34 -> 0.91640048 | AF33: =+AF34-AE34 -> 1.0328621 | AG33: =+AG34-AF34 -> 1.1231005 | AH33: =+AH34-AG34 -> 1.3977543 | AI33: =+AI34-AH34 -> 2.1524385 | AJ33: =+AJ34-AI34 -> 2.1676031 | AK33: =+AK34-AJ34 -> 1.9202249 | AL33: =+AL34-AK34 -> 1.8739018 | ... EC33: =+EC34-EB34 -> 0.034770246
C34: Av. Prog. Acum. (%) - R1 | D34: =+D56/$EC$56*100 -> 0.090812451 | E34: =+E56/$EC$56*100 -> 0.37608633 | F34: =+F56/$EC$56*100 -> 0.71825553 | G34: =+G56/$EC$56*100 -> 1.0863529 | H34: =+H56/$EC$56*100 -> 1.4183007 | I34: =+I56/$EC$56*100 -> 1.6966222 | J34: =+J56/$EC$56*100 -> 2.1637123 | K34: =+K56/$EC$56*100 -> 3.2190263 | ... W34: =+W56/$EC$56*100 -> 14.099729 | AD34: =+AD56/$EC$56*100 -> 18.486561 | AE34: =+AE56/$EC$56*100 -> 19.402961 | AF34: =+AF56/$EC$56*100 -> 20.435823 | AG34: =+AG56/$EC$56*100 -> 21.558924 | AH34: =+AH56/$EC$56*100 -> 22.956678 | AI34: =+AI56/$EC$56*100 -> 25.109116 | AJ34: =+AJ56/$EC$56*100 -> 27.27672 | AK34: =+AK56/$EC$56*100 -> 29.196944 | ... EC34: =+EC56/$EC$56*100 -> 100
C35: Av. Real + Forecast Parcial (%) | D35: 0.12309012 | E35: 0.24618024 | F35: 0.36927035 | G35: 0.49236047 | H35: 0.47171696 | I35: 1.0185754 | J35: 0.89019735 | K35: 1.0285206 | L35: 0.59118685 | M35: 0.59262338 | N35: 0.95609917 | O35: 0.40681816 | P35: 0.6334327 | Q35: 0.45016903 | R35: 0.36950241 | S35: 1.0622479 | T35: 0.80091314 | U35: 0.84766843 | V35: 0.82778496 | W35: 1.8445411 | X35: 1.4240546 | Y35: 0.72496208 | Z35: 0.90803222 | AA35: 0.36587241 | AB35: 0.19079845 | AC35: 0.27051893 | AD35: 0.48129504 | AE35: 0.5177943 | AF35: 1.0187537 | AG35: 0.99173716 | AH35: 0.95104888 | AI35: 1.650015 | AJ35: 1.8530643 | AK35: 1.6332174 | AL35: 1.8395438 | AM35: 1.1482445 | AN35: 0.4485707 | AO35: 0.33304336 | AP35: 0.31011993 | AQ35: 0.10029641 | AR35: 0.17327757 | AS35: 0.60567924 | AT35: 0.79267804 | AU35: 0.28899616 | AV35: 1.0987849 | AW35: 1.0454379 | AX35: 0.58680157 | AY35: 0.8044234 | AZ35: 0.89620806 | BA35: 0.37586108 | BB35: 0.34793182 | BC35: 0.80994865 | BD35: 0.64970022 | BE35: =+BE36-BD36 -> 0.43510811 | BF35: =+BF36-BE36 -> 0.53640996 | BG35: =+BG36-BF36 -> 1.3576247 | BH35: =+BH36-BG36 -> 2.3236696 | BI35: =+BI36-BH36 -> 2.2091501 | BJ35: =+BJ36-BI36 -> 2.1310125 | BK35: =+BK36-BJ36 -> 1.4184441 | BL35: =+BL36-BK36 -> 2.057395 | ... EC35: =+EC36-EB36 -> 0.033287185
C36: Av. Real + Forecast Acum. (%) | D36: =+D35 -> 0.12309012 | E36: =+D36+E35 -> 0.36927035 | F36: =+E36+F35 -> 0.73854071 | G36: =+F36+G35 -> 1.2309012 | H36: =+G36+H35 -> 1.7026181 | I36: =+H36+I35 -> 2.7211936 | J36: =+I36+J35 -> 3.6113909 | K36: =+J36+K35 -> 4.6399115 | L36: =+K36+L35 -> 5.2310984 | ... BD36: =+BC36+BD35 -> 39.659611 | BE36: =+BE68/125424*100 -> 40.094719 | BF36: =+BF68/$EC$48*100 -> 40.631129 | BG36: =+BG68/$EC$48*100 -> 41.988753 | BH36: =+BH68/$EC$48*100 -> 44.312423 | BI36: =+BI68/$EC$48*100 -> 46.521573 | BJ36: =+BJ68/$EC$48*100 -> 48.652586 | BK36: =+BK68/$EC$48*100 -> 50.07103 | BL36: =+BL68/$EC$48*100 -> 52.128425 | BM36: =+BM68/$EC$48*100 -> 53.576688 | ... EC36: =+EC68/$EC$48*100 -> 100
BE37: =+BE36 -> 40.094719 | BF37: =+BF36 -> 40.631129 | BG37: =+BG36 -> 41.988753 | BH37: =+BH36 -> 44.312423 | BI37: =+BI36 -> 46.521573 | BJ37: =+BJ36 -> 48.652586 | BK37: =+BK36 -> 50.07103 | BL37: =+BL36 -> 52.128425 | ... EC37: =+EC36 -> 100
D41: 0.014765101 | E41: 0.02147651 | F41: 0.042693224 | G41: 0.074529119 | H41: 0.12767915 | I41: 0.21133362 | J41: 0.34310673 | K41: 0.582979 | L41: 0.72684564 | M41: 0.78948907 | N41: 0.86899762 | O41: 0.92297034 | P41: 0.94613553 | Q41: 0.9605398 | R41: 0.97402035 | S41: 0.98268023 | T41: 0.98268023 | U41: 0.99567006
I42: 0.2231 | J42: 0.3392 | K42: 0.50840902 | L42: 0.67858235 | M42: 0.76210709 | N42: 0.79579059 | O42: =+O36/100 -> 0.071866391 | P42: 0.93900679 | Q42: 0.96312026 | R42: 0.96980719 | S42: 0.97649412 | T42: 0.98277579 | U42: 0.99594701
L43: =+L35-L31 -> -0.72030444 | M43: =+M35-M31 -> -0.50041353 | N43: =+N35-N31 -> -0.18164864 | O43: =+O35-O31 -> -0.71375931 | P43: =+P35-P31 -> -0.39644795 | Q43: =+Q35-Q31 -> -0.28679575 | R43: =+R35-R31 -> -0.22091943 | S43: =+S35-S31 -> 0.34270843 | ... X43: =+X35-X31 -> -0.10249103
D45: =+D144 -> 45757 | E45: =+E144 -> 45764 | F45: =+F144 -> 45771 | G45: =+G144 -> 45778 | H45: =+H144 -> 45785 | I45: =+I144 -> 45792 | J45: =+J144 -> 45799 | K45: =+K144 -> 45806 | ... EC45: =+EC144 -> 46660
C46: Av. Prog Base | D46: =+D146 -> 265.4 | E46: =+E146 -> 833.7 | F46: =+F146 -> 1276.7 | G46: =+G146 -> 1795.5 | H46: =+H146 -> 2349.8 | I46: =+I146 -> 3235.8 | J46: =+J146 -> 3930.2 | K46: =+K146 -> 5294.4 | ... EC46: =+EC146 -> 117644.7
C47: Av. Distribución Entregables 4-May
C48: Av. Real/Forecast | D48: =+D152 -> 144.809 | E48: =+E152 -> 434.427 | F48: =+F152 -> 868.854 | G48: =+G152 -> 1448.09 | H48: =+H152 -> 2003.04 | I48: =+I152 -> 3201.34 | J48: =+J152 -> 4248.61 | K48: =+K152 -> 5458.61 | ... AC48: =+AC152 -> 21959.56 | AD48: =+AD62 -> 22798.6 | AE48: =+AE62 -> 23914.57 | AF48: =+AF62 -> 25044.44 | AG48: =+AG62 -> 26234.86 | AH48: =+AH62 -> 27426.86 | AI48: =+AI62 -> 29496.85 | AJ48: =+AJ62 -> 31820.98 | AK48: =+AK62 -> 33869.35 | ... BE48: =+BE62 -> 50288.4 | BF48: =+BF68 -> 53304.64 | BG48: =+BG68 -> 55085.73 | BH48: =+BH68 -> 58134.19 | BI48: =+BI68 -> 61032.41 | BJ48: =+BJ68 -> 63828.12 | BK48: =+BK68 -> 65689 | BL48: =+BL68 -> 68388.13 | BM48: =+BM68 -> 70288.13 | ... EC48: =+EC68 -> 131191.63
B51: PROGRAMA REV.1
B52: Avance Programado
C54: Avance En HH | D54: =+D156 -> 45757 | E54: =+E156 -> 45764 | F54: =+F156 -> 45771 | G54: =+G156 -> 45778 | H54: =+H156 -> 45785 | I54: =+I156 -> 45792 | J54: =+J156 -> 45799 | K54: =+K156 -> 45806 | ... EC54: =+EC156 -> 46660
C55: HH Parcial | D55: =+D75 -> 113.9 | E55: =+E75 -> 357.8 | F55: =+F75 -> 429.16 | G55: =+G75 -> 461.68 | H55: =+H75 -> 416.34 | I55: =+I75 -> 349.08 | J55: =+J75 -> 585.84 | K55: =+K75 -> 1323.61 | ... EC55: =+EC75 -> 43.61
C56: HH Acumuladas | D56: =+D55 -> 113.9 | E56: =+D56+E55 -> 471.7 | F56: =+E56+F55 -> 900.86 | G56: =+F56+G55 -> 1362.54 | H56: =+G56+H55 -> 1778.88 | I56: =+H56+I55 -> 2127.96 | J56: =+I56+J55 -> 2713.8 | K56: =+J56+K55 -> 4037.41 | L56: =+K56+L55 -> 5469.3 | ... EC56: =+EB56+EC55 -> 125423.33
AH57: =+AH55/125423 -> 0.01397758
B58: Avance real | AH58: =+AH56/125423 -> 0.22956738
C60: Avance En HH | D60: =+D54 -> 45757 | E60: =+E54 -> 45764 | F60: =+F54 -> 45771 | G60: =+G54 -> 45778 | H60: =+H54 -> 45785 | I60: =+I54 -> 45792 | J60: =+J54 -> 45799 | K60: =+K54 -> 45806 | ... EC60: =+EC54 -> 46660
C61: HH Parcial | D61: 101.39 | E61: 345.29 | F61: 417.6 | G61: 450.75 | H61: 405.41 | I61: 338.15 | J61: 574.91 | K61: 1312.68 | L61: 1420.96 | M61: 1473.93 | N61: 1457.81 | O61: 473.43 | P61: 404.6 | Q61: 471.77 | R61: 652.14 | S61: 598.86 | T61: 1163.44 | U61: 1204.55 | V61: 2052.35 | W61: 2109.3 | X61: 1334.26 | Y61: 857.42 | Z61: 1145.99 | AA61: 326.65 | AB61: 350.34 | AC61: 500.7 | AD61: 853.92 | AE61: 1115.97 | AF61: 1129.87 | AG61: 1190.42 | AH61: 1192 | AI61: 2069.99 | AJ61: 2324.13 | AK61: 1966.82 | AL61: 2307.3 | AM61: 1440.1 | AN61: 562.63 | AO61: 417.74 | AP61: 264.62 | AQ61: 250.17 | AR61: 217.31 | AS61: 1208 | AT61: 994.2 | AU61: 362.69 | AV61: 1190.97 | AW61: 1086.93 | AX61: 1147.46 | AY61: 1008.94 | AZ61: 1124.06 | BA61: 471.42 | BB61: 471.42 | BC61: 1015.87 | BD61: 814.88 | BE61: =+BE62-BD62 -> 545.73 | BF61: =+BF62-BE62 -> 0 | BG61: =+BG62-BF62 -> 0 | BH61: =+BH62-BG62 -> 0 | BI61: =+BI62-BH62 -> 0 | BJ61: =+BJ62-BI62 -> 0 | BK61: =+BK62-BJ62 -> 0 | BL61: =+BL62-BK62 -> 0 | ... EC61: =+EC62-EB62 -> 0
C62: HH Acumuladas | D62: =+D61 -> 101.39 | E62: =+D62+E61 -> 446.68 | F62: =+E62+F61 -> 864.28 | G62: =+F62+G61 -> 1315.03 | H62: =+G62+H61 -> 1720.44 | I62: =+H62+I61 -> 2058.59 | J62: =+I62+J61 -> 2633.5 | K62: =+J62+K61 -> 3946.18 | L62: =+K62+L61 -> 5367.14 | ... AJ62: =+AI62+AJ61 -> 31820.98 | AK62: 33869.35 | AL62: 36176.65 | AM62: 37616.75 | AN62: 38179.38 | AO62: 38597.12 | AP62: 38861.74 | AQ62: 39111.91 | AR62: 38880.86 | AS62: 40088.86 | AT62: 41083.06 | AU62: 41445.75 | AV62: 42636.72 | AW62: 43723.65 | AX62: 44871.11 | AY62: 45880.05 | AZ62: 47004.11 | BA62: 47475.53 | BB62: 47911.92 | BC62: 48927.79 | BD62: 49742.67 | BE62: =+BE83 -> 50288.4 | BF62: =+BF83 -> 50288.4 | BG62: =+BG83 -> 50288.4 | BH62: =+BH83 -> 50288.4 | BI62: =+BI83 -> 50288.4 | BJ62: =+BJ83 -> 50288.4 | BK62: =+BK83 -> 50288.4 | BL62: =+BL83 -> 50288.4 | ... EC62: =+EC83 -> 50288.4
AH63: =+AH61/125423 -> 0.009503839 | AI63: =+AI61/125423 -> 0.01650407 | AJ63: =+AJ61/125423 -> 0.018530333 | AK63: =+AK61/125423 -> 0.015681494 | AL63: =+AL61/125423 -> 0.018396147 | AM63: =+AM61/125423 -> 0.011481945 | AN63: =+AN61/125423 -> 0.0044858599 | AO63: =+AO61/125423 -> 0.0033306491 | ... BE63: =+BE61/125423 -> 0.0043511158
B64: Forecast | AH64: =+AH62/125423 -> 0.21867488 | AI64: =+AI62/125423 -> 0.23517895 | AJ64: =+AJ62/125423 -> 0.25370929 | AK64: =+AK62/125423 -> 0.27004098 | AL64: =+AL62/125423 -> 0.28843713 | AM64: =+AM62/125423 -> 0.29991907 | AN64: =+AN62/125423 -> 0.30440493 | AO64: =+AO62/125423 -> 0.30773558 | ... BE64: =+BE62/125423 -> 0.40095038
C66: Avance En HH | D66: =+D60 -> 45757 | E66: =+E60 -> 45764 | F66: =+F60 -> 45771 | G66: =+G60 -> 45778 | H66: =+H60 -> 45785 | I66: =+I60 -> 45792 | J66: =+J60 -> 45799 | K66: =+K60 -> 45806 | ... EC66: =+EC60 -> 46660
C67: HH Parcial
C68: HH Acumuladas | BE68: =SUM($D$76:BE76) -> 50288.4 | BF68: =+BE68+BF78 -> 53304.64 | BG68: =+BF68+BG78 -> 55085.73 | BH68: =+BG68+BH78 -> 58134.19 | BI68: =+BH68+BI78 -> 61032.41 | BJ68: =+BI68+BJ78 -> 63828.12 | BK68: =+BJ68+BK78 -> 65689 | BL68: =+BK68+BL78 -> 68388.13 | BM68: =+BL68+BM78 -> 70288.13 | ... EC68: =+EB68+EC78 -> 131191.63
B73: PROGRAMA SERVICIO REV.1
C74: Spreadsheet Field | D74: =+D163 -> 45757 | E74: =+E163 -> 45764 | F74: =+F163 -> 45771 | G74: =+G163 -> 45778 | H74: =+H163 -> 45785 | I74: =+I163 -> 45792 | J74: =+J163 -> 45799 | K74: =+K163 -> 45806 | ... EC74: =+EC163 -> 46660
C75: BL1 Labor Units | D75: 113.9 | E75: 357.8 | F75: 429.16 | G75: 461.68 | H75: 416.34 | I75: 349.08 | J75: 585.84 | K75: 1323.61 | L75: 1431.89 | M75: 1488.91 | N75: 1472.6 | O75: 487.49 | P75: 418.66 | Q75: 485.83 | R75: 666.17 | S75: 612.82 | T75: 1177.37 | U75: 1218.48 | V75: 2066.28 | W75: 2120.44 | X75: 1348.17 | Y75: 871.32 | Z75: 1160.82 | AA75: 339.16 | AB75: 362.71 | AC75: 517.51 | AD75: 902.42 | AE75: 1149.38 | AF75: 1295.45 | AG75: 1408.63 | AH75: 1753.11 | AI75: 2699.66 | AJ75: 2718.68 | AK75: 2408.41 | AL75: 2350.31 | AM75: 1821.63 | AN75: 1055.1 | AO75: 679.24 | AP75: 605.44 | AQ75: 913.88 | AR75: 916.42 | AS75: 1017.61 | AT75: 783.93 | AU75: 991.34 | AV75: 1074.99 | AW75: 1504.63 | AX75: 1860.03 | AY75: 1565.52 | AZ75: 1771.43 | BA75: 1683.57 | BB75: 1076.8 | BC75: 886.04 | BD75: 1459.94 | BE75: 2047.4 | BF75: 2603.01 | BG75: 2383.62 | BH75: 2008.67 | BI75: 2193.94 | BJ75: 2121.02 | BK75: 1981.68 | BL75: 1907.57 | BM75: 1835.2 | BN75: 1825.21 | BO75: 1968.17 | BP75: 1558.09 | BQ75: 1893.64 | BR75: 2218.38 | BS75: 2968.6 | BT75: 2693.11 | BU75: 2305.58 | BV75: 2335.41 | BW75: 2188.56 | BX75: 2710.24 | BY75: 1792.79 | BZ75: 1778.14 | CA75: 1150.14 | CB75: 1046.67 | CC75: 1532.86 | CD75: 1561.98 | CE75: 1115.34 | CF75: 1107.43 | CG75: 804.25 | CH75: 1261.28 | CI75: 1289.31 | CJ75: 1295.94 | CK75: 1174.46 | CL75: 658.5 | CM75: 168.96 | CN75: 539.19 | CO75: 117.01 | CP75: 311.12 | CQ75: 125.76 | CR75: 111.91 | CS75: 80.24 | CT75: 80.24 | CU75: 80.24 | CV75: 80.24 | CW75: 80.24 | CX75: 80.24 | CY75: 200.54 | CZ75: 131.44 | DA75: 110.54 | DB75: 85.94 | DC75: 29.4 | DD75: 36.74 | DE75: 36.74 | DF75: 36.74 | DG75: 36.74 | DH75: 36.74 | DI75: 36.74 | DJ75: 36.74 | DK75: 29.4 | DL75: 36.74 | DM75: 36.74 | DN75: 36.74 | DO75: 29.4 | DP75: 29.4 | DQ75: 36.74 | DR75: 36.74 | DS75: 29.4 | DT75: 36.74 | DU75: 36.74 | DV75: 41.51 | DW75: 48.67 | DX75: 48.67 | DY75: 72.38 | DZ75: 72.38 | EA75: 58.15 | EB75: 38.93 | EC75: 43.61
C76: Earned Value Labor Units | D76: 103.25 | E76: 347.15 | F76: 419.14 | G76: 452.09 | H76: 406.75 | I76: 339.49 | J76: 576.25 | K76: 1314.02 | L76: 1422.29 | M76: 1466.48 | N76: 1450.26 | O76: 465.54 | P76: 396.71 | Q76: 463.88 | R76: 644.24 | S76: 586.82 | T76: 1148.27 | U76: 1188.67 | V76: 2036 | W76: 2094.84 | X76: 1317.73 | Y76: 947.76 | Z76: 1047.28 | AA76: 299.63 | AB76: 312.6 | AC76: 472.5 | AD76: 598.88 | AE76: 684.41 | AF76: 690.8 | AG76: 715.28 | AH76: 749.68 | AI76: 1792.96 | AJ76: 2134.03 | AK76: 1467.42 | AL76: 1475.09 | AM76: 1394.12 | AN76: 697.74 | AO76: 528.69 | AP76: 562.31 | AQ76: 596.21 | AR76: 574.94 | AS76: 1063.88 | AT76: 1103.1 | AU76: 746 | AV76: 1119.43 | AW76: 1259.41 | AX76: 1408.49 | AY76: 1438.66 | AZ76: 1277.95 | BA76: 771.89 | BB76: 919.68 | BC76: 960.71 | BD76: 664.08 | BE76: 1172.92
C77: Actual Labor Units | D77: 103.25 | E77: 347.15 | F77: 419.14 | G77: 452.09 | H77: 406.75 | I77: 371.07 | J77: 615.72 | K77: 1426.62 | L77: 1578.38 | M77: 1622.56 | N77: 1606.35 | O77: 518.43 | P77: 408.26 | Q77: 518.43 | R77: 813.54 | S77: 864.81 | T77: 1426.26 | U77: 1501.47 | V77: 2404.51 | W77: 2460.03 | X77: 1470.67 | Y77: 1128.49 | Z77: 1481.1 | AA77: 656.74 | AB77: 549.5 | AC77: 509.2 | AD77: 668.44 | AE77: 741.67 | AF77: 749.71 | AG77: 771.81 | AH77: 960.45 | AI77: 2387.78 | AJ77: 2730.6 | AK77: 2177.11 | AL77: 2265 | AM77: 2187.24 | AN77: 1330.12 | AO77: 895.79 | AP77: 625.47 | AQ77: 670.84 | AR77: 643.1 | AS77: 1190.83 | AT77: 1229.45 | AU77: 906.72 | AV77: 1462.47 | AW77: 1800.43 | AX77: 2032.06 | AY77: 2374.46 | AZ77: 2494.13 | BA77: 1642.05 | BB77: 1138.35 | BC77: 1144.15 | BD77: 828.36 | BE77: 1785.38
C78: Remaining Labor Units | BF78: =2266.24+750 -> 3016.24 | BG78: =3431.09-750-900 -> 1781.09 | BH78: 3048.46 | BI78: 2898.22 | BJ78: 2795.71 | BK78: 1860.88 | BL78: 2699.13 | BM78: 1900 | BN78: =1537.78+900 -> 2437.78 | BO78: 1850.59 | BP78: 1713.11 | BQ78: 2554.57 | BR78: 3864.33 | BS78: 3510.32 | BT78: 3677.71 | BU78: 3119.83 | BV78: 3336.51 | BW78: 3048.47 | BX78: 3697.1 | BY78: 2710.95 | BZ78: 2544.54 | CA78: 1684.79 | CB78: 1569.26 | CC78: 1983.6 | CD78: 1908.39 | CE78: 1517.92 | CF78: 1512.19 | CG78: 1184.94 | CH78: 1539.53 | CI78: 1665.05 | CJ78: 1594.44 | CK78: 1574.86 | CL78: 1069.63 | CM78: 313.23 | CN78: 533.48 | CO78: 278.24 | CP78: 346.56 | CQ78: 228.22 | CR78: 111.99 | CS78: 203.32 | CT78: 80.32 | CU78: 80.32 | CV78: 80.32 | CW78: 80.32 | CX78: 80.32 | CY78: 123.82 | CZ78: 80.32 | DA78: 36.82 | DB78: 36.82 | DC78: 29.46 | DD78: 139.22 | DE78: 62.42 | DF78: 135.22 | DG78: 61.42 | DH78: 36.82 | DI78: 36.82 | DJ78: 36.82 | DK78: 29.46 | DL78: 36.82 | DM78: 36.82 | DN78: 36.82 | DO78: 29.46 | DP78: 29.46 | DQ78: 36.82 | DR78: 36.82 | DS78: 29.46 | DT78: 36.82 | DU78: 36.82 | DV78: 41.59 | DW78: 48.75 | DX78: 48.75 | DY78: 72.45 | DZ78: 72.45 | EA78: 58.23 | EB78: 39 | EC78: 43.67
C80: Programa R1 (HH) | D80: =+D75 -> 113.9 | E80: =+D80+E75 -> 471.7 | F80: =+E80+F75 -> 900.86 | G80: =+F80+G75 -> 1362.54 | H80: =+G80+H75 -> 1778.88 | I80: =+H80+I75 -> 2127.96 | J80: =+I80+J75 -> 2713.8 | K80: =+J80+K75 -> 4037.41 | L80: =+K80+L75 -> 5469.3 | ... EC80: =+EB80+EC75 -> 125423.33
C81: Programa R1 (%) | D81: =+D80/$EC$80 -> 0.00090812451 | E81: =+E80/$EC$80 -> 0.0037608633 | F81: =+F80/$EC$80 -> 0.0071825553 | G81: =+G80/$EC$80 -> 0.010863529 | H81: =+H80/$EC$80 -> 0.014183007 | I81: =+I80/$EC$80 -> 0.016966222 | J81: =+J80/$EC$80 -> 0.021637123 | K81: =+K80/$EC$80 -> 0.032190263 | ... EC81: =+EC80/$EC$80 -> 1
C83: Real R1 (HH) | D83: =+D76 -> 103.25 | E83: =+D83+E76 -> 450.4 | F83: =+E83+F76 -> 869.54 | G83: =+F83+G76 -> 1321.63 | H83: =+G83+H76 -> 1728.38 | I83: =+H83+I76 -> 2067.87 | J83: =+I83+J76 -> 2644.12 | K83: =+J83+K76 -> 3958.14 | L83: =+K83+L76 -> 5380.43 | ... EC83: =+EB83+EC76 -> 50288.4
C84: Real R1 (%) | D84: =+D83/$EC$80 -> 0.00082321208 | E84: =+E83/$EC$80 -> 0.0035910384 | F84: =+F83/$EC$80 -> 0.006932841 | G84: =+G83/$EC$80 -> 0.010537354 | H84: =+H83/$EC$80 -> 0.013780371 | I84: =+I83/$EC$80 -> 0.016487124 | J84: =+J83/$EC$80 -> 0.021081564 | K84: =+K83/$EC$80 -> 0.031558244 | ... EC84: =+EC83/$EC$80 -> 0.40094933
C86: Forecast R1 (HH) | D86: =+D78 -> 0 | E86: =+D86+E78 -> 0 | F86: =+E86+F78 -> 0 | G86: =+F86+G78 -> 0 | H86: =+G86+H78 -> 0 | I86: =+H86+I78 -> 0 | J86: =+I86+J78 -> 0 | K86: =+J86+K78 -> 0 | L86: =+K86+L78 -> 0 | ... BD86: =+BC86+BD78 -> 0 | BE86: =SUM($D$76:BE76) -> 50288.4 | BF86: =+BE86+BF78 -> 53304.64 | BG86: =+BF86+BG78 -> 55085.73 | BH86: =+BG86+BH78 -> 58134.19 | BI86: =+BH86+BI78 -> 61032.41 | BJ86: =+BI86+BJ78 -> 63828.12 | BK86: =+BJ86+BK78 -> 65689 | BL86: =+BK86+BL78 -> 68388.13 | BM86: =+BL86+BM78 -> 70288.13 | ... EC86: =+EB86+EC78 -> 131191.63
C87: Forecast R1 (%) | D87: =+D86/$EC$80 -> 0 | E87: =+E86/$EC$80 -> 0 | F87: =+F86/$EC$80 -> 0 | G87: =+G86/$EC$80 -> 0 | H87: =+H86/$EC$80 -> 0 | I87: =+I86/$EC$80 -> 0 | J87: =+J86/$EC$80 -> 0 | K87: =+K86/$EC$80 -> 0 | ... EC87: =+EC86/$EC$80 -> 1.0459906
C90: Spreadsheet Field | D90: 45757 | E90: 45764 | F90: 45771 | G90: 45778 | H90: 45785 | I90: 45792 | J90: 45799 | K90: 45806 | L90: 45813 | M90: 45820 | N90: 45827 | O90: 45834 | P90: 45841 | Q90: 45848 | R90: 45855 | S90: 45862 | T90: 45869 | U90: 45876 | V90: 45883 | W90: 45890 | X90: 45897 | Y90: 45904 | Z90: 45911 | AA90: 45918 | AB90: 45925 | AC90: 45932 | AD90: 45939 | AE90: 45946 | AF90: 45953 | AG90: 45960 | AH90: 45967 | AI90: 45974 | AJ90: 45981 | AK90: 45988 | AL90: 45995 | AM90: 46002 | AN90: 46009 | AO90: 46016 | AP90: 46023 | AQ90: 46030 | AR90: 46037 | AS90: 46044 | AT90: 46051 | AU90: 46058 | AV90: 46065 | AW90: 46072 | AX90: 46079 | AY90: 46086 | AZ90: 46093 | BA90: 46100 | BB90: 46107 | BC90: 46114 | BD90: 46121 | BE90: 46128 | BF90: 46135 | BG90: 46142 | BH90: 46149 | BI90: 46156 | BJ90: 46163 | BK90: 46170 | BL90: 46177 | BM90: 46184 | BN90: 46191 | BO90: 46198 | BP90: 46205 | BQ90: 46212 | BR90: 46219 | BS90: 46226 | BT90: 46233 | BU90: 46240 | BV90: 46247 | BW90: 46254 | BX90: 46261 | BY90: 46268 | BZ90: 46275 | CA90: 46282 | CB90: 46289 | CC90: 46296 | CD90: 46303 | CE90: 46310 | CF90: 46317 | CG90: 46324 | CH90: 46331 | CI90: 46338 | CJ90: 46345 | CK90: 46352 | CL90: 46359 | CM90: 46366 | CN90: 46373 | CO90: 46380 | CP90: 46387 | CQ90: 46394 | CR90: 46401 | CS90: 46408 | CT90: 46415 | CU90: 46422 | CV90: 46429 | CW90: 46436 | CX90: 46443 | CY90: 46450 | CZ90: 46457 | DA90: 46464 | DB90: 46471 | DC90: 46478 | DD90: 46485 | DE90: 46492 | DF90: 46499 | DG90: 46506 | DH90: 46513 | DI90: 46520 | DJ90: 46527 | DK90: 46534 | DL90: 46541 | DM90: 46548 | DN90: 46555 | DO90: 46562 | DP90: 46569 | DQ90: 46576 | DR90: 46583 | DS90: 46590 | DT90: 46597 | DU90: 46604 | DV90: 46611 | DW90: 46618 | DX90: 46625 | DY90: 46632 | DZ90: 46639 | EA90: 46646 | EB90: 46653 | EC90: 46660
C91: BL1 Labor Units | D91: 113.9 | E91: 357.8 | F91: 429.16 | G91: 461.68 | H91: 416.34 | I91: 349.08 | J91: 585.84 | K91: 1323.61 | L91: 1431.89 | M91: 1488.91 | N91: 1472.6 | O91: 487.49 | P91: 418.66 | Q91: 485.83 | R91: 666.17 | S91: 612.82 | T91: 1177.37 | U91: 1218.48 | V91: 2066.28 | W91: 2120.44 | X91: 1348.17 | Y91: 871.32 | Z91: 1160.82 | AA91: 339.16 | AB91: 362.71 | AC91: 517.51 | AD91: 902.42 | AE91: 1149.38 | AF91: 1295.45 | AG91: 1408.63 | AH91: 1753.11 | AI91: 2699.66 | AJ91: 2718.68 | AK91: 2408.41 | AL91: 2350.31 | AM91: 1821.63 | AN91: 1055.1 | AO91: 679.24 | AP91: 605.44 | AQ91: 913.88 | AR91: 916.42 | AS91: 1017.61 | AT91: 783.93 | AU91: 991.34 | AV91: 1074.99 | AW91: 1504.63 | AX91: 1860.03 | AY91: 1565.52 | AZ91: 1771.43 | BA91: 1683.57 | BB91: 1076.8 | BC91: 886.04 | BD91: 1459.94 | BE91: 2047.4 | BF91: 2603.01 | BG91: 2383.62 | BH91: 2008.67 | BI91: 2193.94 | BJ91: 2121.02 | BK91: 1981.68 | BL91: 1907.57 | BM91: 1835.2 | BN91: 1825.21 | BO91: 1968.17 | BP91: 1558.09 | BQ91: 1893.64 | BR91: 2218.38 | BS91: 2968.6 | BT91: 2693.11 | BU91: 2305.58 | BV91: 2335.41 | BW91: 2188.56 | BX91: 2710.24 | BY91: 1792.79 | BZ91: 1778.14 | CA91: 1150.14 | CB91: 1046.67 | CC91: 1532.86 | CD91: 1561.98 | CE91: 1115.34 | CF91: 1107.43 | CG91: 804.25 | CH91: 1261.28 | CI91: 1289.31 | CJ91: 1295.94 | CK91: 1174.46 | CL91: 658.5 | CM91: 168.96 | CN91: 539.19 | CO91: 117.01 | CP91: 311.12 | CQ91: 125.76 | CR91: 111.91 | CS91: 80.24 | CT91: 80.24 | CU91: 80.24 | CV91: 80.24 | CW91: 80.24 | CX91: 80.24 | CY91: 200.54 | CZ91: 131.44 | DA91: 110.54 | DB91: 85.94 | DC91: 29.4 | DD91: 36.74 | DE91: 36.74 | DF91: 36.74 | DG91: 36.74 | DH91: 36.74 | DI91: 36.74 | DJ91: 36.74 | DK91: 29.4 | DL91: 36.74 | DM91: 36.74 | DN91: 36.74 | DO91: 29.4 | DP91: 29.4 | DQ91: 36.74 | DR91: 36.74 | DS91: 29.4 | DT91: 36.74 | DU91: 36.74 | DV91: 41.51 | DW91: 48.67 | DX91: 48.67 | DY91: 72.38 | DZ91: 72.38 | EA91: 58.15 | EB91: 38.93 | EC91: 43.61
C92: Earned Value Labor Units | D92: 103.25 | E92: 347.15 | F92: 419.14 | G92: 452.09 | H92: 406.75 | I92: 339.49 | J92: 576.25 | K92: 1314.02 | L92: 1422.29 | M92: 1466.48 | N92: 1450.26 | O92: 465.54 | P92: 396.71 | Q92: 463.88 | R92: 644.24 | S92: 586.82 | T92: 1148.27 | U92: 1188.67 | V92: 2036 | W92: 2094.84 | X92: 1317.73 | Y92: 947.76 | Z92: 1047.28 | AA92: 299.63 | AB92: 312.6 | AC92: 472.5 | AD92: 598.88 | AE92: 684.41 | AF92: 690.8 | AG92: 715.28 | AH92: 749.68 | AI92: 1792.96 | AJ92: 2134.03 | AK92: 1467.42 | AL92: 1475.09 | AM92: 1394.12 | AN92: 697.74 | AO92: 528.69 | AP92: 562.31 | AQ92: 596.21 | AR92: 574.94 | AS92: 1063.88 | AT92: 1103.1 | AU92: 746 | AV92: 1119.43 | AW92: 1259.41 | AX92: 1408.49 | AY92: 1438.66 | AZ92: 1277.95 | BA92: 771.89 | BB92: 919.68 | BC92: 960.71 | BD92: 664.08 | BE92: 1172.92
C93: Actual Labor Units | D93: 103.25 | E93: 347.15 | F93: 419.14 | G93: 452.09 | H93: 406.75 | I93: 371.07 | J93: 615.72 | K93: 1426.62 | L93: 1578.38 | M93: 1622.56 | N93: 1606.35 | O93: 518.43 | P93: 408.26 | Q93: 518.43 | R93: 813.54 | S93: 864.81 | T93: 1426.26 | U93: 1501.47 | V93: 2404.51 | W93: 2460.03 | X93: 1470.67 | Y93: 1128.49 | Z93: 1481.1 | AA93: 656.74 | AB93: 549.5 | AC93: 509.2 | AD93: 668.44 | AE93: 741.67 | AF93: 749.71 | AG93: 771.81 | AH93: 960.45 | AI93: 2387.78 | AJ93: 2730.6 | AK93: 2177.11 | AL93: 2265 | AM93: 2187.24 | AN93: 1330.12 | AO93: 895.79 | AP93: 625.47 | AQ93: 670.84 | AR93: 643.1 | AS93: 1190.83 | AT93: 1229.45 | AU93: 906.72 | AV93: 1462.47 | AW93: 1800.43 | AX93: 2032.06 | AY93: 2374.46 | AZ93: 2494.13 | BA93: 1642.05 | BB93: 1138.35 | BC93: 1144.15 | BD93: 828.36 | BE93: 1785.38
C94: Remaining Labor Units | BF94: 2266.24 | BG94: 3431.09 | BH94: 3048.46 | BI94: 2898.22 | BJ94: 2795.71 | BK94: 1860.88 | BL94: 2699.13 | BM94: 1900 | BN94: 1537.78 | BO94: 1850.59 | BP94: 1713.11 | BQ94: 2554.57 | BR94: 3864.33 | BS94: 3510.32 | BT94: 3677.71 | BU94: 3119.83 | BV94: 3336.51 | BW94: 3048.47 | BX94: 3697.1 | BY94: 2710.95 | BZ94: 2544.54 | CA94: 1684.79 | CB94: 1569.26 | CC94: 1983.6 | CD94: 1908.39 | CE94: 1517.92 | CF94: 1512.19 | CG94: 1184.94 | CH94: 1539.53 | CI94: 1665.05 | CJ94: 1594.44 | CK94: 1574.86 | CL94: 1069.63 | CM94: 313.23 | CN94: 533.48 | CO94: 278.24 | CP94: 346.56 | CQ94: 228.22 | CR94: 111.99 | CS94: 203.32 | CT94: 80.32 | CU94: 80.32 | CV94: 80.32 | CW94: 80.32 | CX94: 80.32 | CY94: 123.82 | CZ94: 80.32 | DA94: 36.82 | DB94: 36.82 | DC94: 29.46 | DD94: 139.22 | DE94: 62.42 | DF94: 135.22 | DG94: 61.42 | DH94: 36.82 | DI94: 36.82 | DJ94: 36.82 | DK94: 29.46 | DL94: 36.82 | DM94: 36.82 | DN94: 36.82 | DO94: 29.46 | DP94: 29.46 | DQ94: 36.82 | DR94: 36.82 | DS94: 29.46 | DT94: 36.82 | DU94: 36.82 | DV94: 41.59 | DW94: 48.75 | DX94: 48.75 | DY94: 72.45 | DZ94: 72.45 | EA94: 58.23 | EB94: 39 | EC94: 43.67
C136: Forecast
C137: Programado % | D137: =+D146/$EC$146*100 -> 0.22559452 | E137: =+E146/$EC$146*100 -> 0.70865921 | F137: =+F146/$EC$146*100 -> 1.0852168 | G137: =+G146/$EC$146*100 -> 1.5262056 | H137: =+H146/$EC$146*100 -> 1.99737 | I137: =+I146/$EC$146*100 -> 2.7504851 | J137: =+J146/$EC$146*100 -> 3.340737 | K137: =+K146/$EC$146*100 -> 4.5003302 | ... EC137: =+EC146/$EC$146*100 -> 100
C138: Real% | D138: 0.11867508 | E138: 0.35602525 | F138: 0.71205051 | G138: 1.1867508 | H138: 1.6415481 | I138: 2.623589 | J138: 3.4818565 | K138: 4.4734858 | L138: 5.2311018 | M138: 5.8237285 | N138: 6.7798209 | O138: 7.1866391 | P138: 7.8200718 | Q138: 8.2702408 | R138: 8.6397432 | S138: 9.7020557 | T138: 10.502969 | U138: 11.350637 | V138: 12.178422 | W138: 14.022963 | X138: =+X152/$EC$158*100 -> 14.152808 | Y138: =+Y152/$EC$158*100 -> 14.817081 | Z138: =+Z152/$EC$158*100 -> 15.649062 | AA138: =+AA152/$EC$158*100 -> 15.984274 | AB138: =+AB152/$EC$158*100 -> 16.354992 | AC138: =+AC152/$EC$158*100 -> 16.738537
C139: Forecast% | X139: =+X138 -> 14.152808 | Y139: =+Y138 -> 14.817081 | Z139: =+Z138 -> 15.649062 | AA139: =+AA138 -> 15.984274 | AB139: =+AB138 -> 16.354992 | AC139: =+AC138 -> 16.738537 | AD139: =+AD158/$EC$158*100 -> 0 | AE139: =+AE158/$EC$158*100 -> 0 | AF139: =+AF158/$EC$158*100 -> 0 | AG139: =+AG158/$EC$158*100 -> 0 | AH139: =+AH158/$EC$158*100 -> 0 | AI139: =+AI158/$EC$158*100 -> 0 | AJ139: =+AJ158/$EC$158*100 -> 0 | AK139: =+AK158/$EC$158*100 -> 0 | ... EC139: =+EC158/$EC$158*100 -> 100
B141: PROGRAMA REV.0
B142: Avance Programado
C144: Avance En HH | D144: =+D163 -> 45757 | E144: =+E163 -> 45764 | F144: =+F163 -> 45771 | G144: =+G163 -> 45778 | H144: =+H163 -> 45785 | I144: =+I163 -> 45792 | J144: =+J163 -> 45799 | K144: =+K163 -> 45806 | ... EC144: =+EC163 -> 46660
C145: HH Parcial | D145: =+D164 -> 265.4 | E145: =+E164 -> 568.3 | F145: =+F164 -> 443 | G145: =+G164 -> 518.8 | H145: =+H164 -> 554.3 | I145: =+I164 -> 886 | J145: =+J164 -> 694.4 | K145: =+K164 -> 1364.2 | ... EC145: =+EC164 -> 43.7
C146: HH Acumuladas | D146: =+D145 -> 265.4 | E146: =+D146+E145 -> 833.7 | F146: =+E146+F145 -> 1276.7 | G146: =+F146+G145 -> 1795.5 | H146: =+G146+H145 -> 2349.8 | I146: =+H146+I145 -> 3235.8 | J146: =+I146+J145 -> 3930.2 | K146: =+J146+K145 -> 5294.4 | L146: =+K146+L145 -> 6837.3 | ... EC146: =+EB146+EC145 -> 117644.7
B148: Avance real
C150: Avance En HH | D150: =+D144 -> 45757 | E150: =+E144 -> 45764 | F150: =+F144 -> 45771 | G150: =+G144 -> 45778 | H150: =+H144 -> 45785 | I150: =+I144 -> 45792 | J150: =+J144 -> 45799 | K150: =+K144 -> 45806 | ... EC150: =+EC144 -> 46660
C151: HH Parcial | D151: 144.809 | E151: 289.618 | F151: 434.427 | G151: 579.236 | H151: 554.95 | I151: 1198.3 | J151: 1047.27 | K151: 1210 | L151: 695.5 | M151: 697.19 | N151: 1124.8 | O151: 478.6 | P151: 745.2 | Q151: 529.6 | R151: 434.7 | S151: 1497.7 | T151: 962.7 | U151: 1018.9 | V151: 995 | W151: 2217.2 | X151: 1711.6 | Y151: 871.47 | Z151: 1091.49 | AA151: 439.77 | AB151: 486.35 | AC151: 503.18
C152: HH Acumuladas | D152: =+D151 -> 144.809 | E152: =+D152+E151 -> 434.427 | F152: =+E152+F151 -> 868.854 | G152: =+F152+G151 -> 1448.09 | H152: =+G152+H151 -> 2003.04 | I152: =+H152+I151 -> 3201.34 | J152: =+I152+J151 -> 4248.61 | K152: =+J152+K151 -> 5458.61 | L152: =+K152+L151 -> 6154.11 | ... AC152: =+AB152+AC151 -> 21959.56 | AD152: 23063.41 | AE152: =+AD152+AE151 -> 23063.41
B154: Forecast
C156: Avance En HH | D156: =+D150 -> 45757 | E156: =+E150 -> 45764 | F156: =+F150 -> 45771 | G156: =+G150 -> 45778 | H156: =+H150 -> 45785 | I156: =+I150 -> 45792 | J156: =+J150 -> 45799 | K156: =+K150 -> 45806 | ... EC156: =+EC150 -> 46660
C157: HH Parcial | AD157: =+AD172 -> 0 | AE157: =+AE172 -> 0 | AF157: =+AF172 -> 0 | AG157: =+AG172 -> 0 | AH157: =+AH172 -> 0 | AI157: =+AI172 -> 0 | AJ157: =+AJ172 -> 0 | AK157: =+AK172 -> 0 | ... EC157: =+EC172 -> 43.67
C158: HH Acumuladas | AD158: =+AD86 -> 0 | AE158: =+AE86 -> 0 | AF158: =+AF86 -> 0 | AG158: =+AG86 -> 0 | AH158: =+AH86 -> 0 | AI158: =+AI86 -> 0 | AJ158: =+AJ86 -> 0 | AK158: =+AK86 -> 0 | ... EC158: =+EC86 -> 131191.63
B161: PROGRAMA SERVICIO REV.0
C162: INICIO | D162: 45751 | E162: 45758 | F162: 45765 | G162: 45772 | H162: 45779 | I162: 45786 | J162: 45793 | K162: 45800 | L162: 45807 | M162: 45814 | N162: 45821 | O162: 45828 | P162: 45835 | Q162: 45842 | R162: 45849 | S162: 45856 | T162: 45863 | U162: 45870 | V162: 45877 | W162: 45884 | X162: 45891 | Y162: 45898 | Z162: 45905 | AA162: 45912 | AB162: 45919 | AC162: 45926 | AD162: 45933 | AE162: 45940 | AF162: 45947 | AG162: 45954 | AH162: 45961 | AI162: 45968 | AJ162: 45975 | AK162: 45982 | AL162: 45989 | AM162: 45996 | AN162: 46003 | AO162: 46010 | AP162: 46017 | AQ162: 46024 | AR162: 46031 | AS162: 46038 | AT162: 46045 | AU162: 46052 | AV162: 46059 | AW162: 46066 | AX162: 46073 | AY162: 46080 | AZ162: 46087 | BA162: 46094 | BB162: 46101 | BC162: 46108 | BD162: 46115 | BE162: 46122 | BF162: 46129 | BG162: 46136 | BH162: 46143 | BI162: 46150 | BJ162: 46157 | BK162: 46164 | BL162: 46171 | BM162: 46178 | BN162: 46185 | BO162: 46192 | BP162: 46199 | BQ162: 46206 | BR162: 46213 | BS162: 46220 | BT162: 46227 | BU162: 46234 | BV162: 46241 | BW162: 46248 | BX162: 46255 | BY162: 46262 | BZ162: 46269 | CA162: 46276 | CB162: 46283 | CC162: 46290 | CD162: 46297 | CE162: 46304 | CF162: 46311 | CG162: 46318 | CH162: 46325 | CI162: 46332 | CJ162: 46339 | CK162: 46346 | CL162: 46353 | CM162: 46360 | CN162: 46367 | CO162: 46374 | CP162: 46381 | CQ162: 46388 | CR162: 46395 | CS162: 46402 | CT162: 46409 | CU162: 46416 | CV162: 46423 | CW162: 46430 | CX162: 46437 | CY162: 46444 | CZ162: 46451 | DA162: 46458 | DB162: 46465 | DC162: 46472 | DD162: 46479 | DE162: 46486 | DF162: 46493 | DG162: 46500 | DH162: 46507 | DI162: 46514 | DJ162: 46521 | DK162: 46528 | DL162: 46535 | DM162: 46542 | DN162: 46549 | DO162: 46556 | DP162: 46563 | DQ162: 46570 | DR162: 46577 | DS162: 46584 | DT162: 46591 | DU162: 46598 | DV162: 46605 | DW162: 46612 | DX162: 46619 | DY162: 46626 | DZ162: 46633 | EA162: 46640 | EB162: 46647 | EC162: 46654
C163: CORTE | D163: =+D162+6 -> 45757 | E163: =+E162+6 -> 45764 | F163: =+F162+6 -> 45771 | G163: =+G162+6 -> 45778 | H163: =+H162+6 -> 45785 | I163: =+I162+6 -> 45792 | J163: =+J162+6 -> 45799 | K163: =+K162+6 -> 45806 | ... EC163: =+EC162+6 -> 46660
C164: Budgeted Labor Units | D164: 265.4 | E164: 568.3 | F164: 443 | G164: 518.8 | H164: 554.3 | I164: 886 | J164: 694.4 | K164: 1364.2 | L164: 1542.9 | M164: 1285.9 | N164: 1338.5 | O164: 1318.3 | P164: 1211.6 | Q164: 867 | R164: 694.6 | S164: 846.5 | T164: 782.8 | U164: 845.5 | V164: 897.5 | W164: 2470.7 | X164: 1795.9 | Y164: 1011.2 | Z164: 1012.1 | AA164: 960.9 | AB164: 984.8 | AC164: 1208.9 | AD164: 1116.2 | AE164: 1150.8 | AF164: 1361 | AG164: 1331 | AH164: 1271.3 | AI164: 1382 | AJ164: 1495.3 | AK164: 1198.6 | AL164: 1864.4 | AM164: 1987.5 | AN164: 1823.5 | AO164: 817.1 | AP164: 805.6 | AQ164: 872.4 | AR164: 780.9 | AS164: 828.3 | AT164: 1284.9 | AU164: 1101.8 | AV164: 815.3 | AW164: 1299 | AX164: 1174.7 | AY164: 1049.1 | AZ164: 1074.1 | BA164: 1313.6 | BB164: 784.1 | BC164: 920.9 | BD164: 1516 | BE164: 1698.4 | BF164: 2116.7 | BG164: 1929.3 | BH164: 1667 | BI164: 1782.7 | BJ164: 1918.9 | BK164: 1629.7 | BL164: 1881.4 | BM164: 1387.2 | BN164: 1594.6 | BO164: 1744.8 | BP164: 1323.3 | BQ164: 1472.9 | BR164: 2294.5 | BS164: 3012.2 | BT164: 2696 | BU164: 2488.4 | BV164: 2278.5 | BW164: 2034.3 | BX164: 2517.1 | BY164: 1557.1 | BZ164: 1637.7 | CA164: 992.3 | CB164: 928.2 | CC164: 1443.1 | CD164: 1519.7 | CE164: 1119.8 | CF164: 1012.9 | CG164: 770.3 | CH164: 1141.6 | CI164: 1213.4 | CJ164: 1165.1 | CK164: 1161.3 | CL164: 585.7 | CM164: 154.1 | CN164: 445.8 | CO164: 135 | CP164: 305.3 | CQ164: 140.3 | CR164: 108.9 | CS164: 80.4 | CT164: 80.4 | CU164: 80.4 | CV164: 80.4 | CW164: 80.4 | CX164: 80.4 | CY164: 123.9 | CZ164: 80.4 | DA164: 36.9 | DB164: 36.9 | DC164: 29.5 | DD164: 36.9 | DE164: 36.9 | DF164: 36.9 | DG164: 36.9 | DH164: 36.9 | DI164: 36.9 | DJ164: 36.9 | DK164: 29.5 | DL164: 36.9 | DM164: 36.9 | DN164: 36.9 | DO164: 29.5 | DP164: 29.5 | DQ164: 36.9 | DR164: 36.9 | DS164: 29.5 | DT164: 36.9 | DU164: 36.9 | DV164: 41.6 | DW164: 48.8 | DX164: 48.8 | DY164: 72.5 | DZ164: 72.5 | EA164: 58.3 | EB164: 39 | EC164: 43.7
C165: Budgeted Labor Units (Acumulado) | D165: =+D164 -> 265.4 | E165: =+D165+E164 -> 833.7 | F165: =+E165+F164 -> 1276.7 | G165: =+F165+G164 -> 1795.5 | H165: =+G165+H164 -> 2349.8 | I165: =+H165+I164 -> 3235.8 | J165: =+I165+J164 -> 3930.2 | K165: =+J165+K164 -> 5294.4 | L165: =+K165+L164 -> 6837.3 | ... EC165: =+EB165+EC164 -> 117644.7
C166: Av. Programado (%) | D166: =+D165/$EC$165 -> 0.0022559452 | E166: =+E165/$EC$165 -> 0.0070865921 | F166: =+F165/$EC$165 -> 0.010852168 | G166: =+G165/$EC$165 -> 0.015262056 | H166: =+H165/$EC$165 -> 0.0199737 | I166: =+I165/$EC$165 -> 0.027504851 | J166: =+J165/$EC$165 -> 0.03340737 | K166: =+K165/$EC$165 -> 0.045003302 | ... EC166: =+EC165/$EC$165 -> 1
C168: Earned Value Labor Units | D168: 144.809 | E168: 289.618 | F168: 434.427 | G168: 579.236 | H168: 554.95 | I168: 1198.3 | J168: 1047.27 | K168: 1210 | L168: 695.5 | M168: 697.19 | N168: 1124.8 | O168: 478.6 | P168: 745.2 | Q168: 529.6 | R168: 434.7 | S168: 1497.7
C169: Earned Value Labor Units (Acumulado) | D169: =+D168 -> 144.809 | E169: =+D169+E168 -> 434.427 | F169: =+E169+F168 -> 868.854 | G169: =+F169+G168 -> 1448.09 | H169: =+G169+H168 -> 2003.04 | I169: =+H169+I168 -> 3201.34 | J169: =+I169+J168 -> 4248.61 | K169: =+J169+K168 -> 5458.61 | L169: =+K169+L168 -> 6154.11 | ... Q169: =+P169+Q168 -> 9729.5 | R169: =SUM($D$92:R92) -> 10267.54 | S169: =SUM($D$93:S93) -> 12072.55 | T169: =SUM($D$93:T93) -> 13498.81 | U169: =SUM($D$93:U93) -> 15000.28 | V169: =SUM($D$93:V93) -> 17404.79 | W169: =SUM($D$93:W93) -> 19864.82 | X169: =SUM($D$93:X93) -> 21335.49
C170: Curva Av. Real | D170: =+D169/$EC$165 -> 0.0012309012 | E170: =+E169/$EC$165 -> 0.0036927035 | F170: =+F169/$EC$165 -> 0.0073854071 | G170: =+G169/$EC$165 -> 0.012309012 | H170: =+H169/$EC$165 -> 0.017026181 | I170: =+I169/$EC$165 -> 0.027211936 | J170: =+J169/$EC$165 -> 0.036113909 | K170: =+K169/$EC$165 -> 0.046399115 | ... R170: =+R169/$EC$165 -> 0.08727584 | S170: =+S169/$EC$173 -> 0.11808198 | T170: =+T169/$EC$173 -> 0.13203227 | U170: =+U169/$EC$173 -> 0.14671819 | V170: =+V169/$EC$173 -> 0.17023678 | W170: =+W169/$EC$173 -> 0.1942984 | X170: =+X169/$EC$173 -> 0.20868307 | Y170: =+Y169/$EC$173 -> 0 | Z170: =+Z169/$EC$173 -> 0 | ... EC170: =+EC169/$EC$173 -> 0
C172: Remaining Labor Units (Acumulado) | X172: =+X94 -> 0 | Y172: =+Y94 -> 0 | Z172: =+Z94 -> 0 | AA172: =+AA94 -> 0 | AB172: =+AB94 -> 0 | AC172: =+AC94 -> 0 | AD172: =+AD94 -> 0 | AE172: =+AE94 -> 0 | ... EC172: =+EC94 -> 43.67
X173: =+X169 -> 21335.49 | Y173: =+X173+Y172 -> 21335.49 | Z173: =+Y173+Z172 -> 21335.49 | AA173: =+Z173+AA172 -> 21335.49 | AB173: =+AA173+AB172 -> 21335.49 | AC173: =+AB173+AC172 -> 21335.49 | AD173: =+AC173+AD172 -> 21335.49 | AE173: =+AD173+AE172 -> 21335.49 | AF173: =+AE173+AF172 -> 21335.49 | ... EC173: =+EB173+EC172 -> 102238.72
C174: Forecast | D174: =+D172/$EC$165 -> 0 | E174: =+E172/$EC$165 -> 0 | F174: =+F172/$EC$165 -> 0 | G174: =+G172/$EC$165 -> 0 | H174: =+H172/$EC$165 -> 0 | I174: =+I172/$EC$165 -> 0 | J174: =+J172/$EC$165 -> 0 | K174: =+K172/$EC$165 -> 0 | ... M174: =+M172/$EC$165 -> 0 | N174: =+N173/$EC$165 -> 0 | O174: =+O173/$EC$165 -> 0 | P174: =+P173/$EC$165 -> 0 | Q174: =+Q173/$EC$165 -> 0 | R174: =+R173/$EC$165 -> 0 | S174: =+S173/$EC$173 -> 0 | T174: =+T173/$EC$173 -> 0 | U174: =+U173/$EC$173 -> 0 | V174: =+V173/$EC$173 -> 0 | W174: =+W173/$EC$173 -> 0 | X174: =+X173/$EC$173 -> 0.20868307 | Y174: =+Y173/$EC$173 -> 0.20868307 | Z174: =+Z173/$EC$173 -> 0.20868307 | ... EC174: =+EC173/$EC$173 -> 1

Sheet Histog Sem R1
B3: HISTROGRAMA SEMANAL
B58: Semana | C58: 45757 | D58: 45764 | E58: 45771 | F58: 45778 | G58: 45785 | H58: 45792 | I58: 45799 | J58: 45806 | K58: 45813 | L58: 45820 | M58: 45827 | N58: 45834 | O58: 45841 | P58: 45848 | Q58: 45855 | R58: 45862 | S58: 45869 | T58: 45876 | U58: 45883 | V58: 45890 | W58: 45897 | X58: 45904 | Y58: 45911 | Z58: 45918 | AA58: 45925 | AB58: 45932 | AC58: 45939 | AD58: 45946 | AE58: 45953 | AF58: 45960 | AG58: 45967 | AH58: 45974 | AI58: 45981 | AJ58: 45988 | AK58: 45995 | AL58: 46002 | AM58: 46009 | AN58: 46016 | AO58: 46023 | AP58: 46030 | AQ58: 46037 | AR58: 46044 | AS58: 46051 | AT58: 46058 | AU58: 46065 | AV58: 46072 | AW58: 46079 | AX58: 46086 | AY58: 46093 | AZ58: 46100 | BA58: 46107 | BB58: 46114 | BC58: 46121 | BD58: 46128 | BE58: 46135 | BF58: 46142 | BG58: 46149 | BH58: 46156 | BI58: 46163 | BJ58: 46170 | BK58: 46177 | BL58: 46184 | BM58: 46191 | BN58: 46198 | BO58: 46205 | BP58: 46212 | BQ58: 46219 | BR58: 46226 | BS58: 46233 | BT58: 46240 | BU58: 46247 | BV58: 46254 | BW58: 46261 | BX58: 46268 | BY58: 46275 | BZ58: 46282 | CA58: 46289 | CB58: 46296 | CC58: 46303 | CD58: 46310 | CE58: 46317 | CF58: 46324 | CG58: 46331 | CH58: 46338 | CI58: 46345 | CJ58: 46352 | CK58: 46359 | CL58: 46366 | CM58: 46373 | CN58: 46380 | CO58: 46387 | CP58: 46394 | CQ58: 46401 | CR58: 46408 | CS58: 46415 | CT58: 46422 | CU58: 46429 | CV58: 46436 | CW58: 46443 | CX58: 46450 | CY58: 46457 | CZ58: 46464 | DA58: 46471 | DB58: 46478 | DC58: 46485 | DD58: 46492 | DE58: 46499 | DF58: 46506 | DG58: 46513 | DH58: 46520 | DI58: 46527 | DJ58: 46534 | DK58: 46541 | DL58: 46548 | DM58: 46555 | DN58: 46562 | DO58: 46569 | DP58: 46576 | DQ58: 46583 | DR58: 46590 | DS58: 46597 | DT58: 46604 | DU58: 46611 | DV58: 46618 | DW58: 46625 | DX58: 46632 | DY58: 46639 | DZ58: 46646 | EA58: 46653 | EB58: 46660
B59: HH Prog | AD59: =+AD67+AD73 -> 1090.7 | AE59: =+AE67+AE73 -> 1256.93 | AF59: =+AF67+AF73 -> 1371.12 | AG59: =+AG67+AG73 -> 1755.59 | AH59: =+AH67+AH73 -> 2703.42 | AI59: =+AI67+AI73 -> 2723.18 | AJ59: =+AJ67+AJ73 -> 2413.97 | AK59: =+AK67+AK73 -> 2356.32 | ... EB59: =+EB67+EB73 -> 43.6
B60: FTE Parcial | AD60: =+AD68+AD74 -> 19.100964 | AE60: =+AE68+AE74 -> 22.989714 | AF60: =+AF68+AF74 -> 25.265893 | AG60: =+AG68+AG74 -> 30.13625 | AH60: =+AH68+AH74 -> 45.985286 | AI60: =+AI68+AI74 -> 45.464964 | AJ60: =+AJ68+AJ74 -> 41.360429 | AK60: =+AK68+AK74 -> 39.852536 | ... EB60: =+EB68+EB74 -> 1.09
B61: HH Real | C61: 144.809 | D61: 289.618 | E61: 434.427 | F61: 579.236 | G61: 554.95 | H61: 1198.3 | I61: 1047.27 | J61: 1209.97 | K61: 695.5 | L61: 697.19 | M61: 1125.0025 | N61: 495.22754 | O61: 728.5575 | P61: 528.9625 | Q61: 435.0775 | R61: 1497.7725 | S61: 962.71 | T61: 1018.902 | U61: 994.9815 | V61: 2216.9557 | W61: 1711.7525 | X61: 871.4085 | Y61: 1091.4879 | Z61: 439.2095 | AA61: 229.7144 | AB61: 325.0619 | AC61: =1581.93955000003-313 -> 1268.9396 | AD61: =+AD69+AD75 -> 919.7 | AE61: =+AE69+AE75 -> 1101.89 | AF61: =+AF69+AF75 -> 1190.43 | AG61: =+AG69+AG75 -> 1192.45 | AH61: =+AH69+AH75 -> 2069.51 | AI61: =+AI69+AI75 -> 2324.13 | AJ61: =+AJ69+AJ75 -> 2048.37 | AK61: =+AK69+AK75 -> 2307.32 | ... BD61: =+BD69+BD75 -> 1157.94
B62: FTE Parcial Real | C62: 3.620225 | D62: 7.24045 | E62: 10.860675 | F62: 14.4809 | G62: 13.87375 | H62: 29.9575 | I62: 26.18175 | J62: 30.24925 | K62: 17.3875 | L62: 17.42975 | M62: 28.125062 | N62: 12.380689 | O62: 18.213938 | P62: 13.224063 | Q62: 10.876937 | R62: 37.444312 | S62: 24.06775 | T62: 25.47255 | U62: 24.874537 | V62: 55.423891 | W62: 42.793812 | X62: 21.785213 | Y62: 27.287196 | Z62: 10.980237 | AA62: 5.74286 | AB62: 8.1265475 | AC62: 27.98884 | AD62: =+AD70+AD76 -> 17.604286 | AE62: =+AE70+AE76 -> 20.320786 | AF62: =+AF70+AF76 -> 21.451393 | AG62: =+AG70+AG76 -> 21.892964 | AH62: =+AH70+AH76 -> 31.993357 | AI62: =+AI70+AI76 -> 35.938393 | AJ62: =+AJ70+AJ76 -> 32.582786 | AK62: =+AK70+AK76 -> 35.548786 | ... BD62: =+BD70+BD76 -> 23.497071
B66: GABINETE
B67: HH Prog Gabinete | AD67: 328.49 | AE67: 469.8 | AF67: 529.99 | AG67: 471.93 | AH67: 687.4 | AI67: 612.49 | AJ67: 641.68 | AK67: 577.81 | AL67: 378.4 | AM67: 796.72 | AN67: 482.36 | AO67: 430.28 | AP67: 587.74 | AQ67: 533.23 | AR67: 474.42 | AS67: 530.71 | AT67: 495.91 | AU67: 401.11 | AV67: 399.48 | AW67: 751.11 | AX67: 508.42 | AY67: 519.21 | AZ67: 413.89 | BA67: 521.14 | BB67: 690.34 | BC67: 672.87 | BD67: 974.05 | BE67: 1116.95 | BF67: 1422.68 | BG67: 1274.13 | BH67: 1395.98 | BI67: 958.58 | BJ67: 1265.81 | BK67: 1184.97 | BL67: 1072.59 | BM67: 948.62 | BN67: 1128.6 | BO67: 838.97 | BP67: 1180.61 | BQ67: 1626.35 | BR67: 2522.41 | BS67: 2504.32 | BT67: 2309.83 | BU67: 2339.66 | BV67: 2192.81 | BW67: 2714.49 | BX67: 1797.04 | BY67: 1782.39 | BZ67: 1154.39 | CA67: 1050.07 | CB67: 1537.17 | CC67: 1566.49 | CD67: 1118.95 | CE67: 1111.94 | CF67: 808.77 | CG67: 1265.8 | CH67: 1293.82 | CI67: 1300.45 | CJ67: 1178.97 | CK67: 663.01 | CL67: 172.58 | CM67: 543.7 | CN67: 121.52 | CO67: 314.73 | CP67: 125.75 | CQ67: 111.9 | CR67: 80.24 | CS67: 80.24 | CT67: 80.24 | CU67: 80.24 | CV67: 80.24 | CW67: 80.24 | CX67: 200.54 | CY67: 131.44 | CZ67: 110.54 | DA67: 85.94 | DB67: 29.39 | DC67: 36.74 | DD67: 36.74 | DE67: 36.74 | DF67: 36.74 | DG67: 36.74 | DH67: 36.74 | DI67: 36.74 | DJ67: 29.39 | DK67: 36.74 | DL67: 36.74 | DM67: 36.74 | DN67: 29.39 | DO67: 29.39 | DP67: 36.74 | DQ67: 36.74 | DR67: 29.39 | DS67: 36.74 | DT67: 36.74 | DU67: 41.51 | DV67: 48.66 | DW67: 48.66 | DX67: 72.37 | DY67: 72.37 | DZ67: 58.14 | EA67: 38.93 | EB67: 43.6
B68: FTE Parcial Gabinete | AD68: =+AD67/40 -> 8.21225 | AE68: =+AE67/40 -> 11.745 | AF68: =+AF67/40 -> 13.24975 | AG68: =+AG67/40 -> 11.79825 | AH68: =+AH67/40 -> 17.185 | AI68: =+AI67/40 -> 15.31225 | AJ68: =+AJ67/40 -> 16.042 | AK68: =+AK67/40 -> 14.44525 | ... EB68: =+EB67/40 -> 1.09
B69: HH Real | AD69: 416.8 | AE69: 427.42 | AF69: 414.89 | AG69: 453.41 | AH69: 226.7 | AI69: 255.41 | AJ69: 309.9 | AK69: 241.46 | AL69: 199.04 | AM69: 320.47 | AN69: 334 | AO69: 264.61 | AP69: 250.19 | AQ69: 217.32 | AR69: 319.86 | AS69: 337.27 | AT69: 316.75 | AU69: 247.98 | AV69: 288.2 | AW69: 337.74 | AX69: 209.96 | AY69: 330.06 | AZ69: 222.5 | BA69: =+BA92 -> 381.95 | BB69: =+BB92 -> 506.62 | BC69: =+BC92 -> 1158.19 | BD69: =+BD92 -> 649.14 | BE69: =+BE92 -> 0 | BF69: =+BF92 -> 0 | BG69: =+BG92 -> 0 | BH69: =+BH92 -> 0 | ... EB69: =+EB92 -> 0
B70: FTE Parcial Real | AD70: =+AD69/40 -> 10.42 | AE70: =+AE69/40 -> 10.6855 | AF70: =+AF69/40 -> 10.37225 | AG70: =+AG69/40 -> 11.33525 | AH70: =+AH69/40 -> 5.6675 | AI70: =+AI69/40 -> 6.38525 | AJ70: =+AJ69/40 -> 7.7475 | AK70: =+AK69/40 -> 6.0365 | ... EB70: =+EB69/40 -> 0
B72: TERRENO
B73: HH Prog Terreno | AD73: 762.21 | AE73: 787.13 | AF73: 841.13 | AG73: 1283.66 | AH73: 2016.02 | AI73: 2110.69 | AJ73: 1772.29 | AK73: 1778.51 | AL73: 1447.03 | AM73: 262.18 | AN73: 199.71 | AO73: 178.15 | AP73: 331.73 | AQ73: 388.78 | AR73: 548.78 | AS73: 258.81 | AT73: 499.95 | AU73: 678.13 | AV73: 1109.39 | AW73: 1113.17 | AX73: 1061.35 | AY73: 1256.47 | AZ73: 1273.92 | BA73: 559.91 | BB73: 199.95 | BC73: 790.46 | BD73: 1077.61 | BE73: 1490.3 | BF73: 965.19 | BG73: 737.93 | BH73: 802.21 | BI73: 1165.84 | BJ73: 720.12 | BK73: 726.86 | BL73: 766.86 | BM73: 880.84 | BN73: 843.82 | BO73: 722.52 | BP73: 717.28 | BQ73: 595.43 | BR73: 450.43 | BS73: 193.04 | BT73: 0 | BU73: 0 | BV73: 0 | BW73: 0 | BX73: 0 | BY73: 0 | BZ73: 0 | CA73: 0 | CB73: 0 | CC73: 0 | CD73: 0 | CE73: 0 | CF73: 0 | CG73: 0 | CH73: 0 | CI73: 0 | CJ73: 0 | CK73: 0 | CL73: 0 | CM73: 0 | CN73: 0 | CO73: 0 | CP73: 0 | CQ73: 0 | CR73: 0 | CS73: 0 | CT73: 0 | CU73: 0 | CV73: 0 | CW73: 0 | CX73: 0 | CY73: 0 | CZ73: 0 | DA73: 0 | DB73: 0 | DC73: 0 | DD73: 0 | DE73: 0 | DF73: 0 | DG73: 0 | DH73: 0 | DI73: 0 | DJ73: 0 | DK73: 0 | DL73: 0 | DM73: 0 | DN73: 0 | DO73: 0 | DP73: 0 | DQ73: 0 | DR73: 0 | DS73: 0 | DT73: 0 | DU73: 0 | DV73: 0 | DW73: 0 | DX73: 0 | DY73: 0 | DZ73: 0 | EA73: 0 | EB73: 0
B74: FTE Parcial Terreno | AD74: =+AD73/70 -> 10.888714 | AE74: =+AE73/70 -> 11.244714 | AF74: =+AF73/70 -> 12.016143 | AG74: =+AG73/70 -> 18.338 | AH74: =+AH73/70 -> 28.800286 | AI74: =+AI73/70 -> 30.152714 | AJ74: =+AJ73/70 -> 25.318429 | AK74: =+AK73/70 -> 25.407286 | ... EB74: =+EB73/70 -> 0
B75: HH Real | AD75: 502.9 | AE75: 674.47 | AF75: 775.54 | AG75: 739.04 | AH75: 1842.81 | AI75: 2068.72 | AJ75: 1738.47 | AK75: 2065.86 | AL75: 1241.34 | AM75: 241.88 | AN75: 83.74 | AO75: -0.04 | AP75: 0.02 | AQ75: -0.02 | AR75: 967.75 | AS75: 923.78 | AT75: 632.39 | AU75: 1141.4 | AV75: 1157.21 | AW75: 877.01 | AX75: 1170.48 | AY75: 1768.4 | AZ75: 643.17 | BA75: =+BA88 -> 162.31 | BB75: =+BB88 -> 607.92 | BC75: =+BC88 -> 3225.04 | BD75: =+BD88 -> 508.8 | BE75: =+BE88 -> 0 | BF75: =+BF88 -> 0 | BG75: =+BG88 -> 0 | BH75: =+BH88 -> 0 | ... EB75: =+EB88 -> 0
B76: FTE Parcial Real | AD76: =+AD75/70 -> 7.1842857 | AE76: =+AE75/70 -> 9.6352857 | AF76: =+AF75/70 -> 11.079143 | AG76: =+AG75/70 -> 10.557714 | AH76: =+AH75/70 -> 26.325857 | AI76: =+AI75/70 -> 29.553143 | AJ76: =+AJ75/70 -> 24.835286 | AK76: =+AK75/70 -> 29.512286 | ... EB76: =+EB75/70 -> 0
A80: Activity ID | B80: Spreadsheet Field | C80: =+C58 -> 45757 | D80: =+D58 -> 45764 | E80: =+E58 -> 45771 | F80: =+F58 -> 45778 | G80: =+G58 -> 45785 | H80: =+H58 -> 45792 | I80: =+I58 -> 45799 | J80: =+J58 -> 45806 | ... EB80: =+EB58 -> 46660
A81: CMDIC AGP HH Terreno | B81: Actual Labor Units | I81: 246.48 | J81: 1067.89 | K81: 1173.58 | L81: 1173.58 | M81: 1173.58 | N81: 85.89 | R81: 99.56 | S81: 849.95 | T81: 907.59 | U81: 1758.83 | V81: 1858.83 | W81: 957 | X81: 505.97 | Y81: 746.29 | Z81: 117.27 | AA81: 82.04 | AB81: 162.04 | AC81: 552.94 | AD81: 729.14 | AE81: 748.54 | AF81: 775.54
A82: CMDIC AGP HH Terreno | B82: Remaining Labor Units | AG82: 678.58 | AH82: 1955.35 | AI82: 2218.91 | AJ82: 2233.85 | AK82: 1966.72 | AL82: 1408.73 | AM82: 283.16 | AN82: 180.69 | AO82: 148.98 | AP82: 346.04 | AQ82: 388.78 | AR82: 388.78 | AS82: 298.81 | AT82: 559.95 | AU82: 658.13 | AV82: 1285.08 | AW82: 1033.17 | AX82: 1081.35 | AY82: 1209.81 | AZ82: 1260.59 | BA82: 639.91 | BB82: 149.39 | BC82: 783.8 | BD82: 1124.27 | BE82: 1490.3 | BF82: 965.19 | BG82: 788.49 | BH82: 762.21 | BI82: 1165.84 | BJ82: 760.12 | BK82: 726.86 | BL82: 756.86 | BM82: 850.84 | BN82: 843.82 | BO82: 722.52 | BP82: 747.28 | BQ82: 625.43 | BR82: 470.43 | BS82: 193.04
A84: CMDIC AGP HH Oficina | B84: Actual Labor Units | C84: 101.39 | D84: 345.29 | E84: 417.6 | F84: 450.75 | G84: 405.41 | H84: 338.15 | I84: 328.43 | J84: 244.79 | K84: 247.38 | L84: 300.36 | M84: 284.23 | N84: 387.54 | O84: 404.6 | P84: 471.77 | Q84: 652.14 | R84: 499.3 | S84: 313.49 | T84: 296.96 | U84: 293.52 | V84: 250.47 | W84: 377.26 | X84: 351.45 | Y84: 399.69 | Z84: 209.39 | AA84: 268.31 | AB84: 338.66 | AC84: 300.98 | AD84: 386.83 | AE84: 381.34 | AF84: 414.89
A85: CMDIC AGP HH Oficina | B85: Remaining Labor Units | AG85: 367.44 | AH85: 358.29 | AI85: 494.84 | AJ85: 537.18 | AK85: 436.63 | AL85: 340.43 | AM85: 659.02 | AN85: 504.9 | AO85: 493.44 | AP85: 736.04 | AQ85: 703.04 | AR85: 576.49 | AS85: 561.93 | AT85: 649.06 | AU85: 489.11 | AV85: 457.19 | AW85: 819.89 | AX85: 539.3 | AY85: 530.41 | AZ85: 462.13 | BA85: 484.36 | BB85: 748.65 | BC85: 675.56 | BD85: 955.41 | BE85: 1112.97 | BF85: 1513.48 | BG85: 1272.59 | BH85: 1434.09 | BI85: 935.23 | BJ85: 1285.25 | BK85: 1196.74 | BL85: 1109.02 | BM85: 939.55 | BN85: 1111.84 | BO85: 840.16 | BP85: 1178.97 | BQ85: 1606.32 | BR85: 2586.52 | BS85: 2544.44 | BT85: 2359.77 | BU85: 2364.06 | BV85: 2211.69 | BW85: 2722.33 | BX85: 1797.99 | BY85: 1783.33 | BZ85: 1155.33 | CA85: 1050.82 | CB85: 1538.13 | CC85: 1567.54 | CD85: 1119.8 | CE85: 1112.99 | CF85: 809.82 | CG85: 1266.85 | CH85: 1294.88 | CI85: 1301.51 | CJ85: 1180.03 | CK85: 664.07 | CL85: 173.42 | CM85: 544.75 | CN85: 122.57 | CO85: 315.57 | CP85: 125.76 | CQ85: 111.91 | CR85: 80.24 | CS85: 80.24 | CT85: 80.24 | CU85: 80.24 | CV85: 80.24 | CW85: 80.24 | CX85: 200.54 | CY85: 131.44 | CZ85: 110.54 | DA85: 85.94 | DB85: 29.4 | DC85: 36.74 | DD85: 36.74 | DE85: 36.74 | DF85: 36.74 | DG85: 36.74 | DH85: 36.74 | DI85: 36.74 | DJ85: 29.4 | DK85: 36.74 | DL85: 36.74 | DM85: 36.74 | DN85: 29.4 | DO85: 29.4 | DP85: 36.74 | DQ85: 36.74 | DR85: 29.4 | DS85: 36.74 | DT85: 36.74 | DU85: 41.51 | DV85: 48.67 | DW85: 48.67 | DX85: 72.38 | DY85: 72.38 | DZ85: 58.15 | EA85: 38.93 | EB85: 43.61
A88: =+A81 -> CMDIC AGP HH Terreno | I88: 246.48 | J88: 1177.54 | K88: 1329.66 | L88: 1329.66 | M88: 1329.66 | N88: 130.49 | Q88: 138.09 | R88: 348.3 | S88: 1094.21 | T88: 1190.86 | U88: 2100.63 | V88: 2200.63 | W88: 1078.66 | X88: 758.31 | Y88: 1065.42 | Z88: 436.39 | AA88: 260.05 | AB88: 151.91 | AC88: 366.86 | AD88: 394.89 | AE88: 414.29 | AF88: 441.29 | AG88: 703.1 | AH88: 2046.56 | AI88: 2422.56 | AJ88: 1919.16 | AK88: 2019.79 | AL88: 1992.24 | AM88: 1113.31 | AN88: 691.29 | AO88: 367.08 | AP88: 367.08 | AQ88: 367.08 | AR88: 967.75 | AS88: 923.78 | AT88: 632.39 | AU88: 1141.4 | AV88: 1157.21 | AW88: 877.01 | AX88: 1170.48 | AY88: 1768.4 | AZ88: 643.17 | BA88: 162.31 | BB88: 607.92 | BC88: 3225.04 | BD88: =+BD89-BC89 -> 508.8
A89: ACUM | C89: 0 | D89: 0 | E89: 0 | F89: 0 | G89: 0 | H89: 0 | I89: 246.48 | J89: =+I89+J88 -> 1424.02 | K89: =+J89+K88 -> 2753.68 | L89: =+K89+L88 -> 4083.34 | M89: =+L89+M88 -> 5413 | N89: =+M89+N88 -> 5543.49 | O89: =+N89+O88 -> 5543.49 | P89: =+O89+P88 -> 5543.49 | Q89: =+P89+Q88 -> 5681.58 | ... BC89: =+BB89+BC88 -> 45270.39 | BD89: =SUM($C$103:BD103) -> 45779.19
A92: CMDIC AGP HH Oficina | C92: 104.53 | D92: 348.43 | E92: 420.58 | F92: 453.63 | G92: 408.29 | H92: 372.61 | I92: 370.78 | J92: 250.62 | K92: 250.25 | L92: 296.2 | M92: 279.94 | N92: 391.02 | O92: 411.34 | P92: 521.5 | Q92: 678.52 | R92: 517.67 | S92: 331.75 | T92: 310.47 | U92: 303.86 | V92: 258.74 | W92: 392 | X92: 370.17 | Y92: 415.66 | Z92: 219.69 | AA92: 288.8 | AB92: 370.63 | AC92: 334.54 | AD92: 431.8 | AE92: 423.58 | AF92: 420.72 | AG92: 329.41 | AH92: 370.17 | AI92: 336.02 | AJ92: 285.7 | AK92: 272.99 | AL92: 211.4 | AM92: 305.53 | AN92: 285.83 | AO92: 334.86 | AP92: 379.66 | AQ92: 352.33 | AR92: 319.86 | AS92: 337.27 | AT92: 316.75 | AU92: 247.98 | AV92: 288.2 | AW92: 337.74 | AX92: 209.96 | AY92: 330.06 | AZ92: 222.5 | BA92: 381.95 | BB92: 506.62 | BC92: 1158.19 | BD92: =+BD93-BC93 -> 649.14
A93: ACUM | C93: 101.39 | D93: =+C93+D92 -> 449.82 | E93: =+D93+E92 -> 870.4 | F93: =+E93+F92 -> 1324.03 | G93: =+F93+G92 -> 1732.32 | H93: =+G93+H92 -> 2104.93 | I93: =+H93+I92 -> 2475.71 | J93: =+I93+J92 -> 2726.33 | K93: =+J93+K92 -> 2976.58 | ... BC93: =+BB93+BC92 -> 19066.16 | BD93: =SUM($C$105:BD105) -> 19715.3
A95: Total Acum | C95: 101.39 | D95: 446.68 | E95: 864.28 | F95: 1315.03 | G95: 1720.44 | H95: 2058.59 | I95: 2633.5 | J95: 3946.18 | K95: 5367.14 | L95: 6841.08 | M95: 8298.89 | N95: 8772.32 | O95: 9176.92 | P95: 9648.69 | Q95: 10300.83 | R95: 10899.69 | S95: 12063.13 | T95: 13267.68 | U95: 15320.03 | V95: 17429.33 | W95: 18763.59 | X95: 19621.01 | Y95: 20766.99 | Z95: 21093.65 | AA95: 21444 | AB95: 21944.7 | AC95: 22798.62 | AD95: 23914.59 | AE95: 25044.47 | AF95: 26234.9 | AG95: 27427.35 | AH95: 29496.86 | AI95: 31820.99 | AJ95: 33869.36 | AK95: 36176.68 | AL95: 37617.06 | AM95: 38179.41 | AN95: 38597.15 | AO95: 38861.72 | AP95: 39111.93 | AQ95: 39329.23 | AR95: 40088.86 | AS95: 49694.77 | AT95: =+AT89+AT93 -> 49900.41 | AU95: =+AU89+AU93 -> 51289.79 | AV95: =+AV89+AV93 -> 52735.2 | AW95: =+AW89+AW93 -> 53949.95 | AX95: =+AX89+AX93 -> 55330.39 | AY95: =+AY89+AY93 -> 57428.85 | AZ95: =+AZ89+AZ93 -> 58294.52 | BA95: =+BA89+BA93 -> 58838.78 | ... BD95: =+BD89+BD93 -> 65494.49
AX96: =+AX95-AW95 -> 1380.44 | AY96: =+AY95-AX95 -> 2098.46 | AZ96: =+AZ95-AY95 -> 865.67 | BA96: =+BA95-AZ95 -> 544.26 | BB96: =+BB95-BA95 -> 1114.54 | BC96: =+BC95-BB95 -> 4383.23 | BD96: =+BD95-BC95 -> 1157.94
A102: Activity ID | B102: Spreadsheet Field | C102: 45751 | D102: 45758 | E102: 45765 | F102: 45772 | G102: 45779 | H102: 45786 | I102: 45793 | J102: 45800 | K102: 45807 | L102: 45814 | M102: 45821 | N102: 45828 | O102: 45835 | P102: 45842 | Q102: 45849 | R102: 45856 | S102: 45863 | T102: 45870 | U102: 45877 | V102: 45884 | W102: 45891 | X102: 45898 | Y102: 45905 | Z102: 45912 | AA102: 45919 | AB102: 45926 | AC102: 45933 | AD102: 45940 | AE102: 45947 | AF102: 45954 | AG102: 45961 | AH102: 45968 | AI102: 45975 | AJ102: 45982 | AK102: 45989 | AL102: 45996 | AM102: 46003 | AN102: 46010 | AO102: 46017 | AP102: 46024 | AQ102: 46031 | AR102: 46038 | AS102: 46045 | AT102: 46052 | AU102: 46059 | AV102: 46066 | AW102: 46073 | AX102: 46080 | AY102: 46087 | AZ102: 46094 | BA102: 46101 | BB102: 46108 | BC102: 46115 | BD102: 46122 | BE102: 46129 | BF102: 46136 | BG102: 46143 | BH102: 46150 | BI102: 46157 | BJ102: 46164 | BK102: 46171 | BL102: 46178 | BM102: 46185 | BN102: 46192 | BO102: 46199 | BP102: 46206 | BQ102: 46213 | BR102: 46220 | BS102: 46227 | BT102: 46234 | BU102: 46241 | BV102: 46248 | BW102: 46255 | BX102: 46262 | BY102: 46269 | BZ102: 46276 | CA102: 46283 | CB102: 46290 | CC102: 46297 | CD102: 46304 | CE102: 46311 | CF102: 46318 | CG102: 46325 | CH102: 46332 | CI102: 46339 | CJ102: 46346 | CK102: 46353 | CL102: 46360 | CM102: 46367 | CN102: 46374 | CO102: 46381 | CP102: 46388 | CQ102: 46395 | CR102: 46402 | CS102: 46409 | CT102: 46416 | CU102: 46423 | CV102: 46430 | CW102: 46437 | CX102: 46444 | CY102: 46451 | CZ102: 46458 | DA102: 46465 | DB102: 46472 | DC102: 46479 | DD102: 46486 | DE102: 46493 | DF102: 46500 | DG102: 46507 | DH102: 46514 | DI102: 46521 | DJ102: 46528 | DK102: 46535 | DL102: 46542 | DM102: 46549 | DN102: 46556 | DO102: 46563 | DP102: 46570 | DQ102: 46577 | DR102: 46584 | DS102: 46591 | DT102: 46598 | DU102: 46605 | DV102: 46612 | DW102: 46619 | DX102: 46626 | DY102: 46633 | DZ102: 46640 | EA102: 46647 | EB102: 46654 | EC102: 46661 | ED102: 46668 | EE102: 46675 | EF102: 46682 | EG102: 46689 | EH102: 46696 | EI102: 46703 | EJ102: 46710 | EK102: 46717 | EL102: 46724 | EM102: 46731 | EN102: 46738 | EO102: 46745 | EP102: 46752 | EQ102: 46759 | ER102: 46766 | ES102: 46773 | ET102: 46780 | EU102: 46787 | EV102: 46794 | EW102: 46801 | EX102: 46808 | EY102: 46815 | EZ102: 46822 | FA102: 46829 | FB102: 46836 | FC102: 46843
A103: CMDIC AGP HH Terreno | B103: Actual Labor Units | I103: 246.48 | J103: 1177.54 | K103: 1329.66 | L103: 1329.66 | M103: 1329.66 | N103: 130.49 | Q103: 138.09 | R103: 350.09 | S103: 1097.42 | T103: 1194.08 | U103: 2103.84 | V103: 2203.84 | W103: 1081.87 | X103: 761.52 | Y103: 1068.64 | Z103: 439.61 | AA103: 263.27 | AB103: 141.79 | AC103: 337.13 | AD103: 312.85 | AE103: 332.25 | AF103: 359.25 | AG103: 638.27 | AH103: 2027.37 | AI103: 2403.37 | AJ103: 1899.96 | AK103: 2000.6 | AL103: 1981.58 | AM103: 1032.03 | AN103: 610.57 | AO103: 286.37 | AP103: 286.37 | AQ103: 286.37 | AR103: 871.13 | AS103: 890.54 | AT103: 586.27 | AU103: 1216.82 | AV103: 1576.19 | AW103: 1750.28 | AX103: 2084 | AY103: 2193.16 | AZ103: 1267.12 | BA103: 618.02 | BB103: 541.59 | BC103: 264.09 | BD103: 738.09
A105: CMDIC AGP HH Oficina | B105: Actual Labor Units | C105: 103.25 | D105: 347.15 | E105: 419.14 | F105: 452.09 | G105: 406.75 | H105: 371.07 | I105: 369.24 | J105: 249.08 | K105: 248.71 | L105: 292.9 | M105: 276.68 | N105: 387.94 | O105: 408.26 | P105: 518.43 | Q105: 675.45 | R105: 514.72 | S105: 328.83 | T105: 307.39 | U105: 300.66 | V105: 256.18 | W105: 388.8 | X105: 366.97 | Y105: 412.46 | Z105: 217.13 | AA105: 286.23 | AB105: 367.41 | AC105: 331.31 | AD105: 428.82 | AE105: 417.46 | AF105: 412.56 | AG105: 322.17 | AH105: 360.42 | AI105: 327.23 | AJ105: 277.15 | AK105: 264.4 | AL105: 205.66 | AM105: 298.09 | AN105: 285.21 | AO105: 339.11 | AP105: 384.48 | AQ105: 356.73 | AR105: 319.71 | AS105: 338.92 | AT105: 320.45 | AU105: 245.65 | AV105: 224.25 | AW105: 281.78 | AX105: 290.47 | AY105: 300.96 | AZ105: 374.93 | BA105: 520.33 | BB105: 602.56 | BC105: 564.27 | BD105: 1047.3

Sheet Av. Subcontratos
J4: =+'Informe Semanal'!$Q$3 -> 46128
B5: =+'Informe Semanal'!D3 -> Reporte Semanal de Proyectos
B7: =+'Informe Semanal'!G4 -> 477-PRI24045-000-083-RS-0054
B9: Avance de Subcontratos
C11: Subcontrato | D11: Av. Físico Programado | E11: Av. Físico Real | F11: HH Cto. | G11: HH TD | H11: HH Total | I11: HH Plan | J11: HH Ganadas
B12: 1 | C12: GEOBIOTA | D12: =+I12/H12 -> 0.61741904 | E12: =+J12/H12 -> 0.61184763 | F12: 37081 | G12: =3060+1848+7601+2282+359+3272+5260 -> 23682 | H12: =+F12+G12 -> 60763 | I12: 37516.233 | J12: 37177.697
B13: =+B12+1 -> 2 | C13: HIDROESTUDIOS | D13: =+I13/H13 -> 0.084933633 | E13: =+J13/H13 -> 0.073295092 | F13: 7217.4 | H13: =+F13+G13 -> 7217.4 | I13: 613 | J13: 529
B14: =+B13+1 -> 3 | C14: DFM | D14: =+I14/H14 -> 0.012814352 | E14: =+J14/H14 -> 0.012814352 | F14: 2497.2 | H14: =+F14+G14 -> 2497.2 | I14: 32 | J14: 32
B15: =+B14+1 -> 4 | C15: CONTROL ACÚSTICO | D15: =+I15/H15 -> 0.61089303 | E15: =+J15/H15 -> 0.61089303 | F15: 407.6 | H15: =+F15+G15 -> 407.6 | I15: 249 | J15: 249
B16: =+B15+1 -> 5 | C16: PALEOCONSULTORES | D16: =+I16/H16 -> 0.89353612 | E16: =+J16/H16 -> 0.89353612 | F16: 315.6 | H16: =+F16+G16 -> 315.6 | I16: 282 | J16: 282
B17: =+B16+1 -> 6 | C17: ARKA | D17: =+I17/H17 -> 0 | E17: =+J17/H17 -> 0 | F17: 1303.6 | H17: =+F17+G17 -> 1303.6
B18: =+B17+1 -> 7 | C18: COSTA SUR | D18: =+I18/H18 -> 0.47583896 | E18: =+J18/H18 -> 0.4336305 | F18: 10566.6 | H18: =+F18+G18 -> 10566.6 | I18: 5028 | J18: 4582
B19: =+B18+1 -> 8 | C19: AMYT | D19: =+I19/H19 -> 0 | E19: =+J19/H19 -> 0 | F19: 945.2 | H19: =+F19+G19 -> 945.2
B20: =+B19+1 -> 9 | C20: SALIMAX | D20: =+I20/H20 -> 0 | E20: =+J20/H20 -> 0 | F20: 922.209 | H20: =+F20+G20 -> 922.209
B21: =+B20+1 -> 10 | C21: PROAM | D21: =+I21/H21 -> 0 | E21: =+J21/H21 -> 0 | F21: 759 | H21: =+F21+G21 -> 759
B22: =+B21+1 -> 11 | C22: ABOGADO | D22: =+I22/H22 -> 0 | E22: =+J22/H22 -> 0 | F22: 66.8 | H22: =+F22+G22 -> 66.8
B23: =+B22+1 -> 12 | C23: PLATAFORMA DINÁMICA | D23: =+I23/H23 -> 0 | E23: =+J23/H23 -> 0 | F23: 459.2 | H23: =+F23+G23 -> 459.2
B24: =+B23+1 -> 13 | C24: GEOPIXEL | D24: =+I24/H24 -> 0 | E24: =+J24/H24 -> 0 | F24: 75 | H24: =+F24+G24 -> 75
C25: Total | D25: =+I25/F25 -> 0.69822326 | E25: =+J25/F25 -> 0.68435252 | F25: =SUM(F12:F24) -> 62616.409 | G25: =SUM(G12:G24) -> 23682 | H25: =SUM(H12:H24) -> 86298.409 | I25: =SUM(I12:I24) -> 43720.233 | J25: =SUM(J12:J24) -> 42851.697
C27: Nota: Subcontrato Geobiota, se incorpora la Tendencia 12 "Campaña Biótica Complementaria Otoño"

Sheet Log Tendencias
B1: CONTRATO No PRI24045
B2: COMPAÑÍA DOÑA INÉS DE COLLAHUASI
B4: REGISTRO DE TENDENCIAS
B7: Tendencia Tipo : Cambio de Alcance (SC) ; Evolución de Diseño (DE) ; Cambio de Precio (PC) ; Cambio Cantidades (CC) Condiciones de Terreno (ST) ; Transferencias (BT) ; Otro (O) | S7: Fecha de Corte : | T7: =+'Informe Semanal'!Q3 -> 46128
B8: Estado : Potencial (P); Cancelados (C); Pendiente Eval Inicial(PEI);Pendiente Eval Detallada (PED); Emitido GP (EGP);Emitido Cliente (EC); Aprobados (A) ; Rechazado (R )
H10: Impacto | I10: Total | J10: COSTO CLP
B11: Tendencia | C11: OC | D11: Rev. | E11: Título | F11: Tipo | G11: Estado | H11: Ruta | I11: Horas | J11: Costo Directo | K11: Gastos Generales | L11: Utilidades | M11: Viajes y Estadía | N11: Costo Subcontratos | O11: Fee Subcontratos | P11: Descuento Comercial | Q11: GG | R11: Total CLP | S11: Alcance | T11: Observaciones
B12: N° | C12: N° | D12: N° | H12: Crítica
B14: 1 | D14: 0 | E14: Profesionales control operacional de terreno | F14: SC | G14: A | H14: NO | I14: =15+21+516 -> 552 | J14: 573 | K14: C | L14: 46 | M14: 369 | R14: =SUM(J14:Q14) -> 988 | S14: La presente tendencia detalla la incorporación del requerimiento de Collahuasi de tener un representante de WSP durante el desarrollo de las actividades de terreno de subcontratos de WSP, relacionados con el desarrollo de las campañas de líneas de base del EIA ACP Collahuasi, para que actúe de control operacional de terreno y que sea el nexo formal en terreno entre Collahuasi y WSP. | T14: 15/05/25: Versión para revisión 30/05/25: Tendencia fue emitida en Rev.1 04/06/25: Aprobación Collahuasi a Tendencia 1
B15: 2 | D15: C | E15: Profesionales Control Operacional de Terreno (Extensión a Diciembre 25) | F15: SC | G15: A | H15: NO | I15: =84+1920 -> 2004 | J15: 2079 | L15: 166 | R15: =SUM(J15:Q15) -> 2245 | S15: Tendencia que complementa a Tendencia 1. Corresponde a las horas profesionales contempladas para la continuidad del rol de Control Operacional de Terreno, considerando 24 semanas de trabajo (julio 25 a diciembre 25) | T15: Tendencia aprobada.
B16: 3 | D16: 2 | E16: Nuevas campañas de Línea de Base de Invertebrados Terrestres | F16: SC | G16: A | H16: NO | I16: 3431 | J16: 202 | L16: 16 | M16: 313 | N16: 3402 | O16: 170 | P16: -207 | R16: =SUM(J16:Q16) -> 3896 | S16: El Alcance original solicitado por Collahuasi contempló 1 campaña de terreno. La recomendación de equipo especialista es realizar 4 campañas, manteniendo así el criterios de 4 campañas para los distintos aspectos del medio biótico. Por lo anterior, la Tendencia 3 incluye la cotización de 3 campañas adicionales de invertebrados terrestres. | T16: 11/07/25: Tendencia fue emitida vía Aconex. 25/07/25. En reunión Ejecutiva del lunes 21/jul se informa a WSP que la versión Rev.B de esta Tendencia estaría en categoría Rechazada por Collahuasi. Sin embargo, a la fecha de cierre de este informe, no se había recibido la revisión de Collahuasi a esta Tendencia. 31/07/25: Se envía Rev.1 de Tendencia, actualizada según revisión de Collahuasi. 20/08/2025: Collahuasi emite Rechazo a versión Rev.1 de Tendencia 3. WSP revisará comentarios y emitirá nueva versión el 25/ago 27/08/2025: WSP emite versión Rev.2 de Tendencia 3 Tendencia en stand by por solicitud de WSP, hasta aclarar la situación del descuento comercial de última línea. Con fecha 29/sep, Collahuasi aprueba Tendencia 3.
B17: 4 | D17: 2 | E17: Nuevas campañas de Línea de Base de Ecosistemas Acuáticos Continentales | F17: SC | G17: A | H17: NO | I17: 2145 | J17: 179.52 | L17: 14.3616 | N17: 1677 | O17: 84 | P17: -107 | R17: =SUM(J17:Q17) -> 1847.8816 | S17: El Alcance original solicitado por Collahuasi contempló 1 campaña de terreno. La recomendación de equipo especialista es realizar, al menos, una campaña más. El número de nuevas campañas a contemplar se definirá en las próximas semanas por parte de Subcontrato Geobiota. Por lo anterior, la Tendencia 4 incluye la cotización de 3 campañas adicionales de ecosistemas acuáticos continentales. | T17: 11/07/25: Tendencia fue emitida vía Aconex. 25/07/25. En reunión Ejecutiva del lunes 21/jul se informa a WSP que la versión Rev.B de esta Tendencia estaría en categoría Rechazada por Collahuasi. Sin embargo, a la fecha de cierre de este informe, no se había recibido la revisión de Collahuasi a esta Tendencia. 31/07/25: Se envía Rev.1 de Tendencia, actualizada según revisión de Collahuasi. 20/08/2025: Collahuasi emite Rechazo a versión Rev.1 de Tendencia 4. WSP revisará comentarios y emitirá nueva versión el 25/ago. 27/08/2025: WSP emite versión Rev.2 de Tendencia 4 Tendencia en stand by por solicitud de WSP, hasta aclarar la situación del descuento comercial de última línea. Con fecha 22/sep, Collahuasi aprueba Tendencia 4
B18: 5 | D18: B | E18: Esfuerzos de terreno Adicionales (aspectos bióticos), campañas 2025 | F18: SC | G18: A | H18: NO | I18: 7846 | J18: 374 | L18: 30 | M18: 2758 | N18: 9048 | O18: 452 | P18: -26 | R18: =SUM(J18:Q18) -> 12636 | S18: La Tendencia 5 incluye los esfuerzos de terreno asociados a la ampliación de las superficies a caracterizar como parte del Area de Estudio definida en el marco del Hito 5. Cabe indicar que la estimación económica de esfuerzos complementarios de terreno asociados a la ampliación del área a caracterizar considera las estaciones de otoño, invierno y primavera de 2025, aplicando para las componentes plantas, animales silvestres, hongos y líquenes. De la misma forma, esta Tendencia incluye la estimación económica por esfuerzos adicionales para la ampliación del área de estudio definida en el Hito 8, incorporando los sistemas azonales que son parte de la Quebrada de Caya, además de la cuenca de Falla Pabellón y la Cuenca de Chusquina. Se incluye estimación por terreno para Invierno y primavera 2025, para caracterizar las componentes plantas, animales silvestres, hongos, líquenes y ecosistemas acuáticos continentales. | T18: 03/10/2025: Se emite versión Rev.B de Tendencia 5 09/10/2025: Se emite versión Rev.0 de Tendencia 5 28/10/2025: Se recibe versión 0 rechazada por Collahuasi. 13/11/2025: Se emite versión Rev. 1 de Tendencia 5. 26/11/2025: Se envía Tendencia 5 con las correcciones solicitadas, en versión PDF firmado y el archivo editable, además se adjunta una hoja de respuesta a cada uno de los comentarios enviados, donde se aclaran los criterios usados. 27/11/2025: CMDIC solicita revisar HH de procesamiento de información para la campaña de primavera. 30/12/2025: Tendencia aprobada por CMDIC
B19: =+B18+1 -> 6 | D19: 0 | E19: Esfuerzos de terreno Adicionales (Arquelogía, aspectos bióticos), campañas 2025 | F19: SC | G19: A | H19: NO | I19: 6879 | J19: 463 | L19: 37 | M19: 1357 | N19: 2651 | O19: 133 | P19: -19 | R19: =SUM(J19:Q19) -> 4622 | S19: LTE ACP - Trazado Alternativo La presente propuesta considera el esfuerzo adicional en terreno para prospectar una alternativa de trazado correspondiente a la LTE cuya longitud alcanza los 20 kilómetros aproximadamente. La propuesta considera 2 temporadas (primavera 2025 y verano 2026) para los componentes bioticos. Los profesionales y turnos considerados son los siguientes: - Arqueología - Plantas - Fauna - Hongos y Líquenes | T19: 28/11/2025: Semite en versión Rev. B 22/12/2025: TD Aprobada por CMDIC
B20: =+B19+1 -> 7 | D20: 0 | E20: Descuento comercial | F20: SC | G20: A | H20: NO | I20: 0 | P20: 233 | R20: =SUM(J20:Q20) -> 233 | S20: La presente Tendencia incluye ajustes relacionados con el cálculo del Descuento Comercial aplicable en cada Tendencia. Esta Tendencia actualiza y regulariza el criterio de cálculo aplicado en las Tendencias 1 a la 6 de Descuento Comercial, considerando para el caso: - Excluir a los subcontratos de la aplicación de descuento comercial en todas las Tendencias, aplicando este criterio de manera retroactiva y para las siguientes Tendencia a presentar. - Considerar un descuento comercial de última línea de 3% sobre el valor ofertado de WSP, aplicable sólo a los costos directos, gastos generales y utilidad de profesionales WSP, aplicando este criterio de manera retroactiva y para las siguientes Tendencia a presentar. | T20: TD en proceso de aprobación por CMDIC 02/02/2026: Tendencia Aprobada por CMDIC
B21: =+B20+1 -> 8 | D21: 0 | E21: Continuidad Control Operacional del Terreno | F21: SC | G21: A | H21: NO | I21: 1575 | J21: 1634.85 | L21: 130.788 | P21: -52.96914 | R21: =SUM(J21:Q21) -> 1712.6689 | S21: Continuidad Control Operacional del Terreno La presente tendencia detalla la continuidad de la actividad de Control Operacional de Terreno, llevada a cabo por supervisores WSP, a realizarse durante las actividades de terreno de subcontratos de WSP, relacionados con el desarrollo de las campañas de líneas de base del EIA ACP Collahuasi. Estas actividades se estiman en 18 semanas, desde la semana del 26/enero 2026 a la ultima semana de mayo 2026. Los profesionales dedicados a esta labor serán la supervisión WSP en terreno, y serán el nexo formal en terreno entre Collahuasi y WSP. Por lo anterior, WSP dispondrá de 2 profesionales en contraturno (1 profesional siempre en terreno) cada vez que se desarrollen trabajos de campañas de líneas de base del EIA ACP, en los sectores de Cordillera/Puerto. Cabe indicar que esta Tendencia no modifica el programa de trabajo, debido a que corresponde a horas profesionales relacionadas con supervisión de actividades de terreno de actividades incluidas en la programación vigente. | T21: TD Emitida al cliente 04/02/2026: Tendencia Aprobada por CMDIC.
B22: =+B21+1 -> 9 | D22: 1 | E22: Transferencia de Presupueto Brigada Canina | F22: BT | G22: A | H22: NO | I22: 359 | M22: -2152.8 | N22: 464.3 | O22: 23.2 | R22: =SUM(J22:Q22) -> -1665.3 | S22: Sitios de nidificación En la propuesta original, se consideró como parte de las metodologías de avifauna, realizar la búsqueda de nidos de golondrinas de mar y gaviota garuma mediante la implementación de una brigada canina consistente en la utilización de perros entrenados para la detección de nidos. Dado la imposibilidad de ejecutar esta metodología ya que no se dispone de los perros entrenados y certificados acorde a las exigencias de la guía del SEA publicada en mayo de 2025, la metodología es desarrollada por cuatro especialistas en aves quienes identifican en un área previamente determinada . La metodología implementada por los profesionales corresponde a la realización de recorridos pedestres mediante transectos y barridos en una superficie de 300x300 metros, inspeccionado los distintos tipos de sustratos en busca de grietas, agujeros, paredes rocosas en faldeos de quebradas y otras estructuras potenciales para la nidificación de golondrinas de mar, gaviota garuma. Durante la prospección del ambiente en estos barridos se implementan también metodologías de inspección visual, detección olfativa, playback y uso de boroscopios para examinar cavidades. Complementario al barrido de aves, se realizarán recorridos pedestres en sectores que, mediante prospección visual o con binoculares, se identifiquen sustratos adecuados para las especies objetivo. En el caso de detectar presencia de cavidades, grietas o madrigueras adecuadas para la nidificación de golondrinas de mar, se aplica la metodología estándar para estas especies (detección olfativa, respuesta al playback y/o uso de boroscopio). | T22: TD Emitida al cliente 13/02/2026: Tendencia Rechazada por CMDIC 01/04/2026: Tendencia Aprobada por CMDIC.
B23: =+B22+1 -> 10 | D23: 1 | E23: Campaña de Verano Área de Estudio | F23: SC | G23: A | H23: NO | I23: 3314 | J23: 59.82 | L23: 4.7856 | M23: 1102.3047 | N23: 3804.075 | O23: 190.20375 | P23: -1.7946 | R23: =SUM(J23:Q23) -> 5159.3944 | S23: CAMPAÑA VERANO ÁREA DE ESTUDIO Durante el desarrollo del Hito 5, se consideró la definición de un área de estudio que permitió delimitar una superficie a caracterizar para las componentes bióticas. Para lo anterior, se consideró la superficie proyectada por la ocupación de las obras, y también la superficie generada por los impactos funcionales derivados por la ampliación del rajo, específicamente su delimitación fue realizada considerando el modelo hidrogeológico disponible, el cual fue construido en base a un desarrollo de ingeniería FEL2. Esta delimitación permitió enfocar los esfuerzos en terreno para las componentes bióticas que deben cumplir con el levantamiento de información estacional y cuyos terrenos ya ejecutados, comprenden las campañas de otoño, invierno y primavera. _x000B_ Como los resultados de un modelo más avanzado que permita concluir el área de afectación hidrogeológica no está disponible aún, no es factible definir el área de influencia, lo cual no será factible de realizar hasta contar con información que le permite precisar las condiciones de borde del modelo hidrogeológico. Con el objetivo de mantener la continuidad en el esfuerzo de muestreo estacional, se adjunta la presente tendencia correspondiente a la propuesta económica para la campaña de verano, considerando la misma área de estudio realizada en campañas anteriores. | T23: 29/01/2026: TD Emitida al cliente 18/02/2026: TD rechazada por el cliente. 01/04/2026: Tendencia Aprobada por CMDIC.
B24: =+B23+1 -> 11 | D24: 0 | E24: Estudio de Capacidad de Carga | F24: SC | G24: EC | H24: NO | I24: 338 | J24: 28.42 | L24: 2.2736 | N24: 498.3 | O24: 24.915 | P24: -0.8526 | R24: =SUM(J24:Q24) -> 553.056 | S24: Objetivos Los objetivos del estudio corresponden a: 1. Estimar la capacidad de carga animal de pastizales, en el área de estudio actualmente utilizada para los levantamientos de flora y vegetación asociada a las quebradas y de las cuales se tiene información relacionada al uso de comunidades indígenas. 2. Estimar la carga animal actual sobre la base de información de censos de animales que utilizan los terrenos de pastoreo. 3. Sobre la base a la información anterior, estimar un indicador de la intensidad del uso de los pastizales. Para cumplir con los objetivos anteriores, se utilizará los datos obtenidos para la línea de base de plantas y se efectuará un análisis espaciotemporal de imágenes de satelitales disponibles, para determinar perfiles de NDVI de los diferentes tipos de pastizales que sea posible diferenciar. A partir de esta información, se estimará las variaciones temporales de la cobertura y el crecimiento vegetal, mediante la aplicación del modelo de Monteith (Gallego et al., 20171; Baldassini et al., 20122). Conocidas las curvas promedio de crecimiento de cada tipo de pastizal y aplicando un método de integración numérica, se estimará la producción promedio anual de materia seca (PMSA, kg ha-1), la cual se utilizará a su vez para determinar la capacidad de carga (CC) expresada en Unidades animales-mes, según la ecuación siguiente: '𝐶𝐶=(𝑃𝑀𝑆∗𝑃𝑆𝑃∗𝐹𝑈𝐴)/365 [Ec. 1] En la Ec. 1, PSP es la fracción de especies palatables y FUA es el factor de uso apropiado (~35% para praderas y matorrales de zonas áridas (Holechek, 1988). La información anterior será complementada con literatura e información de vegetación levantada por la Línea de Base de Plantas. Se analizarán los censos ganaderos existentes, determinado el número de animales de diferentes categorías y el periodo de uso de los pastizales. Esta información será transformada a Unidades Animales (UA), con el propósito de establecer la carga ganadera actual del sector y compararla con la capacidad de carga, para así determinar la intensidad de uso de los pastizales. | T24: 01/04/2026: Rechazado CMDIC. 10/04/2026: Se emite TD R1 el 10/04/26 16/04/2026: Se envía actualización por e-mail a CMDIC.
B25: =+B24+1 -> 12 | D25: 0 | E25: Campaña Adicional de Otoño | F25: SC | G25: A | H25: NO | I25: 5260 | J25: 24.675 | L25: 1.974 | M25: 5400.152 | N25: 6290.875 | O25: 314.54375 | P25: -0.74025 | R25: =SUM(J25:Q25) -> 12031.479 | S25: Campaña Complementaria Se propone realizar una campaña complementaria para las subcomponentes; plantas, fauna, hongos, líquenes, y sistemas azonales (humedales), este último punto es para reforzar algunos sectores que no fue factible completar información de suelo en época estival por congelamiento. El objetivo es robustecer el muestreo realizado en la campaña de otoño 2025 considerando el bajo rendimiento de puntos realizados en comparación de campañas de invierno, primavera y verano. Esta campaña complementaria permitirá aumentar la cobertura de las estaciones de muestreo disminuyendo el error de extrapolación, permitiendo tener una mayor precisión de la base de datos obtenida en campañas anteriores, así como realizar réplicas en sectores con mayor diversidad de especies, lo cual permite, a su vez, realizar análisis estadísticos sólidos y tener datos comparables entre estaciones (según los lineamientos sugeridos en la Guía Metodologica para la Descripción de Ecosistemas Terrestres. SEA, 2025). Se ha considerado de manera simultanea, realizar un esfuerzo de muestreo en áreas adicionadas en la campaña de verano, por lo cual se ha considerado pertinente realizar campaña de otoño en estos sectores con el objetivo de contar con datos de terreno de, por lo menos, dos campañas, igualando el esfuerzo de muestreo estacional realizado al área de estudio. Cabe indicar que, en verano, se realizó una campaña extra de fauna (Turno 4) con una cuadrilla mixta (vertebrados e invertebrados) para completar sector del tranque de relaves que quedo sin esfuerzo de muestreo en las campañas realizadas para esta estación, por lo cual se incluye en esta Tendencia las horas de especialistas en terreno (dos especialistas y 5 días efectivos de terreno). En la hoja 4, se detalla el esfuerzo de muestreo por componente. No se consideran HH de informe, ya que estas se incluyen en la actualización del informe de línea de base en REV.B | T25: 27/03/2026: Emitido para revisión por WSP. 13/04/2026: Aprobado CMDIC
B26: =+B25+1 -> 13 | D26: A | E26: Áreas Adicionales (Arqueología y Medio Biótico) | F26: SC | G26: P | H26: NO | J26: 3461.892 | L26: 276.95136 | N26: 1299 | O26: 64.95 | P26: -103.85676 | R26: =SUM(J26:Q26) -> 4998.9366 | S26: Arqueología Se considera una prospección superficial con transectas cada 25 metros en un total de 1.365,4 hectáreas, además en la zona que ya cuenta con prospección superficial con transectas cada 50 metros, se consideran transectas intercaladas a las existentes, esto en una superficie de 271,7 hecáreas. Al total de ambas superficies (1.637 ha) se ha descontado la superficie que quedó por prospectar en las campalas anteriores (964,5 ha), por lo que la superficie adicional corresponde a 672,6 hectárea, es decir que la presente estimación es para cubrir la superficie adicional. Además se considera una superficie de 115 hectáreas asociadas a la variante de la ruta A-97. _x000B_Se consideran 5,25 turnos en una jornada de 7x7 con 12 horas de trabajo diario de 6 profesionales por turno. Además se considera la prospección de 115 hectáras asociadas a la variante de la Ruta A-97 con una duración de 0,5 turno, a continuación del levantamiento de las 672,6 hectáreas. Campaña áreas adicionales (Campañas Bióticas) Se ha considerado de manera independiente a las campañas complementarias, realizar un esfuerzo de muestreo en áreas adicionadas en la campaña de verano, por lo cual se ha considerado pertinente realizar campaña de otoño e invierno en estos sectores con el objetivo de contar con datos de terreno de, por lo menos, tres campañas, igualando el esfuerzo de muestreo estacional realizado al área de estudio. Por lo cual el detalle de HH ha considerado campaña de otoño + campaña de invierno. Cabe indicar que en verano, se realizará una campaña de fauna con una cuadrilla mixta (vertebrados e invertebrados) para completar sector del tranque de relaves que quedo sin esfuerzo de muestreo en las campañas realizadas para esta estación. En la hoja 4, se detalla el esfuerzo de muestreo por componente. Campaña ruta proyectada A-97 (Campañas Bióticas) La campaña correspondiente a la ruta A-97, fuera de faenas, aun no esta segura su incorporación al proyecto, por lo cual se ha cotizado de manera independiente. La campaña en este sector, ha considerado realizar por lo menos tres campañas (otoño, invierno y primavera) con el objetivo de igualr esfuerzo de muestreo de otros sectores. En la hoja 4, se detalla el esfuerzo de muestreo por componente.
B27: =+B26+1 -> 14 | D27: A | E27: Campaña Pozos de Sondeo | F27: SC | G27: P | H27: NO | I27: 18944 | J27: 24320 | L27: =+J27*8% -> 1945.6 | N27: 5656 | O27: =+N27*5% -> 282.8 | P27: =+J27*-3% -> -729.6 | R27: =SUM(J27:Q27) -> 31474.8 | S27: Campaña Pozos de Sondeo, Se requiere realizar un aumento en el presupuesto de ejecución de pozos de sondeo, ya que el contrato origianl sólo cuenta con el presupuesto para 200 pozos, sin embargo según los FSA N°1 (142 pozos), N°2 (237 pozos) y N°3 (333 pozos preliminar), la cantidad total de pozos a realizar es de 712, por lo que el presupuesto de aumento es por 512 pozos. A esto se le debe incluir la empresa subcontratista que incluirá al personal auxiliar (jornales) e implementos para trabajo de terreno.
B28: =+B27+1 -> 15 | D28: A | E28: Campaña para LdB Geología, Geomorfología y Riesgos Geológicos | F28: SC | G28: P | H28: NO | I28: 592 | J28: 1285.3 | L28: =+J28*8% -> 102.824 | O28: =+N28*5% -> 0 | P28: =+J28*-3% -> -38.559 | R28: =SUM(J28:Q28) -> 1349.565 | S28: Campaña GGR Tendencia asociada a tareas complementarias para la elaboración de la línea de Base de Geología, Geomorfología y Riesgos Geológicos identificadas en el anpalisis de brechas (Hito 4).
B29: =+B28+1 -> 16 | D29: A | E29: Estudio de Felinos | F29: SC | G29: P | H29: NO | J29: 43 | L29: =+J29*8% -> 3.44 | N29: 349 | O29: =+N29*5% -> 17.45 | P29: =+J29*-3% -> -1.29 | R29: =SUM(J29:Q29) -> 411.6 | S29: ESTUDIO DE FELINOS A partir de la evidencia obtenida durante la campaña de otoño 2025 en el AE del proyecto, donde fue posible detectar a un individuo de gato colocolo (Leopardus colocolo) mediante cámara trampa, específicamente en el sector cordillera, en las inmediaciones del campamento Pioneros (aproximadamente a 1,5 km), se propone realizar un estudio de felinos, consistente en un seguimiento continuo mediante la instalación de cámaras trampas en ambientes propicios para el desarrollo de felinos, las cuales permanecerán hasta la próxima campañ estacional (verano) en la cual serán retiradas y se realizará el análisis de registros. Lo anterior se respalda en función de algunos estudios reportan la presencia de esta especie en las inmediaciones del proyecto y sectores aledaños, específicamente en quebradas del área sur, como es el caso de las quebradas de Mal Paso y Ceusis, entre otras (Castro-Pastene, 2016), mientras que la revisión de antecedentes de Línea de base del EIA 2021 (EIA “Desarrollo de Infraestructura y Mejoramiento de Capacidad Productiva de Collahuasi”), reportan la presencia mediante evidencia indirecta para gato andino (Leopardus jacobita) en los sectores de Huinquintipa y cercano al tranque de relaves (Figura 1‑2). Ambas especies de felino se encuentran en categoría de conservación, siendo el gato colocolo catalogada como casi amenazada (NT), mientras que el gato andino está clasificado como especie En Peligro. Adicionalmente se han obtenido registros indirectos de puma (Puma concolor) en el área del proyecto, lo que, sumado a la información obtenida de la literatura, que señala su presencia en el altiplano de la región de Tarapacá (Leichtle, 2013; Leichtle et al, 2016), permite extender este estudio como especie relevante, considerando su categoría de conservación como Casi Amenazada (NT).
B30: =+B29+1 -> 17 | D30: A | E30: Monitoreo MPS | F30: SC | G30: P | H30: NO | I30: =(14*12)+65 -> 233 | J30: =255*1.2 -> 306 | L30: =J30*8% -> 24.48 | N30: 1250 | O30: =+N30*5% -> 62.5 | P30: =I30*-3% -> -6.99 | R30: =SUM(J30:Q30) -> 1635.99 | S30: En función de la nueva "Guía para la predicción y evaluación de impactos sobre ecosistemas terrestres" (agosto, 2025), se requiere incorporar mediciones de MPS en el sector cordillera, ductos alto (por Metharme lanata y vegetación azonal) y sector pampa tamarugal.
B31: =+B30+1 -> 18 | D31: A | E31: Viajes y Estadia a Tarifas Unitarias | F31: SC | G31: P | H31: NO | M31: =(5759*0.25)+(4551*0.25)+(1745*0.15)+(805*0.15) -> 2960 | R31: =SUM(J31:Q31) -> 2960 | S31: Viajes y Estadia a Tarifas Unitarias Gastos reembolsables adicionales
B32: =+B31+1 -> 19
B33: =+B32+1 -> 20
B34: =+B33+1 -> 21
B35: =+B34+1 -> 22
B36: =+B35+1 -> 23
B37: 26
B38: 27
B39: 28
B40: 29
B41: 30
B42: 31
B43: 32
B44: 33
B45: 34
B46: 35
B47: 36
B48: 37
B49: 38
E55: TOTAL APROBADOS (A) | I55: =SUMIF($G$14:$G$53,"A",I14:I53) -> 33365 | J55: =SUMIF($G$14:$G$53,"A",J14:J53) -> 5589.865 | K55: =SUMIF($G$14:$G$53,"A",K14:K53) -> 0 | L55: =SUMIF($G$14:$G$53,"A",L14:L53) -> 446.9092 | M55: =SUMIF($G$14:$G$53,"A",M14:M53) -> 9146.6567 | N55: =SUMIF($G$14:$G$53,"A",N14:N53) -> 27337.25 | O55: =SUMIF($G$14:$G$53,"A",O14:O53) -> 1366.9475 | P55: =SUMIF($G$14:$G$53,"A",P14:P53) -> -181.50399 | ... R55: =SUMIF($G$14:$G$53,"A",R14:R53) -> 43706.124
E56: TOTAL POTENCIAL (P) | I56: =SUMIF($G$14:$G$53,"P",I14:I53) -> 19769 | J56: =SUMIF($G$14:$G$53,"P",J14:J53) -> 29416.192 | K56: =SUMIF($G$14:$G$53,"P",K14:K53) -> 0 | L56: =SUMIF($G$14:$G$53,"P",L14:L53) -> 2353.2954 | M56: =SUMIF($G$14:$G$53,"P",M14:M53) -> 2960 | N56: =SUMIF($G$14:$G$53,"P",N14:N53) -> 8554 | O56: =SUMIF($G$14:$G$53,"P",O14:O53) -> 427.7 | P56: =SUMIF($G$14:$G$53,"P",P14:P53) -> -880.29576 | ... R56: =SUMIF($G$14:$G$53,"P",R14:R53) -> 42830.892
E57: TOTAL RECHAZADOS (R) | I57: =SUMIF($G$14:$G$53,"R",I14:I53) -> 0 | J57: =SUMIF($G$14:$G$53,"R",J14:J53) -> 0 | K57: =SUMIF($G$14:$G$53,"R",K14:K53) -> 0 | L57: =SUMIF($G$14:$G$53,"R",L14:L53) -> 0 | M57: =SUMIF($G$14:$G$53,"R",M14:M53) -> 0 | N57: =SUMIF($G$14:$G$53,"R",N14:N53) -> 0 | O57: =SUMIF($G$14:$G$53,"R",O14:O53) -> 0 | P57: =SUMIF($G$14:$G$53,"R",P14:P53) -> 0 | ... R57: =SUMIF($G$14:$G$53,"R",R14:R53) -> 0
E58: TOTAL EMITIDO CLIENTE (EC) | I58: =SUMIF($G$14:$G$53,"EC",I14:I53) -> 338 | J58: =SUMIF($G$14:$G$53,"EC",J14:J53) -> 28.42 | K58: =SUMIF($G$14:$G$53,"EC",K14:K53) -> 0 | L58: =SUMIF($G$14:$G$53,"EC",L14:L53) -> 2.2736 | M58: =SUMIF($G$14:$G$53,"EC",M14:M53) -> 0 | N58: =SUMIF($G$14:$G$53,"EC",N14:N53) -> 498.3 | O58: =SUMIF($G$14:$G$53,"EC",O14:O53) -> 24.915 | P58: =SUMIF($G$14:$G$53,"EC",P14:P53) -> -0.8526 | ... R58: =SUMIF($G$14:$G$53,"EC",R14:R53) -> 553.056
E59: TOTAL PENDIENTE EVAL INICIAL (PEI) | I59: =SUMIF($G$14:$G$53,"PEI",I14:I53) -> 0 | J59: =SUMIF($G$14:$G$53,"PEI",J14:J53) -> 0 | K59: =SUMIF($G$14:$G$53,"PEI",K14:K53) -> 0 | L59: =SUMIF($G$14:$G$53,"PEI",L14:L53) -> 0 | M59: =SUMIF($G$14:$G$53,"PEI",M14:M53) -> 0 | N59: =SUMIF($G$14:$G$53,"PEI",N14:N53) -> 0 | O59: =SUMIF($G$14:$G$53,"PEI",O14:O53) -> 0 | P59: =SUMIF($G$14:$G$53,"PEI",P14:P53) -> 0 | ... R59: =SUMIF($G$14:$G$53,"PEI",R14:R53) -> 0
E60: TOTAL PENDIENTE EVAL DETALLADA (PED) | I60: =SUMIF($G$14:$G$53,"PED",I14:I53) -> 0 | J60: =SUMIF($G$14:$G$53,"PED",J14:J53) -> 0 | K60: =SUMIF($G$14:$G$53,"PED",K14:K53) -> 0 | L60: =SUMIF($G$14:$G$53,"PED",L14:L53) -> 0 | M60: =SUMIF($G$14:$G$53,"PED",M14:M53) -> 0 | N60: =SUMIF($G$14:$G$53,"PED",N14:N53) -> 0 | O60: =SUMIF($G$14:$G$53,"PED",O14:O53) -> 0 | P60: =SUMIF($G$14:$G$53,"PED",P14:P53) -> 0 | ... R60: =SUMIF($G$14:$G$53,"PED",R14:R53) -> 0
E61: TOTAL CANCELADOS (C) | I61: =SUMIF($G$14:$G$53,"C",I14:I53) -> 0 | J61: =SUMIF($G$14:$G$53,"C",J14:J53) -> 0 | K61: =SUMIF($G$14:$G$53,"C",K14:K53) -> 0 | L61: =SUMIF($G$14:$G$53,"C",L14:L53) -> 0 | M61: =SUMIF($G$14:$G$53,"C",M14:M53) -> 0 | N61: =SUMIF($G$14:$G$53,"C",N14:N53) -> 0 | O61: =SUMIF($G$14:$G$53,"C",O14:O53) -> 0 | P61: =SUMIF($G$14:$G$53,"C",P14:P53) -> 0 | ... R61: =SUMIF($G$14:$G$53,"C",R14:R53) -> 0
E62: TOTAL ESTADO DE TENDENCIAS | I62: =SUM(I55:I61) -> 53472 | J62: =SUM(J55:J61) -> 35034.477 | K62: =SUM(K55:K61) -> 0 | L62: =SUM(L55:L61) -> 2802.4782 | M62: =SUM(M55:M61) -> 12106.657 | N62: =SUM(N55:N61) -> 36389.55 | O62: =SUM(O55:O61) -> 1819.5625 | P62: =SUM(P55:P61) -> -1062.6523 | ... R62: =SUM(R55:R61) -> 87090.072
E65: TOTAL CAMBIO DE ALCANCE ( SC ) | I65: =SUMIF($F$14:$F$53,"SC",I14:I53) -> 53113 | J65: =SUMIF($F$14:$F$53,"SC",J14:J53) -> 35034.477 | K65: =SUMIF($F$14:$F$53,"SC",K14:K53) -> 0 | L65: =SUMIF($F$14:$F$53,"SC",L14:L53) -> 2802.4782 | M65: =SUMIF($F$14:$F$53,"SC",M14:M53) -> 14259.457 | N65: =SUMIF($F$14:$F$53,"SC",N14:N53) -> 35925.25 | O65: =SUMIF($F$14:$F$53,"SC",O14:O53) -> 1796.3625 | P65: =SUMIF($F$14:$F$53,"SC",P14:P53) -> -1062.6524 | ... R65: =SUMIF($F$14:$F$53,"SC",R14:R53) -> 88755.372
E66: TOTAL EVOLUCION DE DISEÑO ( DE ) | I66: =SUMIF($F$14:$F$53,"DE",I14:I53) -> 0 | J66: =SUMIF($F$14:$F$53,"DE",J14:J53) -> 0 | K66: =SUMIF($F$14:$F$53,"DE",K14:K53) -> 0 | L66: =SUMIF($F$14:$F$53,"DE",L14:L53) -> 0 | M66: =SUMIF($F$14:$F$53,"DE",M14:M53) -> 0 | N66: =SUMIF($F$14:$F$53,"DE",N14:N53) -> 0 | O66: =SUMIF($F$14:$F$53,"DE",O14:O53) -> 0 | P66: =SUMIF($F$14:$F$53,"DE",P14:P53) -> 0 | ... R66: =SUMIF($F$14:$F$53,"DE",R14:R53) -> 0
E67: TOTAL CAMBIOS DE PRECIO ( PC ) | I67: =SUMIF($F$14:$F$53,"PC",I14:I53) -> 0 | J67: =SUMIF($F$14:$F$53,"PC",J14:J53) -> 0 | K67: =SUMIF($F$14:$F$53,"PC",K14:K53) -> 0 | L67: =SUMIF($F$14:$F$53,"PC",L14:L53) -> 0 | M67: =SUMIF($F$14:$F$53,"PC",M14:M53) -> 0 | N67: =SUMIF($F$14:$F$53,"PC",N14:N53) -> 0 | O67: =SUMIF($F$14:$F$53,"PC",O14:O53) -> 0 | P67: =SUMIF($F$14:$F$53,"PC",P14:P53) -> 0 | Q67: =SUMIF($G$14:$G$53,"PC",Q14:Q53) -> 0 | R67: =SUMIF($F$14:$F$53,"PC",R14:R53) -> 0
E68: TOTAL CONDICIONES DE TERRENO ( ST ) | I68: =SUMIF($F$14:$F$53,"ST",I14:I53) -> 0 | J68: =SUMIF($F$14:$F$53,"ST",J14:J53) -> 0 | K68: =SUMIF($F$14:$F$53,"ST",K14:K53) -> 0 | L68: =SUMIF($F$14:$F$53,"ST",L14:L53) -> 0 | M68: =SUMIF($F$14:$F$53,"ST",M14:M53) -> 0 | N68: =SUMIF($F$14:$F$53,"ST",N14:N53) -> 0 | O68: =SUMIF($F$14:$F$53,"ST",O14:O53) -> 0 | P68: =SUMIF($F$14:$F$53,"ST",P14:P53) -> 0 | Q68: =SUMIF($G$14:$G$53,"ST",Q14:Q53) -> 0 | R68: =SUMIF($F$14:$F$53,"ST",R14:R53) -> 0
E69: TOTAL TRANSFERENCIA DE PRESUPUESTO ( BT ) | I69: =SUMIF($F$14:$F$53,"BT",I14:I53) -> 359 | J69: =SUMIF($F$14:$F$53,"BT",J14:J53) -> 0 | K69: =SUMIF($F$14:$F$53,"BT",K14:K53) -> 0 | L69: =SUMIF($F$14:$F$53,"BT",L14:L53) -> 0 | M69: =SUMIF($F$14:$F$53,"BT",M14:M53) -> -2152.8 | N69: =SUMIF($F$14:$F$53,"BT",N14:N53) -> 464.3 | O69: =SUMIF($F$14:$F$53,"BT",O14:O53) -> 23.2 | P69: =SUMIF($F$14:$F$53,"BT",P14:P53) -> 0 | Q69: =SUMIF($G$14:$G$53,"BT",Q14:Q53) -> 0 | R69: =SUMIF($F$14:$F$53,"BT",R14:R53) -> -1665.3
E70: TOTAL OTROS ( O ) | I70: =SUMIF($F$14:$F$53,"O",I14:I53) -> 0 | J70: =SUMIF($F$14:$F$53,"O",J14:J53) -> 0 | K70: =SUMIF($F$14:$F$53,"O",K14:K53) -> 0 | L70: =SUMIF($F$14:$F$53,"O",L14:L53) -> 0 | M70: =SUMIF($F$14:$F$53,"O",M14:M53) -> 0 | N70: =SUMIF($F$14:$F$53,"O",N14:N53) -> 0 | O70: =SUMIF($F$14:$F$53,"O",O14:O53) -> 0 | P70: =SUMIF($F$14:$F$53,"O",P14:P53) -> 0 | Q70: =SUMIF($G$14:$G$53,"O",Q14:Q53) -> 0 | R70: =SUMIF($F$14:$F$53,"O",R14:R53) -> 0
E71: TOTAL TIPO DE TENDENCIAS | I71: =SUM(I65:I70) -> 53472 | J71: =SUM(J65:J70) -> 35034.477 | K71: =SUM(K65:K70) -> 0 | L71: =SUM(L65:L70) -> 2802.4782 | M71: =SUM(M65:M70) -> 12106.657 | N71: =SUM(N65:N70) -> 36389.55 | O71: =SUM(O65:O70) -> 1819.5625 | P71: =SUM(P65:P70) -> -1062.6524 | ... R71: =SUM(R65:R70) -> 87090.072

Sheet Costos
B3: Area (CLF$) | C3: Presupuesto Original | D3: Cambios Aprobados | E3: Presupuesto Actualizado | F3: Pagado a la Fecha | K3: Area (CLF$m) | L3: Presupuesto Original | M3: Cambios Aprobados | N3: Presupuesto Actualizado | O3: Pagado a la Fecha
B4: Costo Directo | C4: 75765.05 | D4: =+'Log Tendencias'!J55 -> 5589.865 | E4: =C4+D4 -> 81354.915 | F4: =(23725*G4)+462+1050+3025+444+H4 -> 22138 | G4: 0.48 | H4: =5071+111+559+28 -> 5769 | K4: =+B4 -> Costo Directo | L4: =C4/1000 -> 75.76505 | M4: =D4/1000 -> 5.589865 | N4: =E4/1000 -> 81.354915 | O4: =F4/1000 -> 22.138
B5: Gastos Generales | C5: 17645.478 | D5: =+'Log Tendencias'!K55 -> 0 | E5: =C5+D5 -> 17645.478 | F5: =2020.67993647494+704+H5 -> 3905.6799 | H5: 1181 | K5: =+B5 -> Gastos Generales | L5: =C5/1000 -> 17.645478 | M5: =D5/1000 -> 0 | N5: =E5/1000 -> 17.645478 | O5: =F5/1000 -> 3.9056799
B6: Utilidades | C6: 6061.204 | D6: =+'Log Tendencias'!L55 -> 446.9092 | E6: =C6+D6 -> 6508.1132 | F6: =694.101532057203+37+84+3+0.3+242+36+H6 -> 1573.4015 | H6: =406+9+45+2+12+1+2 -> 477 | K6: =+B6 -> Utilidades | L6: =C6/1000 -> 6.061204 | M6: =D6/1000 -> 0.4469092 | N6: =E6/1000 -> 6.5081132 | O6: =F6/1000 -> 1.5734015
B7: Viajes y Estadía | C7: 69014.452 | D7: =+'Log Tendencias'!M55 -> 9146.6567 | E7: =C7+D7 -> 78161.109 | F7: =10160.7295260605+132+6819+H7 -> 23847.73 | H7: =6719+5+12 -> 6736 | K7: =+B7 -> Viajes y Estadía | L7: =C7/1000 -> 69.014452 | M7: =D7/1000 -> 9.1466567 | N7: =E7/1000 -> 78.161109 | O7: =F7/1000 -> 23.84773
B8: Costo Subcontratos | C8: 83157.714 | D8: =+'Log Tendencias'!N55 -> 27337.25 | E8: =C8+D8 -> 110494.96 | F8: =(23725*G8)+1091+16+3937+H8 -> 29746 | G8: 0.52 | H8: =2952+690+3+7490+1230 -> 12365 | K8: =+B8 -> Costo Subcontratos | L8: =C8/1000 -> 83.157714 | M8: =D8/1000 -> 27.33725 | N8: =E8/1000 -> 110.49496 | O8: =F8/1000 -> 29.746
B9: Fee Subcontratos | C9: 4157.8857 | D9: =+'Log Tendencias'!O55 -> 1366.9475 | E9: =C9+D9 -> 5524.8332 | F9: =752.440186952721+53+1+147+H9 -> 1562.4402 | H9: =148+33+367+61 -> 609 | K9: =+B9 -> Fee Subcontratos | L9: =C9/1000 -> 4.1578857 | M9: =D9/1000 -> 1.3669475 | N9: =E9/1000 -> 5.5248332 | O9: =F9/1000 -> 1.5624402
B10: Descuento Comercial | C10: -10215.831 | D10: =+'Log Tendencias'!P55 -> -181.50399 | E10: =C10+D10 -> -10397.335 | F10: =-1525.08880453648-63-1-383-66.77+H10 -> -2388.8588 | H10: =-516-40-20-7+233 -> -350 | K10: =+B10 -> Descuento Comercial | L10: =C10/1000 -> -10.215831 | M10: =D10/1000 -> -0.18150399 | N10: =E10/1000 -> -10.397335 | O10: =F10/1000 -> -2.3888588
B11: Total Contrato | C11: =SUM(C4:C10) -> 245585.95 | D11: =SUM(D4:D10) -> 43706.124 | E11: =SUM(E4:E10) -> 289292.08 | F11: =SUM(F4:F10) -> 80384.392 | H11: =SUM(H4:H10) -> 26787 | K11: Total | L11: =SUM(L4:L10) -> 245.58595 | M11: =SUM(M4:M10) -> 43.706124 | N11: =SUM(N4:N10) -> 289.29208 | O11: =SUM(O4:O10) -> 80.384392
B14: Area (CLF$m) | C14: Presupuesto Original | D14: Cambios Aprobados | E14: Presupuesto Actualizado | F14: Tendencias en Rev. de CMDIC | G14: Potenciales Cambios | H14: Forecast | K14: Area (CLF$m) | L14: Presupuesto Original | M14: Cambios Aprobados | N14: Presupuesto Actualizado | O14: Tendencias en Rev. de CMDIC | P14: Potenciales Cambios | Q14: Forecast
C15: A | D15: B | E15: C=A+B | F15: D | G15: E | H15: F=C+D+E | L15: A | M15: B | N15: C=A+B | O15: D | P15: E | Q15: F=C+D+E
B16: Costo Directo | C16: =C4 -> 75765.05 | D16: =+D4 -> 5589.865 | E16: =C16+D16 -> 81354.915 | F16: =+'Log Tendencias'!J58 -> 28.42 | G16: =+'Log Tendencias'!J56 -> 29416.192 | H16: =E16+F16+G16 -> 110799.53 | K16: =+B16 -> Costo Directo | L16: =C16/1000 -> 75.76505 | M16: =D16/1000 -> 5.589865 | N16: =E16/1000 -> 81.354915 | O16: =F16/1000 -> 0.02842 | P16: =G16/1000 -> 29.416192 | Q16: =H16/1000 -> 110.79953
B17: Gastos Generales | C17: =C5 -> 17645.478 | D17: =+D5 -> 0 | E17: =C17+D17 -> 17645.478 | F17: =+'Log Tendencias'!K55+'Log Tendencias'!K58 -> 0 | G17: =+'Log Tendencias'!K56 -> 0 | H17: =E17+F17+G17 -> 17645.478 | K17: =+B17 -> Gastos Generales | L17: =C17/1000 -> 17.645478 | M17: =D17/1000 -> 0 | N17: =E17/1000 -> 17.645478 | O17: =F17/1000 -> 0 | P17: =G17/1000 -> 0 | Q17: =H17/1000 -> 17.645478
B18: Utilidades | C18: =C6 -> 6061.204 | D18: =+D6 -> 446.9092 | E18: =C18+D18 -> 6508.1132 | F18: =+'Log Tendencias'!L58 -> 2.2736 | G18: =+'Log Tendencias'!L56 -> 2353.2954 | H18: =E18+F18+G18 -> 8863.6822 | K18: =+B18 -> Utilidades | L18: =C18/1000 -> 6.061204 | M18: =D18/1000 -> 0.4469092 | N18: =E18/1000 -> 6.5081132 | O18: =F18/1000 -> 0.0022736 | P18: =G18/1000 -> 2.3532954 | Q18: =H18/1000 -> 8.8636822
B19: Viajes y Estadía | C19: =C7 -> 69014.452 | D19: =+D7 -> 9146.6567 | E19: =C19+D19 -> 78161.109 | F19: =+'Log Tendencias'!M58 -> 0 | G19: =+'Log Tendencias'!M56 -> 2960 | H19: =E19+F19+G19 -> 81121.109 | K19: =+B19 -> Viajes y Estadía | L19: =C19/1000 -> 69.014452 | M19: =D19/1000 -> 9.1466567 | N19: =E19/1000 -> 78.161109 | O19: =F19/1000 -> 0 | P19: =G19/1000 -> 2.96 | Q19: =H19/1000 -> 81.121109
B20: Costo Subcontratos | C20: =C8 -> 83157.714 | D20: =+D8 -> 27337.25 | E20: =C20+D20 -> 110494.96 | F20: =+'Log Tendencias'!N58 -> 498.3 | G20: =+'Log Tendencias'!N56 -> 8554 | H20: =E20+F20+G20 -> 119547.26 | K20: =+B20 -> Costo Subcontratos | L20: =C20/1000 -> 83.157714 | M20: =D20/1000 -> 27.33725 | N20: =E20/1000 -> 110.49496 | O20: =F20/1000 -> 0.4983 | P20: =G20/1000 -> 8.554 | Q20: =H20/1000 -> 119.54726
B21: Fee Subcontratos | C21: =C9 -> 4157.8857 | D21: =+D9 -> 1366.9475 | E21: =C21+D21 -> 5524.8332 | F21: =+'Log Tendencias'!O58 -> 24.915 | G21: =+'Log Tendencias'!O56 -> 427.7 | H21: =E21+F21+G21 -> 5977.4482 | K21: =+B21 -> Fee Subcontratos | L21: =C21/1000 -> 4.1578857 | M21: =D21/1000 -> 1.3669475 | N21: =E21/1000 -> 5.5248332 | O21: =F21/1000 -> 0.024915 | P21: =G21/1000 -> 0.4277 | Q21: =H21/1000 -> 5.9774482
B22: Descuento Comercial | C22: =C10 -> -10215.831 | D22: =+D10 -> -181.50399 | E22: =C22+D22 -> -10397.335 | F22: =+'Log Tendencias'!P58 -> -0.8526 | G22: =+'Log Tendencias'!P56 -> -880.29576 | H22: =E22+F22+G22 -> -11278.483 | K22: =+B22 -> Descuento Comercial | L22: =C22/1000 -> -10.215831 | M22: =D22/1000 -> -0.18150399 | N22: =E22/1000 -> -10.397335 | O22: =F22/1000 -> -0.0008526 | P22: =G22/1000 -> -0.88029576 | Q22: =H22/1000 -> -11.278483
B23: Total Contrato | C23: =SUM(C15:C22) -> 245585.95 | D23: =SUM(D15:D22) -> 43706.124 | E23: =SUM(E15:E22) -> 289292.08 | F23: =SUM(F15:F22) -> 553.056 | G23: =SUM(G15:G22) -> 42830.892 | H23: =SUM(H15:H22) -> 332676.02 | K23: Total | L23: =SUM(L15:L22) -> 245.58595 | M23: =SUM(M15:M22) -> 43.706124 | N23: =SUM(N15:N22) -> 289.29208 | O23: =SUM(O15:O22) -> 0.553056 | P23: =SUM(P15:P22) -> 42.830892 | Q23: =SUM(Q15:Q22) -> 332.67602
D27: Cantidad (*) | E27: Periodo (Semana) | G27: Acumulado
E28: Rev. B | F28: Rev. 0 ó Superior | G28: Rev. B | H28: Rev. 0 ó Superior
C29: EL | D29: 1 | G29: 0 | H29: 1
C30: PG | D30: 1 | G30: 1 | H30: 1
C31: DW | D31: 1
C32: EA | D32: 1
C33: IN | D33: 146 | G33: 14 | H33: 11
C34: ME | D34: 352 | F34: 0 | G34: 0 | H34: 42
C35: MT | D35: 1
C36: NS | D36: 1
C37: PP | D37: 1
C38: RS | D38: 125 | F38: 1 | H38: 53
C39: Total | D39: =SUM(D29:D38) -> 630 | E39: =SUM(E29:E38) -> 0 | F39: =SUM(F29:F38) -> 1 | G39: =SUM(G29:G38) -> 15 | H39: =SUM(H29:H38) -> 108

Sheet HITOS
B4: HITO | C4: TIPO | D4: NOMBRE Y/O DESCRIPCIÓN | H4: PLAN | I4: ACTUAL | J4: FORECAST
B6: =1 -> 1 | C6: Contractual | D6: Listado de Entregables Línea Base | H6: 45758 | I6: 45758
B7: =B6+1 -> 2 | C7: Contractual | D7: Programa de Trabajo del Servicio | H7: 45766 | I7: 45406
B8: =B7+1 -> 3 | C8: Contractual | D8: Término acreditación empresa (WSP - Geobiota) | H8: 45781 | I8: 45786
B9: =B8+1 -> 4 | C9: Contractual | D9: Revisión y evaluación de la información existente | H9: 45781 | I9: 45782
B10: =B9+1 -> 5 | C10: Contractual | D10: Determinación y justificación del AI para cada Componente Ambiental | H10: 45786 | I10: 45786
B11: =B10+1 -> 6 | C11: Contractual | D11: Metodología para el desarrollo de Líneas de Base (componentes críticos) | H11: 45786 | I11: =+I10 -> 45786
B12: =B11+1 -> 7 | C12: Multable | D12: Inicio Línea de Base en terreno | H12: 45796 | I12: 45790
B13: =B12+1 -> 8 | C13: Contractual | D13: Ejecución taller de Identificación de los aspectos críticos del Proyecto y estrategia para abordarlos | H13: 45826 | I13: 45869
B14: =B13+1 -> 9 | C14: Contractual | D14: Análisis y verificación propuesta de gestión compromisos ambientales instrumentos anteriores | H14: 45841 | I14: 45883
B15: =B14+1 -> 10 | C15: Contractual | D15: Metodología y criterios para la Evaluación de Impactos e identificación preliminar de impactos significativos y estrategia para abordarlos | H15: 45875 | I15: 45896
B16: =B15+1 -> 11 | C16: Multable | D16: Término Línea de Base en terreno | H16: 46161 | J16: =+H16 -> 46161
B17: =B16+1 -> 12 | C17: Multable | D17: Término elaboración EIA (rev0) | H17: 46378 | J17: =+H17 -> 46378
B18: =B17+1 -> 13 | C18: Contractual | D18: Ingreso del EIA al SEIA | H18: 46385 | J18: =+H18 -> 46385
B19: =B18+1 -> 14 | C19: Contractual | D19: PPT para Presentación del proyecto a los Servicios | H19: 46392 | J19: =+H19 -> 46392

Sheet LOG RFI
K4: =+'Informe Semanal'!$Q$3 -> 46128
B5: =+'Informe Semanal'!D3 -> Reporte Semanal de Proyectos
B7: =+'Informe Semanal'!G4 -> 477-PRI24045-000-083-RS-0054
B9: LOG DE RFI
B11: N° | C11: RFI N° | D11: N° WSP | E11: Rev. | F11: Título | G11: Transmittal Envío | H11: Fecha Envío | I11: Estatus | J11: Transmittal Respuesta | K11: Fecha Respuesta
B12: 1 | C12: 477-PRI24045-000-040-RI-0001 | D12: MCO0019-J- 00000-GL-RFI- 00001 | E12: 0 | F12: Solicitud de Información N°001 - Solicitud de medidas y compromisos ambientales a modificar | G12: WSP_SA-TRN-000024 | H12: 45805 | I12: Cerrada
B13: =+B12+1 -> 2 | C13: 477-PRI24045-000-040-RI-0002 | D13: MCO0019-J- 00000-GL-RFI- 00002 | E13: 0 | F13: Solicitud de información para el desarrollo de los PAS asociados al Proyecto | G13: WSP_SA-TRN-000032 | H13: 45820 | I13: Cerrada | J13: CMDIC-TRN-000073 | K13: 45827
B14: =+B13+1 -> 3 | C14: 477-PRI24045-000-040-RI-0003 | D14: MCO0019-J- 00000-GL-RFI- 00003 | E14: 0 | F14: Información para el desarrollo de la descripción de proyectos | G14: WSP_SA-TRN-000037 | H14: 45821 | I14: Cerrada | J14: CMDIC-TRN-000076 | K14: 45832
C15: 477-PRI24045-000-040-RI-0004 | I15: Cerrada | J15: CMDIC-TRN-000077 | K15: 45833
C16: 477-PRI24045-000-040-RI-0005 | I16: Cerrada | J16: CMDIC-TRN-000078 | K16: 45834
C17: 477-PRI24045-000-040-RI-0006 | I17: Cerrada | J17: CMDIC-TRN-000079 | K17: 45835
C18: 477-PRI24045-000-040-RI-0007 | I18: Cerrada | J18: CMDIC-TRN-000080 | K18: 45836
C19: 477-PRI24045-000-040-RI-0008 | I19: Cerrada | J19: CMDIC-TRN-000081 | K19: 45837
C20: 477-PRI24045-000-040-RI-0009 | I20: Cerrada | J20: CMDIC-TRN-000082 | K20: 45838
C21: 477-PRI24045-000-040-RI-0010 | I21: Cerrada | J21: CMDIC-TRN-000083 | K21: 45839
C22: 477-PRI24045-000-040-RI-0011 | I22: Cerrada | J22: CMDIC-TRN-000084 | K22: 45840
C23: 477-PRI24045-000-040-RI-0012 | I23: Cerrada | J23: CMDIC-TRN-000085 | K23: 45841
B24: 4 | C24: 477-PRI24045-000-040-RI-0004 | D24: MCO0019-J- 00000-GL-RFI- 00004 | E24: 0 | F24: Solicitud de información para cumplimiento del Hito CMDIC Entrega intermedia de ingeniería FEL-3 | G24: WSP_SA-TRN-000070 | H24: 45905 | I24: Cerrada | J24: CMDIC-TRN-000146 | K24: 45952
B25: 5 | C25: 477-PRI24045-000-040-RI-0005 | D25: MCO0019-J- 00000-GL-RFI- 00005 | E25: 0 | F25: Solicitud Matriz Sistematizada de Compromisos Ambientales | G25: WSP_SA-TRN-000094 | H25: 45946 | I25: Cerrada | J25: CMDIC-TRN-000164 | K25: 45978
B26: 6 | C26: 477-PRI24045-000-040-RI-0006 | D26: MCO0019-J- 00000-GL-RFI- 00006 | E26: 0 | F26: Solicitud Entregables Ingeniería FEL 2 Proyecto IGP Collahusi | G26: WSP_SA-TRN-000094 | H26: 45946 | I26: Cerrada | J26: CMDIC-TRN-000162 | K26: 45973
B27: 7 | C27: 477-PRI24045-000-040-RI-0007 | D27: MCO0019-J- 00000-GL-RFI- 00007 | E27: 0 | F27: Solicitud de Información Contrto PRI24045 N°007 - Antecedentes Para Estudio Lumínico | G27: WSP_SA-TRN-000102 | H27: 45966 | I27: Cerrada | J27: CMDIC-TRN-000165 | K27: 45978
B28: 8 | C28: 477-PRI24045-000-040-RI-0008 | D28: MCO0019-J- 00000-GL-RFI- 00008 | E28: 0 | F28: Solicitud de Información Contrato PRI24045 N°008 - Calidad del Aire | G28: WSP_SA-TRN-000155 | H28: 46056 | I28: Cerrada | J28: CMDIC-TRN-000273 | K28: 46071
B29: 9 | C29: 477-PRI24045-000-040-RI-0009 | D29: MCO0019-J- 00000-GL-RFI- 00009 | E29: 0 | F29: Solicitud de Información Contrato PRI24045 N°009 - Cumplimiento del Hito CMDIC Entrega intermedia de ingeniería FEL 3 | G29: WSP_SA-TRN-000156 | H29: 46058 | I29: Cerrada | J29: CMDIC-TRN-000260 | K29: 46059
B30: 10 | C30: 477-PRI24045-000-040-RI-0010 | D30: MCO0019-J- 00000-GL-RFI- 00010 | E30: 0 | F30: Solicitud de información para cumpliemiento del Hito CMDIC Entrega intermedia de ingeniería FEL3 | G30: WSP_SA-TRN-000164 | H30: 46059 | I30: Cerrada | J30: CMDIC-TRN-000307 | K30: 46121
B31: 11 | C31: 477-PRI24045-000-040-RI-0011 | D31: MCO0019-J- 00000-GL-RFI- 00011 | E31: 0 | F31: Solicitud de información Contrato PRI24045 N°11 - Descripción de Proyectos | G31: WSP_SA-TRN-000172 | H31: 46080 | I31: Abierta
B32: 12 | C32: 477-PRI24045-000-040-RI-0012 | D32: MCO0019-J- 00000-GL-RFI- 00012 | E32: 0 | F32: Solicitud de Información para el desarrollo de los PAS asociados al Proyecto. | G32: Enviada por correo | H32: 46101 | I32: Abierta
B33: 13 | C33: 477-PRI24045-000-040-RI-0013 | D33: MCO0019-J- 00000-GL-RFI- 00013 | E33: 0 | F33: Solicitud de información para el desarrollo de la Descripción de Proyectos | G33: Enviada por correo | H33: 46107 | I33: Abierta

Sheet Reporte Aconex
A1: In case any cell is highlighted in Red, that means the data is not exported correctly for that cell as it has exceeded the excel limit of 32767 characters
A2: P477 Elaboración EIA 4ta Línea | I2: WSP Ambiental S.A
A3: Exportar búsqueda a Excel
A4: Proyecto: | B4: P477 Elaboración EIA 4ta Línea
A5: Generado por: | B5: Juan Jofre, WSP Ambiental S.A
A6: Generado el: | B6: jueves 19 de febrero de 2026 4:47:04
A8: Número de resultados:856
A9: Resultados seleccionados:856
A10: Mostrando resultado 1 hasta 856
A11: Archivo | B11: No. de documento | C11: Título | D11: Revisión | E11: Estatus | F11: Creado por | G11: Fecha de modificación | H11: Nombre de archivo | I11: WBS | J11: Función | K11: Tipo | L11: Categoría | M11: N° de Contrato / OC | N11: Bloquear | O11: Transmitido | P11: Transmitido en
A12: N/A | B12: 477-PRI24045-000-010-ME-2044 | C12: Minuta Reunión Técnica 44 de 72 | D12: '- | E12: Placeholder | F12: WSP Ambiental S.A | G12: 45880.52 | I12: 000 General | J12: 010 Medio ambiente - Medio ambiente General | K12: Minuta de reunión | L12: Línea Base | M12: PRI24045-Wsp-EIA Proyecto IGP | N12: No | O12: false | P12: CMDIC-TRN-000104
A13: N/A | B13: 477-PRI24045-000-010-ME-2045 | C13: Minuta Reunión Técnica 45 de 72 | D13: '- | E13: Placeholder | F13: WSP Ambiental S.A | G13: 45880.52 | I13: 000 General | J13: 010 Medio ambiente - Medio ambiente General | K13: Minuta de reunión | L13: Línea Base | M13: PRI24045-Wsp-EIA Proyecto IGP | N13: No | O13: false | P13: CMDIC-TRN-000104
A14: N/A | B14: 477-PRI24045-000-010-ME-2046 | C14: Minuta Reunión Técnica 46 de 72 | D14: '- | E14: Placeholder | F14: WSP Ambiental S.A | G14: 45880.52 | I14: 000 General | J14: 010 Medio ambiente - Medio ambiente General | K14: Minuta de reunión | L14: Línea Base | M14: PRI24045-Wsp-EIA Proyecto IGP | N14: No | O14: false | P14: CMDIC-TRN-000104
A15: N/A | B15: 477-PRI24045-000-010-ME-2047 | C15: Minuta Reunión Técnica 47 de 72 | D15: '- | E15: Placeholder | F15: WSP Ambiental S.A | G15: 45880.52 | I15: 000 General | J15: 010 Medio ambiente - Medio ambiente General | K15: Minuta de reunión | L15: Línea Base | M15: PRI24045-Wsp-EIA Proyecto IGP | N15: No | O15: false | P15: CMDIC-TRN-000104
A16: N/A | B16: 477-PRI24045-000-010-ME-2048 | C16: Minuta Reunión Técnica 48 de 72 | D16: '- | E16: Placeholder | F16: WSP Ambiental S.A | G16: 45880.52 | I16: 000 General | J16: 010 Medio ambiente - Medio ambiente General | K16: Minuta de reunión | L16: Línea Base | M16: PRI24045-Wsp-EIA Proyecto IGP | N16: No | O16: false | P16: CMDIC-TRN-000104
A17: N/A | B17: 477-PRI24045-000-010-ME-2049 | C17: Minuta Reunión Técnica 49 de 72 | D17: '- | E17: Placeholder | F17: WSP Ambiental S.A | G17: 45880.52 | I17: 000 General | J17: 010 Medio ambiente - Medio ambiente General | K17: Minuta de reunión | L17: Línea Base | M17: PRI24045-Wsp-EIA Proyecto IGP | N17: No | O17: false | P17: CMDIC-TRN-000104
A18: N/A | B18: 477-PRI24045-000-010-ME-2050 | C18: Minuta Reunión Técnica 50 de 72 | D18: '- | E18: Placeholder | F18: WSP Ambiental S.A | G18: 45880.52 | I18: 000 General | J18: 010 Medio ambiente - Medio ambiente General | K18: Minuta de reunión | L18: Línea Base | M18: PRI24045-Wsp-EIA Proyecto IGP | N18: No | O18: false | P18: CMDIC-TRN-000104
A19: N/A | B19: 477-PRI24045-000-010-ME-2051 | C19: Minuta Reunión Técnica 51 de 72 | D19: '- | E19: Placeholder | F19: WSP Ambiental S.A | G19: 45880.52 | I19: 000 General | J19: 010 Medio ambiente - Medio ambiente General | K19: Minuta de reunión | L19: Línea Base | M19: PRI24045-Wsp-EIA Proyecto IGP | N19: No | O19: false | P19: CMDIC-TRN-000104
A20: N/A | B20: 477-PRI24045-000-010-ME-2052 | C20: Minuta Reunión Técnica 52 de 72 | D20: '- | E20: Placeholder | F20: WSP Ambiental S.A | G20: 45880.52 | I20: 000 General | J20: 010 Medio ambiente - Medio ambiente General | K20: Minuta de reunión | L20: Línea Base | M20: PRI24045-Wsp-EIA Proyecto IGP | N20: No | O20: false | P20: CMDIC-TRN-000104
A21: N/A | B21: 477-PRI24045-000-010-ME-2053 | C21: Minuta Reunión Técnica 53 de 72 | D21: '- | E21: Placeholder | F21: WSP Ambiental S.A | G21: 45880.52 | I21: 000 General | J21: 010 Medio ambiente - Medio ambiente General | K21: Minuta de reunión | L21: Línea Base | M21: PRI24045-Wsp-EIA Proyecto IGP | N21: No | O21: false | P21: CMDIC-TRN-000104
A22: N/A | B22: 477-PRI24045-000-010-ME-2054 | C22: Minuta Reunión Técnica 54 de 72 | D22: '- | E22: Placeholder | F22: WSP Ambiental S.A | G22: 45880.52 | I22: 000 General | J22: 010 Medio ambiente - Medio ambiente General | K22: Minuta de reunión | L22: Línea Base | M22: PRI24045-Wsp-EIA Proyecto IGP | N22: No | O22: false | P22: CMDIC-TRN-000104
A23: N/A | B23: 477-PRI24045-000-010-ME-2055 | C23: Minuta Reunión Técnica 55 de 72 | D23: '- | E23: Placeholder | F23: WSP Ambiental S.A | G23: 45880.52 | I23: 000 General | J23: 010 Medio ambiente - Medio ambiente General | K23: Minuta de reunión | L23: Línea Base | M23: PRI24045-Wsp-EIA Proyecto IGP | N23: No | O23: false | P23: CMDIC-TRN-000104
... A146: N/A | B146: 477-PRI24045-000-010-ME-8006 | C146: Reunión PAC FORMAL (unitario ) | D146: '- | E146: Placeholder | F146: WSP Ambiental S.A | G146: 45880.52 | I146: 000 General | J146: 010 Medio ambiente - Medio ambiente General | K146: Minuta de reunión | L146: Línea Base | M146: PRI24045-Wsp-EIA Proyecto IGP | N146: No | O146: false | P146: CMDIC-TRN-000104
A147: zip | B147: 477-PRI24045-000-035-CE-0001 | C147: Entrega documentos de Contrato firmados | D147: 0 | E147: Emitido para información | F147: Compañía Minera Doña Inés de Collahuasi SCM | G147: 45791.434 | H147: 477-PRI24045-000-035-CE-0001_R0 Entrega documentos de Contrato firmados.zip | I147: 000 General | J147: 035 Contratos y Adquisiciones - Contratos | K147: Carta | L147: Línea Base | M147: PRI24045-Wsp-EIA Proyecto IGP | N147: No | O147: false | P147: CMDIC-TRN-000050
A148: pdf | B148: 477-PRI24045-000-035-CE-0002 | C148: Respuesta a carta 477-PRI24045-000-035-CL-0001 “Personal Clave Back Up Proyecto EIA ACP Collahuasi” | D148: 0 | E148: Emitido para información | F148: Compañía Minera Doña Inés de Collahuasi SCM | G148: 45793.597 | H148: 477-PRI24045-000-035-CE-0002_R0 Respuesta a carta N 477-PRI24045-000-035-CL-0001.pdf | I148: 000 General | J148: 035 Contratos y Adquisiciones - Contratos | K148: Carta | L148: Línea Base | M148: PRI24045-Wsp-EIA Proyecto IGP | N148: No | O148: false | P148: CMDIC-TRN-000054
A149: zip | B149: 477-PRI24045-000-035-CE-0003 | C149: Aprobación Estado de Pago N° 01 | D149: 0 | E149: Emitido para información | F149: Compañía Minera Doña Inés de Collahuasi SCM | G149: 45817.632 | H149: 477-PRI24045-000-035-CE-0003_R0 Aprobación Estado de Pago N°01.zip | I149: 000 General | J149: 035 Contratos y Adquisiciones - Contratos | K149: Carta | L149: Línea Base | M149: PRI24045-Wsp-EIA Proyecto IGP | N149: No | O149: false | P149: CMDIC-TRN-000066
A150: pdf | B150: 477-PRI24045-000-035-CE-0004 | C150: Entrega de Modelos Hidrogeológicos FEL 2 | D150: 0 | E150: Emitido para información | F150: Compañía Minera Doña Inés de Collahuasi SCM | G150: 45824.394 | H150: 477-PRI24045-000-035-CE-0004_R0 Entrega Modelos Hidrogeológicos FEL 2.pdf | I150: 000 General | J150: 035 Contratos y Adquisiciones - Contratos | K150: Carta | L150: Línea Base | M150: PRI24045-Wsp-EIA Proyecto IGP | N150: No | O150: false | P150: CMDIC-TRN-000071
A151: pdf | B151: 477-PRI24045-000-035-CE-0005 | C151: Respuesta a carta 477-PRI24045-000-035-CL-0005 “Postergación Hito 8 Proyecto EIA ACP Collahuasi – Taller de aspectos críticos del Proyecto” | D151: 0 | E151: Emitido para información | F151: Compañía Minera Doña Inés de Collahuasi SCM | G151: 45831.677 | H151: 477-PRI24045-000-035-CE-0005_R0 Respuesta a carta N 477-PRI24045-000-035-CL-0005.pdf | I151: 000 General | J151: 035 Contratos y Adquisiciones - Contratos | K151: Carta | L151: Línea Base | M151: PRI24045-Wsp-EIA Proyecto IGP | N151: No | O151: false | P151: CMDIC-TRN-000074
A152: pdf | B152: 477-PRI24045-000-035-CE-0006 | C152: Respuesta a carta 477-PRI24045-000-035-CL-0006 “Personal Clave Back Up Proyecto EIA ACP Collahuasi” | D152: 0 | E152: Emitido para información | F152: Compañía Minera Doña Inés de Collahuasi SCM | G152: 45848.33 | H152: 477-PRI24045-000-035-CE-0006_R0 Respuesta a carta N 477-PRI24045-000-035-CL-0006.pdf | I152: 000 General | J152: 035 Contratos y Adquisiciones - Contratos | K152: Carta | L152: Línea Base | M152: PRI24045-Wsp-EIA Proyecto IGP | N152: No | O152: false | P152: CMDIC-TRN-000087
A153: pdf | B153: 477-PRI24045-000-035-CE-0007 | C153: Respuesta a carta 477-PRI24045-000-035-CL-0008 “Postergación Hito 8 Proyecto EIA ACP Collahuasi – Taller de aspectos críticos del Proyecto” | D153: 0 | E153: Emitido para información | F153: Compañía Minera Doña Inés de Collahuasi SCM | G153: 45848.33 | H153: 477-PRI24045-000-035-CE-0007_R0 Respuesta a carta N 477-PRI24045-000-035-CL-0008.pdf | I153: 000 General | J153: 035 Contratos y Adquisiciones - Contratos | K153: Carta | L153: Línea Base | M153: PRI24045-Wsp-EIA Proyecto IGP | N153: No | O153: false | P153: CMDIC-TRN-000087
A154: pdf | B154: 477-PRI24045-000-035-CE-0008 | C154: Respuesta a carta 477-PRI24045-000-035-CL-0009 “Postergación Hito 9 Proyecto EIA ACP Collahuasi – Taller análisis y verificación compromisos ambientales instrumentos anteriores” | D154: 0 | E154: Emitido para información | F154: Compañía Minera Doña Inés de Collahuasi SCM | G154: 45873.626 | H154: 477-PRI24045-000-035-CE-0008_R0 Respuesta a carta N 477-PRI24045-000-035-CL-0009.pdf | I154: 000 General | J154: 035 Contratos y Adquisiciones - Contratos | K154: Carta | L154: Línea Base | M154: PRI24045-Wsp-EIA Proyecto IGP | N154: No | O154: false | P154: CMDIC-TRN-000100
A155: zip | B155: 477-PRI24045-000-035-CE-0009 | C155: Aprobación Estado de Pago N° 02 | D155: 0 | E155: Emitido para información | F155: Compañía Minera Doña Inés de Collahuasi SCM | G155: 45875.372 | H155: 477-PRI24045-000-035-CE-0009_R0 Aprobación Estado de Pago N°02.zip | I155: 000 General | J155: 035 Contratos y Adquisiciones - Contratos | K155: Carta | L155: Línea Base | M155: PRI24045-Wsp-EIA Proyecto IGP | N155: No | O155: false | P155: CMDIC-TRN-000102
A156: pdf | B156: 477-PRI24045-000-035-CE-0010 | C156: Respuesta a carta 477-PRI24045-000-035-CL-0010 “Postergación Hito 9 Proyecto EIA ACP Collahuasi – Taller análisis y verificación compromisos ambientales instrumentos anteriores” | D156: 0 | E156: Emitido para información | F156: Compañía Minera Doña Inés de Collahuasi SCM | G156: 45890.613 | H156: 477-PRI24045-000-035-CE-0010_R0 Respuesta a carta N 477-PRI24045-000-035-CL-0010.pdf | I156: 000 General | J156: 035 Contratos y Adquisiciones - Contratos | K156: Carta | L156: Línea Base | M156: PRI24045-Wsp-EIA Proyecto IGP | N156: No | O156: false | P156: CMDIC-TRN-000113
A157: pdf | B157: 477-PRI24045-000-035-CE-0011 | C157: Respuesta a carta 477-PRI24045-000-035-CL-0011 “Postergación Hito 10 Proyecto EIA ACP Collahuasi – Identificación preliminar de los Impactos Significativos y Estrategia para Abordarlos” | D157: 0 | E157: Emitido para información | F157: Compañía Minera Doña Inés de Collahuasi SCM | G157: 45890.613 | H157: 477-PRI24045-000-035-CE-0011_R0 Respuesta a carta N 477-PRI24045-000-035-CL-0011.pdf | I157: 000 General | J157: 035 Contratos y Adquisiciones - Contratos | K157: Carta | L157: Línea Base | M157: PRI24045-Wsp-EIA Proyecto IGP | N157: No | O157: false | P157: CMDIC-TRN-000113
A158: pdf | B158: 477-PRI24045-000-035-CE-0012 | C158: Solicitud de reemplazo de Personal Clave – Jefe de Proyecto | D158: 0 | E158: Emitido para información | F158: Compañía Minera Doña Inés de Collahuasi SCM | G158: 45903.491 | H158: 477-PRI24045-000-035-CE-0012_R0 Solicitud de reemplazo de Personal Clave Jefe de Proyecto.pdf | I158: 000 General | J158: 035 Contratos y Adquisiciones - Contratos | K158: Carta | L158: Línea Base | M158: PRI24045-Wsp-EIA Proyecto IGP | N158: No | O158: false | P158: CMDIC-TRN-000119
... A168: zip | B168: 477-PRI24045-000-035-CE-0022 | C168: Aprobación Estado de Pago N° 06 | D168: 0 | E168: Emitido para información | F168: Compañía Minera Doña Inés de Collahuasi SCM | G168: 46058.367 | H168: 477-PRI24045-000-035-CE-0022_R0 Aprobación Estado de Pago N06.zip | I168: 000 General | J168: 035 Contratos y Adquisiciones - Contratos | K168: Carta | L168: Línea Base | M168: PRI24045-Wsp-EIA Proyecto IGP | N168: No | O168: false | P168: CMDIC-TRN-000259
A169: zip | B169: 477-PRI24045-000-035-CL-0001 | C169: Carta - Personal Clave Back Up Proyecto EIA ACP Collahuasi | D169: 0 | E169: Emitido para aprobación | F169: WSP Ambiental S.A | G169: 45763.57 | H169: 477-PRI24045-000-035-CL-0001.zip | I169: 000 General | J169: 035 Contratos y Adquisiciones - Contratos | K169: Carta | L169: Línea Base | M169: PRI24045-Wsp-EIA Proyecto IGP | N169: No | O169: true
A170: pdf | B170: 477-PRI24045-000-035-CL-0002 | C170: Carta - Personal Clave de Vacaciones | D170: 0 | E170: Emitido para aprobación | F170: WSP Ambiental S.A | G170: 45764.433 | H170: 477-PRI24045-000-035-CL-0002.pdf | I170: 000 General | J170: 035 Contratos y Adquisiciones - Contratos | K170: Carta | L170: Línea Base | M170: PRI24045-Wsp-EIA Proyecto IGP | N170: No | O170: true
A171: pdf | B171: 477-PRI24045-000-035-CL-0003 | C171: Carta - Entrega Hito 2 | D171: 0 | E171: Emitido para aprobación | F171: WSP Ambiental S.A | G171: 45771.871 | H171: 477-PRI24045-000-035-CL-0003.pdf | I171: 000 General | J171: 035 Contratos y Adquisiciones - Contratos | K171: Carta | L171: Línea Base | M171: PRI24045-Wsp-EIA Proyecto IGP | N171: No | O171: true
A172: pdf | B172: 477-PRI24045-000-035-CL-0004 | C172: Carta - Cumplimiento Hito 7 - Inicio Línea de Base en Terreno | D172: 0 | E172: Emitido para aprobación | F172: WSP Ambiental S.A | G172: 45800.414 | H172: 477-PRI24045-000-035-CL-0004.pdf | I172: 000 General | J172: 035 Contratos y Adquisiciones - Contratos | K172: Carta | L172: Línea Base | M172: PRI24045-Wsp-EIA Proyecto IGP | N172: No | O172: true
A173: pdf | B173: 477-PRI24045-000-035-CL-0005 | C173: POSTERGACIÓN HITO 8 PROYECTO EIA ACP COLLAHUASI – TALLER DE ASPECTOS CRÍTICOS DEL PROYECTO | D173: 0 | E173: Respuesta Requerida | F173: WSP Ambiental S.A | G173: 45818.47 | H173: 477-PRI24045-000-035-CL-0005.pdf | I173: 000 General | J173: 035 Contratos y Adquisiciones - Contratos | K173: Carta | L173: Línea Base | M173: PRI24045-Wsp-EIA Proyecto IGP | N173: No | O173: true
A174: zip | B174: 477-PRI24045-000-035-CL-0006 | C174: Carta - PERSONAL CLAVE BACK UP PROYECTO EIA ACP COLLAHUASI – DIRECTOR Y JEFE DE PROYECTO | D174: 0 | E174: Respuesta Requerida | F174: WSP Ambiental S.A | G174: 45821.557 | H174: 477-PRI24045-000-035-CL-0006.zip | I174: 000 General | J174: 035 Contratos y Adquisiciones - Contratos | K174: Carta | L174: Línea Base | M174: PRI24045-Wsp-EIA Proyecto IGP | N174: No | O174: true
A175: pdf | B175: 477-PRI24045-000-035-CL-0007 | C175: PERSONAL CLAVE DE VACACIONES | D175: 0 | E175: Emitido para información | F175: WSP Ambiental S.A | G175: 45832.69 | H175: 477-PRI24045-000-035-CL-0007.pdf | I175: 000 General | J175: 035 Contratos y Adquisiciones - Contratos | K175: Carta | L175: Línea Base | M175: PRI24045-Wsp-EIA Proyecto IGP | N175: No | O175: true
A176: zip | B176: 477-PRI24045-000-035-CL-0008 | C176: RESPUESTA CARTA 477-PRI24045-000-035-CE-0005 | D176: 0 | E176: Respuesta Requerida | F176: WSP Ambiental S.A | G176: 45834.702 | H176: 477-PRI24045-000-035-CL-0008.zip | I176: 000 General | J176: 035 Contratos y Adquisiciones - Contratos | K176: Carta | L176: Línea Base | M176: PRI24045-Wsp-EIA Proyecto IGP | N176: No | O176: true
A177: pdf | B177: 477-PRI24045-000-035-CL-0009 | C177: POSTERGACIÓN HITO 9 PROYECTO EIA ACP COLLAHUASI – TALLER ANÁLISIS Y VERIFICACIÓN COMPROMISOS AMBIENTALES INSTRUMENTOS ANTERIORES | D177: 0 | E177: Respuesta Requerida | F177: WSP Ambiental S.A | G177: 45860.688 | H177: 477-PRI24045-000-035-CL-0009.pdf | I177: 000 General | J177: 035 Contratos y Adquisiciones - Contratos | K177: Carta | L177: Línea Base | M177: PRI24045-Wsp-EIA Proyecto IGP | N177: No | O177: true
A178: pdf | B178: 477-PRI24045-000-035-CL-0010 | C178: POSTERGACIÓN HITO 9 PROYECTO EIA ACP COLLAHUASI – ANÁLISIS Y VERIFICACIÓN COMPROMISOS AMBIENTALES INSTRUMENTOS ANTERIORES | D178: 0 | E178: Emitido para información | F178: WSP Ambiental S.A | G178: 45877.55 | H178: 477-PRI24045-000-035-CL-0010.pdf | I178: 000 General | J178: 035 Contratos y Adquisiciones - Contratos | K178: Carta | L178: Línea Base | M178: PRI24045-Wsp-EIA Proyecto IGP | N178: No | O178: true
A179: pdf | B179: 477-PRI24045-000-035-CL-0011 | C179: POSTERGACIÓN HITO 10 PROYECTO EIA ACP COLLAHUASI – IDENTIFICACIÓN PRELIMINAR DE LOS IMPACTOS SIGNIFICATIVOS Y ESTRATEGIA PARA ABORDARLOS | D179: 0 | E179: Emitido para información | F179: WSP Ambiental S.A | G179: 45877.553 | H179: 477-PRI24045-000-035-CL-0011.pdf | I179: 000 General | J179: 035 Contratos y Adquisiciones - Contratos | K179: Carta | L179: Línea Base | M179: PRI24045-Wsp-EIA Proyecto IGP | N179: No | O179: true
A180: pdf | B180: 477-PRI24045-000-035-CL-0012 | C180: RESPUESTA CARTA SOLICITUD DE INFORMACIÓN FINANCIERA | D180: 0 | E180: Emitido para información | F180: WSP Ambiental S.A | G180: 45910.6 | H180: 477-PRI24045-000-035-CL-0012.pdf | I180: 000 General | J180: 035 Contratos y Adquisiciones - Contratos | K180: Carta | L180: Línea Base | M180: PRI24045-Wsp-EIA Proyecto IGP | N180: No | O180: true
... A189: pdf | B189: 477-PRI24045-000-035-CL-0021 | C189: VACACIONES PERSONAL CLAVE PROYECTO EIA ACP | D189: 0 | E189: Emitido para información | F189: WSP Ambiental S.A | G189: 46036.634 | H189: 477-PRI24045-000-035-CL-0021.pdf | I189: 000 General | J189: 035 Contratos y Adquisiciones - Contratos | K189: Carta | L189: Línea Base | M189: PRI24045-Wsp-EIA Proyecto IGP | N189: No | O189: true
A190: pdf | B190: 477-PRI24045-000-035-EP-0001 | C190: PRI24045 - Estado de Pago N°001 | D190: 1 | E190: Aprobado | F190: WSP Ambiental S.A | G190: 45812.627 | H190: 477-PRI24045-000-035-EP-0001[1]_Integración.pdf | I190: 000 General | J190: 035 Contratos y Adquisiciones - Contratos | K190: Estado de Pago | L190: Línea Base | M190: PRI24045-Wsp-EIA Proyecto IGP | N190: No | O190: false | P190: CMDIC-TRN-000064
A191: pdf | B191: 477-PRI24045-000-035-EP-0002 | C191: Estado de Pago N°0002 | D191: 1 | E191: Aprobado | F191: WSP Ambiental S.A | G191: 45873.776 | H191: 477-PRI24045-000-035-EP-0002[1]_Integración.pdf | I191: 000 General | J191: 035 Contratos y Adquisiciones - Contratos | K191: Estado de Pago | L191: Línea Base | M191: PRI24045-Wsp-EIA Proyecto IGP | N191: No | O191: false | P191: CMDIC-TRN-000101
A192: pdf | B192: 477-PRI24045-000-035-EP-0003 | C192: Estado de Pago N°0003 | D192: 0 | E192: Aprobado | F192: WSP Ambiental S.A | G192: 45917.424 | H192: 477-PRI24045-000-035-EP-0003[0]_Integración.pdf | I192: 000 General | J192: 035 Contratos y Adquisiciones - Contratos | K192: Estado de Pago | L192: Línea Base | M192: PRI24045-Wsp-EIA Proyecto IGP | N192: No | O192: false | P192: CMDIC-TRN-000127
A193: pdf | B193: 477-PRI24045-000-035-EP-0004 | C193: Estado de Pago N°0004 | D193: 1 | E193: Aprobado | F193: WSP Ambiental S.A | G193: 45960.578 | H193: 477-PRI24045-000-035-EP-0004[1]_Integración.pdf | I193: 000 General | J193: 035 Contratos y Adquisiciones - Contratos | K193: Estado de Pago | L193: Línea Base | M193: PRI24045-Wsp-EIA Proyecto IGP | N193: No | O193: false | P193: CMDIC-TRN-000153
A194: pdf | B194: 477-PRI24045-000-035-EP-0005 | C194: Estado de Pago N°0005 | D194: 0 | E194: Aprobado | F194: WSP Ambiental S.A | G194: 45994.431 | H194: 477-PRI24045-000-035-EP-0005 R0 v2_Integración.pdf | I194: 000 General | J194: 035 Contratos y Adquisiciones - Contratos | K194: Estado de Pago | L194: Línea Base | M194: PRI24045-Wsp-EIA Proyecto IGP | N194: No | O194: false | P194: CMDIC-TRN-000189
A195: pdf | B195: 477-PRI24045-000-035-EP-0006 | C195: Estado de Pago N°0006 | D195: 2 | E195: Aprobado | F195: WSP Ambiental S.A | G195: 46057.401 | H195: 477-PRI24045-000-035-EP-0006[2]_Integración.pdf | I195: 000 General | J195: 035 Contratos y Adquisiciones - Contratos | K195: Estado de Pago | L195: Línea Base | M195: PRI24045-Wsp-EIA Proyecto IGP | N195: No | O195: false | P195: CMDIC-TRN-000256
A196: pdf | B196: 477-PRI24045-000-035-EP-0007 | C196: Estado de Pago N°0007 | D196: 0 | E196: Emitido para aprobación | F196: WSP Ambiental S.A | G196: 46062.595 | H196: 477-PRI24045-000-035-EP-0007.pdf | I196: 000 General | J196: 035 Contratos y Adquisiciones - Contratos | K196: Estado de Pago | L196: Línea Base | M196: PRI24045-Wsp-EIA Proyecto IGP | N196: No | O196: true
A197: pdf | B197: 477-PRI24045-000-035-LA-0001 | C197: Carta de Adjudicación y Orden de Proceder | D197: 0 | E197: Emitido para información | F197: Compañía Minera Doña Inés de Collahuasi SCM | G197: 45748.685 | H197: 477-PRI24045-000-035-LA-0001_R0 Carta de Adjudicación y Orden de Proceder (002)_JG.pdf | I197: 000 General | J197: 035 Contratos y Adquisiciones - Contratos | K197: Carta de Adjudicación | L197: Línea Base | M197: PRI24045-Wsp-EIA Proyecto IGP | N197: No | O197: false | P197: CMDIC-TRN-000030
A198: zip | B198: 477-PRI24045-000-035-ME-0001 | C198: Minuta Reunión Contractual Semanal Contrato PRI24045 - 09-04-2025 | D198: 0 | E198: Emitido para información | F198: WSP Ambiental S.A | G198: 45772.416 | H198: 477-PRI24045-000-035-ME-0001.zip | I198: 000 General | J198: 035 Contratos y Adquisiciones - Contratos | K198: Minuta de reunión | L198: Línea Base | M198: PRI24045-Wsp-EIA Proyecto IGP | N198: No | O198: false | P198: CMDIC-TRN-000038
A199: pdf | B199: 477-PRI24045-000-035-ME-0002 | C199: Minuta Reunión Contractual Semanal Contrato PRI24045 - 16-04-2025 | D199: 0 | E199: Emitido para información | F199: WSP Ambiental S.A | G199: 45833.672 | H199: 477-PRI24045-000-035-ME-0002.pdf | I199: 000 General | J199: 035 Contratos y Adquisiciones - Contratos | K199: Minuta de reunión | L199: Línea Base | M199: PRI24045-Wsp-EIA Proyecto IGP | N199: No | O199: true
A200: pdf | B200: 477-PRI24045-000-035-ME-0003 | C200: Minuta Reunión Contractual Semanal Contrato PRI24045 - 23-04-2025 | D200: 0 | E200: Emitido para información | F200: WSP Ambiental S.A | G200: 45833.674 | H200: 477-PRI24045-000-035-ME-0003.pdf | I200: 000 General | J200: 035 Contratos y Adquisiciones - Contratos | K200: Minuta de reunión | L200: Línea Base | M200: PRI24045-Wsp-EIA Proyecto IGP | N200: No | O200: true
A201: pdf | B201: 477-PRI24045-000-035-ME-0004 | C201: Minuta Reunión Contractual Semanal Contrato PRI24045 - 30-04-2025 | D201: 0 | E201: Emitido para información | F201: WSP Ambiental S.A | G201: 45833.675 | H201: 477-PRI24045-000-035-ME-0004.pdf | I201: 000 General | J201: 035 Contratos y Adquisiciones - Contratos | K201: Minuta de reunión | L201: Línea Base | M201: PRI24045-Wsp-EIA Proyecto IGP | N201: No | O201: true
A202: pdf | B202: 477-PRI24045-000-035-ME-0005 | C202: Minuta Reunión Contractual Semanal Contrato PRI24045 - 14-05-2025 | D202: 0 | E202: Emitido para información | F202: WSP Ambiental S.A | G202: 45833.677 | H202: 477-PRI24045-000-035-ME-0005.pdf | I202: 000 General | J202: 035 Contratos y Adquisiciones - Contratos | K202: Minuta de reunión | L202: Línea Base | M202: PRI24045-Wsp-EIA Proyecto IGP | N202: No | O202: true
A203: pdf | B203: 477-PRI24045-000-035-ME-0006 | C203: Minuta Reunión Contractual Semanal N°6 Contrato PRI24045 - 28-05-2025 | D203: 0 | E203: Emitido para información | F203: WSP Ambiental S.A | G203: 45888.534 | H203: 477-PRI24045-000-035-ME-0006.pdf | I203: 000 General | J203: 035 Contratos y Adquisiciones - Contratos | K203: Minuta de reunión | L203: Línea Base | M203: PRI24045-Wsp-EIA Proyecto IGP | N203: No | O203: true
A204: pdf | B204: 477-PRI24045-000-035-ME-0007 | C204: Minuta Reunión Contractual Semanal N°7 Contrato PRI24045 - 04-06-2025 | D204: 0 | E204: Emitido para información | F204: WSP Ambiental S.A | G204: 45888.535 | H204: 477-PRI24045-000-035-ME-0007.pdf | I204: 000 General | J204: 035 Contratos y Adquisiciones - Contratos | K204: Minuta de reunión | L204: Línea Base | M204: PRI24045-Wsp-EIA Proyecto IGP | N204: No | O204: true
A205: pdf | B205: 477-PRI24045-000-035-ME-0008 | C205: Minuta Reunión Contractual Semanal N°8 Contrato PRI24045 - 11-06-2025 | D205: 0 | E205: Emitido para información | F205: WSP Ambiental S.A | G205: 45888.536 | H205: 477-PRI24045-000-035-ME-0008.pdf | I205: 000 General | J205: 035 Contratos y Adquisiciones - Contratos | K205: Minuta de reunión | L205: Línea Base | M205: PRI24045-Wsp-EIA Proyecto IGP | N205: No | O205: true
A206: pdf | B206: 477-PRI24045-000-035-ME-0009 | C206: Minuta Reunión Contractual Semanal N°9 Contrato PRI24045 - 18-06-2025 | D206: 0 | E206: Emitido para información | F206: WSP Ambiental S.A | G206: 45888.537 | H206: 477-PRI24045-000-035-ME-0009.pdf | I206: 000 General | J206: 035 Contratos y Adquisiciones - Contratos | K206: Minuta de reunión | L206: Línea Base | M206: PRI24045-Wsp-EIA Proyecto IGP | N206: No | O206: true
A207: pdf | B207: 477-PRI24045-000-035-ME-0010 | C207: Minuta Reunión Contractual Semanal N°10 Contrato PRI24045 - 25-06-2025 | D207: 0 | E207: Emitido para información | F207: WSP Ambiental S.A | G207: 45888.538 | H207: 477-PRI24045-000-035-ME-0010.pdf | I207: 000 General | J207: 035 Contratos y Adquisiciones - Contratos | K207: Minuta de reunión | L207: Línea Base | M207: PRI24045-Wsp-EIA Proyecto IGP | N207: No | O207: true
A208: pdf | B208: 477-PRI24045-000-035-ME-0011 | C208: Minuta Reunión Contractual Semanal N°11 Contrato PRI24045 - 02-07-2025 | D208: 0 | E208: Emitido para información | F208: WSP Ambiental S.A | G208: 45888.539 | H208: 477-PRI24045-000-035-ME-0011.pdf | I208: 000 General | J208: 035 Contratos y Adquisiciones - Contratos | K208: Minuta de reunión | L208: Línea Base | M208: PRI24045-Wsp-EIA Proyecto IGP | N208: No | O208: true
A209: pdf | B209: 477-PRI24045-000-035-ME-0012 | C209: Minuta Reunión Contractual Semanal N°12 Contrato PRI24045 - 09-07-2025 | D209: 0 | E209: Emitido para información | F209: WSP Ambiental S.A | G209: 45982.262 | H209: 477-PRI24045-000-035- ME-0012.pdf | I209: 000 General | J209: 035 Contratos y Adquisiciones - Contratos | K209: Minuta de reunión | L209: Línea Base | M209: PRI24045-Wsp-EIA Proyecto IGP | N209: No | O209: true
A210: pdf | B210: 477-PRI24045-000-035-ME-0013 | C210: Minuta Reunión Contractual Semanal N°13 Contrato PRI24045 - 23-07-2025 | D210: 0 | E210: Emitido para información | F210: WSP Ambiental S.A | G210: 46020.552 | H210: 477-PRI24045-000-035- ME-0013.pdf | I210: 000 General | J210: 035 Contratos y Adquisiciones - Contratos | K210: Minuta de reunión | L210: Línea Base | M210: PRI24045-Wsp-EIA Proyecto IGP | N210: No | O210: true
... A218: pdf | B218: 477-PRI24045-000-035-ME-0021 | C218: Minuta Reunión Contractual Semanal N°21 Contrato PRI24045 - 08-10-2025 | D218: 0 | E218: Emitido para información | F218: WSP Ambiental S.A | G218: 46020.552 | H218: 477-PRI24045-000-035- ME-0021.pdf | I218: 000 General | J218: 035 Contratos y Adquisiciones - Contratos | K218: Minuta de reunión | L218: Línea Base | M218: PRI24045-Wsp-EIA Proyecto IGP | N218: No | O218: true
A219: N/A | B219: 477-PRI24045-000-035-ME-0022 | C219: Minuta Reunión Contractual Semanal 22 de 125 | D219: '- | E219: Placeholder | F219: WSP Ambiental S.A | G219: 45880.52 | I219: 000 General | J219: 035 Contratos y Adquisiciones - Contratos | K219: Minuta de reunión | L219: Línea Base | M219: PRI24045-Wsp-EIA Proyecto IGP | N219: No | O219: false | P219: CMDIC-TRN-000104
A220: N/A | B220: 477-PRI24045-000-035-ME-0023 | C220: Minuta Reunión Contractual Semanal 23 de 125 | D220: '- | E220: Placeholder | F220: WSP Ambiental S.A | G220: 45880.52 | I220: 000 General | J220: 035 Contratos y Adquisiciones - Contratos | K220: Minuta de reunión | L220: Línea Base | M220: PRI24045-Wsp-EIA Proyecto IGP | N220: No | O220: false | P220: CMDIC-TRN-000104
A221: N/A | B221: 477-PRI24045-000-035-ME-0024 | C221: Minuta Reunión Contractual Semanal 24 de 125 | D221: '- | E221: Placeholder | F221: WSP Ambiental S.A | G221: 45880.52 | I221: 000 General | J221: 035 Contratos y Adquisiciones - Contratos | K221: Minuta de reunión | L221: Línea Base | M221: PRI24045-Wsp-EIA Proyecto IGP | N221: No | O221: false | P221: CMDIC-TRN-000104
A222: N/A | B222: 477-PRI24045-000-035-ME-0025 | C222: Minuta Reunión Contractual Semanal 25 de 125 | D222: '- | E222: Placeholder | F222: WSP Ambiental S.A | G222: 45880.52 | I222: 000 General | J222: 035 Contratos y Adquisiciones - Contratos | K222: Minuta de reunión | L222: Línea Base | M222: PRI24045-Wsp-EIA Proyecto IGP | N222: No | O222: false | P222: CMDIC-TRN-000104
A223: N/A | B223: 477-PRI24045-000-035-ME-0026 | C223: Minuta Reunión Contractual Semanal 26 de 125 | D223: '- | E223: Placeholder | F223: WSP Ambiental S.A | G223: 45880.52 | I223: 000 General | J223: 035 Contratos y Adquisiciones - Contratos | K223: Minuta de reunión | L223: Línea Base | M223: PRI24045-Wsp-EIA Proyecto IGP | N223: No | O223: false | P223: CMDIC-TRN-000104
A224: N/A | B224: 477-PRI24045-000-035-ME-0027 | C224: Minuta Reunión Contractual Semanal 27 de 125 | D224: '- | E224: Placeholder | F224: WSP Ambiental S.A | G224: 45880.52 | I224: 000 General | J224: 035 Contratos y Adquisiciones - Contratos | K224: Minuta de reunión | L224: Línea Base | M224: PRI24045-Wsp-EIA Proyecto IGP | N224: No | O224: false | P224: CMDIC-TRN-000104
A225: N/A | B225: 477-PRI24045-000-035-ME-0028 | C225: Minuta Reunión Contractual Semanal 28 de 125 | D225: '- | E225: Placeholder | F225: WSP Ambiental S.A | G225: 45880.52 | I225: 000 General | J225: 035 Contratos y Adquisiciones - Contratos | K225: Minuta de reunión | L225: Línea Base | M225: PRI24045-Wsp-EIA Proyecto IGP | N225: No | O225: false | P225: CMDIC-TRN-000104
A226: N/A | B226: 477-PRI24045-000-035-ME-0029 | C226: Minuta Reunión Contractual Semanal 29 de 125 | D226: '- | E226: Placeholder | F226: WSP Ambiental S.A | G226: 45880.52 | I226: 000 General | J226: 035 Contratos y Adquisiciones - Contratos | K226: Minuta de reunión | L226: Línea Base | M226: PRI24045-Wsp-EIA Proyecto IGP | N226: No | O226: false | P226: CMDIC-TRN-000104
A227: N/A | B227: 477-PRI24045-000-035-ME-0030 | C227: Minuta Reunión Contractual Semanal 30 de 125 | D227: '- | E227: Placeholder | F227: WSP Ambiental S.A | G227: 45880.52 | I227: 000 General | J227: 035 Contratos y Adquisiciones - Contratos | K227: Minuta de reunión | L227: Línea Base | M227: PRI24045-Wsp-EIA Proyecto IGP | N227: No | O227: false | P227: CMDIC-TRN-000104
A228: N/A | B228: 477-PRI24045-000-035-ME-0031 | C228: Minuta Reunión Contractual Semanal 31 de 125 | D228: '- | E228: Placeholder | F228: WSP Ambiental S.A | G228: 45880.52 | I228: 000 General | J228: 035 Contratos y Adquisiciones - Contratos | K228: Minuta de reunión | L228: Línea Base | M228: PRI24045-Wsp-EIA Proyecto IGP | N228: No | O228: false | P228: CMDIC-TRN-000104
A229: N/A | B229: 477-PRI24045-000-035-ME-0032 | C229: Minuta Reunión Contractual Semanal 32 de 125 | D229: '- | E229: Placeholder | F229: WSP Ambiental S.A | G229: 45880.52 | I229: 000 General | J229: 035 Contratos y Adquisiciones - Contratos | K229: Minuta de reunión | L229: Línea Base | M229: PRI24045-Wsp-EIA Proyecto IGP | N229: No | O229: false | P229: CMDIC-TRN-000104
A230: N/A | B230: 477-PRI24045-000-035-ME-0033 | C230: Minuta Reunión Contractual Semanal 33 de 125 | D230: '- | E230: Placeholder | F230: WSP Ambiental S.A | G230: 45880.52 | I230: 000 General | J230: 035 Contratos y Adquisiciones - Contratos | K230: Minuta de reunión | L230: Línea Base | M230: PRI24045-Wsp-EIA Proyecto IGP | N230: No | O230: false | P230: CMDIC-TRN-000104
... A322: N/A | B322: 477-PRI24045-000-035-ME-0125 | C322: Minuta Reunión Contractual Semanal 125 de 125 | D322: '- | E322: Placeholder | F322: WSP Ambiental S.A | G322: 45880.52 | I322: 000 General | J322: 035 Contratos y Adquisiciones - Contratos | K322: Minuta de reunión | L322: Línea Base | M322: PRI24045-Wsp-EIA Proyecto IGP | N322: No | O322: false | P322: CMDIC-TRN-000104
A323: zip | B323: 477-PRI24045-000-040-RI-0001 | C323: Solicitud de Información Contrato PRI24045 N°001 - Solicitud de medidas y compromisos ambientales a modificar | D323: 0 | E323: Respondido | F323: WSP Ambiental S.A | G323: 45838.358 | H323: 477-PRI24045-000-040-RI-0001.zip | I323: 000 General | J323: 040 Ingeniería - Ingeniería General | K323: Solicitud de Información | L323: Línea Base | M323: PRI24045-Wsp-EIA Proyecto IGP | N323: No | O323: false | P323: CMDIC-TRN-000080
A324: pdf | B324: 477-PRI24045-000-040-RI-0002 | C324: Solicitud de Información Contrato PRI24045 N°002 - Solicitud para el Desarrollo de los PAS Asociados al Proyecto | D324: 0 | E324: Respondido | F324: WSP Ambiental S.A | G324: 45827.337 | H324: 477-PRI24045-000-040-RI-0002.pdf | I324: 000 General | J324: 040 Ingeniería - Ingeniería General | K324: Solicitud de Información | L324: Línea Base | M324: PRI24045-Wsp-EIA Proyecto IGP | N324: No | O324: false | P324: CMDIC-TRN-000073
A325: pdf | B325: 477-PRI24045-000-040-RI-0003 | C325: Contrato PRI24045 - Solicitud de Información N°003 - información para el desarrollo de la Descripción de Proyectos | D325: 0 | E325: Respondido | F325: WSP Ambiental S.A | G325: 45832.643 | H325: 477-PRI24045-000-040-RI-0003.pdf | I325: 000 General | J325: 040 Ingeniería - Ingeniería General | K325: Solicitud de Información | L325: Línea Base | M325: PRI24045-Wsp-EIA Proyecto IGP | N325: No | O325: false | P325: CMDIC-TRN-000076
A326: pdf | B326: 477-PRI24045-000-040-RI-0004 | C326: Solicitud de Información Contrato PRI24045 N°004 - Cumplimiento del Hito CMDIC Entrega Intermedia de Ingeniería FEL3 | D326: 0 | E326: Respondido | F326: WSP Ambiental S.A | G326: 45952.627 | H326: 477-PRI24045-000-040-RI-0004.pdf | I326: 000 General | J326: 040 Ingeniería - Ingeniería General | K326: Solicitud de Información | L326: Línea Base | M326: PRI24045-Wsp-EIA Proyecto IGP | N326: No | O326: false | P326: CMDIC-TRN-000146
A327: pdf | B327: 477-PRI24045-000-040-RI-0005 | C327: Solicitud de Información Contrato PRI24045 N°005 - Solicitud de Matriz Sistematizada de Compromisos Ambientales | D327: 0 | E327: Respondido | F327: WSP Ambiental S.A | G327: 45978.604 | H327: 477-PRI24045-000-040-RI-0005.pdf | I327: 000 General | J327: 040 Ingeniería - Ingeniería General | K327: Solicitud de Información | L327: Línea Base | M327: PRI24045-Wsp-EIA Proyecto IGP | N327: No | O327: false | P327: CMDIC-TRN-000164
A328: zip | B328: 477-PRI24045-000-040-RI-0006 | C328: Solicitud de Información Contrato PRI24045 N°006 - Solicitud Entregables Ingeniería FEL 2 Proyecto IGP Collahuasi | D328: 0 | E328: Respondido | F328: WSP Ambiental S.A | G328: 45973.523 | H328: 477-PRI24045-000-040-RI-0006.zip | I328: 000 General | J328: 040 Ingeniería - Ingeniería General | K328: Solicitud de Información | L328: Línea Base | M328: PRI24045-Wsp-EIA Proyecto IGP | N328: No | O328: false | P328: CMDIC-TRN-000162
A329: pdf | B329: 477-PRI24045-000-040-RI-0007 | C329: Solicitud de Información Contrato PRI24045 N°007 - Antecedentes Para Estudio Lumínico | D329: 0 | E329: Respondido | F329: WSP Ambiental S.A | G329: 45978.609 | H329: 477-PRI24045-000-040-RI-0007.pdf | I329: 000 General | J329: 040 Ingeniería - Ingeniería General | K329: Solicitud de Información | L329: Línea Base | M329: PRI24045-Wsp-EIA Proyecto IGP | N329: No | O329: false | P329: CMDIC-TRN-000165
A330: zip | B330: 477-PRI24045-000-040-RI-0008 | C330: Solicitud de Información Contrato PRI24045 N°008 - Calidad del Aire | D330: 0 | E330: Respondido | F330: WSP Ambiental S.A | G330: 46071.442 | H330: 477-PRI24045-000-040-RI-0008.zip | I330: 000 General | J330: 040 Ingeniería - Ingeniería General | K330: Solicitud de Información | L330: Línea Base | M330: PRI24045-Wsp-EIA Proyecto IGP | N330: No | O330: false | P330: CMDIC-TRN-000273
A331: pdf | B331: 477-PRI24045-000-040-RI-0009 | C331: Solicitud de Información Contrato PRI24045 N°009 - Cumplimiento del Hito CMDIC Entrega intermedia de ingeniería FEL3 | D331: 0 | E331: Respondido | F331: WSP Ambiental S.A | G331: 46059.368 | H331: 477-PRI24045-000-040-RI-0009.pdf | I331: 000 General | J331: 040 Ingeniería - Ingeniería General | K331: Solicitud de Información | L331: Línea Base | M331: PRI24045-Wsp-EIA Proyecto IGP | N331: No | O331: false | P331: CMDIC-TRN-000260
A332: pdf | B332: 477-PRI24045-000-040-RI-0010 | C332: Solicitud de Información Contrato PRI24045 N°010- Cumplimiento del Hito CMDIC Entrega Intermédia | D332: 0 | E332: Respuesta Requerida | F332: WSP Ambiental S.A | G332: 46066.491 | H332: 477-PRI24045-000-040-RI-0010.pdf | I332: 000 General | J332: 040 Ingeniería - Ingeniería General | K332: Solicitud de Información | L332: Línea Base | M332: PRI24045-Wsp-EIA Proyecto IGP | N332: No | O332: true
A333: pdf | B333: 477-PRI24045-000-081-TD-0001 | C333: PRI24045 - Aviso de Tendencia N°0001 | D333: 1 | E333: Aprobado | F333: WSP Ambiental S.A | G333: 45821.607 | H333: 477-PRI24045-000-081-TD-0001[1].pdf | I333: 000 General | J333: 081 Control - Costos | K333: Tendencia | L333: Línea Base | M333: PRI24045-Wsp-EIA Proyecto IGP | N333: No | O333: false | P333: CMDIC-TRN-000069
A334: pdf | B334: 477-PRI24045-000-081-TD-0002 | C334: PRI24045 - Aviso de Tendencia N°0002 | D334: 0 | E334: Aprobado | F334: WSP Ambiental S.A | G334: 45845.491 | H334: 477-PRI24045-000-081-TD-0002.pdf | I334: 000 General | J334: 081 Control - Costos | K334: Tendencia | L334: Línea Base | M334: PRI24045-Wsp-EIA Proyecto IGP | N334: No | O334: false | P334: CMDIC-TRN-000084
A335: pdf | B335: 477-PRI24045-000-081-TD-0003 | C335: PRI24045 - Aviso de Tendencia N°0003 | D335: 2 | E335: Aprobado | F335: WSP Ambiental S.A | G335: 45929.63 | H335: 477-PRI24045-000-081-TD-0003[2].pdf | I335: 000 General | J335: 081 Control - Costos | K335: Tendencia | L335: Línea Base | M335: PRI24045-Wsp-EIA Proyecto IGP | N335: No | O335: false | P335: CMDIC-TRN-000133
A336: pdf | B336: 477-PRI24045-000-081-TD-0004 | C336: PRI24045 - Aviso de Tendencia N°0004 | D336: 2 | E336: Aprobado | F336: WSP Ambiental S.A | G336: 45929.575 | H336: 477-PRI24045-000-081-TD-0004[2].pdf | I336: 000 General | J336: 081 Control - Costos | K336: Tendencia | L336: Línea Base | M336: PRI24045-Wsp-EIA Proyecto IGP | N336: No | O336: false | P336: CMDIC-TRN-000132
A337: pdf | B337: 477-PRI24045-000-081-TD-0005 | C337: PRI24045 - Aviso de Tendencia N°0005 | D337: 1 | E337: Aprobado | F337: WSP Ambiental S.A | G337: 46027.411 | H337: 477-PRI24045-000-081-TD-0005_Rev. 1.pdf | I337: 000 General | J337: 081 Control - Costos | K337: Tendencia | L337: Línea Base | M337: PRI24045-Wsp-EIA Proyecto IGP | N337: No | O337: false | P337: CMDIC-TRN-000219
A338: pdf | B338: 477-PRI24045-000-081-TD-0006 | C338: PRI24045 - Aviso de Tendencia N°0006 | D338: 0 | E338: Aprobado | F338: WSP Ambiental S.A | G338: 46014.643 | H338: 477-PRI24045-000-081-TD-0006.pdf | I338: 000 General | J338: 081 Control - Costos | K338: Tendencia | L338: Línea Base | M338: PRI24045-Wsp-EIA Proyecto IGP | N338: No | O338: false | P338: CMDIC-TRN-000210
...

Sheet Programa P6 Excel R1
B1: =+'Av. Subcontratos'!B5 -> Reporte Semanal de Proyectos
B2: Programa del Servicio | U2: INFORME ANTERIOR
B4: Activity ID | C4: Activity Name | D4: Original Duration | E4: BL1 Start | F4: BL1 Finish | G4: Start | H4: Finish | I4: Schedule % Complete | J4: Performance % Complete | K4: Budgeted Labor Units | L4: Planned Value Labor Units | M4: Earned Value Labor Units | N4: Actual Labor Units | P4: Predecessors | Q4: Successors | R4: Desv. HH | S4: Desv. % | U4: Desv. % Inf.40 | V4: Diferencia | X4: Activity ID | Y4: Activity Name | Z4: Original Duration | AA4: BL1 Start | AB4: BL1 Finish | AC4: Start | AD4: Finish | AE4: Schedule % Complete | AF4: Performance % Complete | AG4: Budgeted Labor Units | AH4: Planned Value Labor Units | AI4: Earned Value Labor Units | AJ4: Actual Labor Units
B5: Contrato N° PRI24045 LB R1 DD 16-abr-26 | D5: 1016 | E5: 45751 | F5: 46660 | G5: 45751 | H5: 46660 | I5: 0.4998 | J5: 0.4009 | K5: =+W5 -> 125424 | L5: 62685.04 | M5: 50288.4 | N5: 65494.47 | O5: 62897.86 | R5: =+M5-L5 -> -12396.64 | S5: =+R5/$K$5 -> -0.098837862 | U5: -0.044908366 | V5: =+S5-U5 -> -0.053929496 | W5: 125424 | X5: Contrato N° PRI24045 LB R1 DD 16-abr-26 | Z5: 1016 | AA5: 45751 | AB5: 46660 | AC5: 45751 | AD5: 46660 | AE5: 0.4998 | AF5: 0.4009 | AG5: 146397.8 | AH5: 62685.04 | AI5: 50288.4 | AJ5: 65494.47
B6: Hitos Contractuales | D6: 822 | E6: 45771 | F6: 46660 | G6: 45771 | H6: 46660 | I6: 0 | J6: 0 | K6: 0 | L6: 0 | M6: 0 | N6: 0 | O6: 0 | R6: =+N6-L6 -> 0 | S6: =+R6/$K$5 -> 0 | U6: 0 | V6: =+S6-U6 -> 0 | X6: Hitos Contractuales | Z6: 822 | AA6: 45771 | AB6: 46660 | AC6: 45771 | AD6: 46660 | AE6: 0 | AF6: 0 | AG6: 0 | AH6: 0 | AI6: 0 | AJ6: 0
B7: Hitos Contractuales | D7: 822 | E7: 45771 | F7: 46660 | G7: 45771 | H7: 46660 | I7: 0 | J7: 0 | K7: 0 | L7: 0 | M7: 0 | N7: 0 | O7: 0 | R7: =+N7-L7 -> 0 | S7: =+R7/$K$5 -> 0 | U7: 0 | V7: =+S7-U7 -> 0 | X7: Hitos Contractuales | Z7: 822 | AA7: 45771 | AB7: 46660 | AC7: 45771 | AD7: 46660 | AE7: 0 | AF7: 0 | AG7: 0 | AH7: 0 | AI7: 0 | AJ7: 0
B8: HCONT-001 | C8: Hito 1: Listado de entregables (Día 7) | D8: 0 | F8: 45819 | H8: 45819 | I8: 1 | J8: 1 | K8: 0 | L8: 0 | M8: 0 | N8: 0 | O8: 0 | P8: 477-010-40-0012 | Q8: 477-010-40-0007 | R8: =+N8-L8 -> 0 | S8: =+R8/$K$5 -> 0 | U8: 0 | V8: =+S8-U8 -> 0 | X8: HCONT-001 | Y8: Hito 1: Listado de entregables (Día 7) | Z8: 0 | AB8: 45819 | AD8: 45819 | AE8: 1 | AF8: 1 | AG8: 0 | AH8: 0 | AI8: 0 | AJ8: 0
B9: HCONT-002 | C9: Hito 2: Programa de Ejecución del servicio (Día 15) | D9: 0 | F9: 45771 | H9: 45771 | I9: 1 | J9: 1 | K9: 0 | L9: 0 | M9: 0 | N9: 0 | O9: 0 | P9: 477-010-40-0006 | Q9: 477-010-40-0005 | R9: =+N9-L9 -> 0 | S9: =+R9/$K$5 -> 0 | U9: 0 | V9: =+S9-U9 -> 0 | X9: HCONT-002 | Y9: Hito 2: Programa de Ejecución del servicio (Día 15) | Z9: 0 | AB9: 45771 | AD9: 45771 | AE9: 1 | AF9: 1 | AG9: 0 | AH9: 0 | AI9: 0 | AJ9: 0
B10: HCONT-003 | C10: Hito 3: Capeta de arranque y acreditaciones WSP y Geobiota (Día 30) | D10: 0 | F10: 45782 | H10: 45782 | I10: 1 | J10: 1 | K10: 0 | L10: 0 | M10: 0 | N10: 0 | O10: 0 | P10: 477-010-40-0008, 477-010-40-0009 | Q10: 477-010-40-0376, 477-010-40-0392, 477-010-40-0408, 477-010-40-0424 | R10: =+N10-L10 -> 0 | S10: =+R10/$K$5 -> 0 | U10: 0 | V10: =+S10-U10 -> 0 | X10: HCONT-003 | Y10: Hito 3: Capeta de arranque y acreditaciones WSP y Geobiota (Día 30) | Z10: 0 | AB10: 45782 | AD10: 45782 | AE10: 1 | AF10: 1 | AG10: 0 | AH10: 0 | AI10: 0 | AJ10: 0
B11: HCONT-004 | C11: Hito 4: Revisión y evaluación de información disponible (Día 30) | D11: 0 | F11: 45782 | H11: 45782 | I11: 1 | J11: 1 | K11: 0 | L11: 0 | M11: 0 | N11: 0 | O11: 0 | P11: 477-010-40-0023 | Q11: 477-010-40-0024 | R11: =+N11-L11 -> 0 | S11: =+R11/$K$5 -> 0 | U11: 0 | V11: =+S11-U11 -> 0 | X11: HCONT-004 | Y11: Hito 4: Revisión y evaluación de información disponible (Día 30) | Z11: 0 | AB11: 45782 | AD11: 45782 | AE11: 1 | AF11: 1 | AG11: 0 | AH11: 0 | AI11: 0 | AJ11: 0
B12: HCONT-005 | C12: Hito 5: Determinación y justificación inicial AI para cada componente (Día 35) | D12: 0 | F12: 45786 | H12: 45786 | I12: 1 | J12: 1 | K12: 0 | L12: 0 | M12: 0 | N12: 0 | O12: 0 | P12: 477-010-40-0015 | Q12: 477-010-40-0376, 477-010-40-0408, 477-010-40-0392, 477-010-40-0424 | R12: =+N12-L12 -> 0 | S12: =+R12/$K$5 -> 0 | U12: 0 | V12: =+S12-U12 -> 0 | X12: HCONT-005 | Y12: Hito 5: Determinación y justificación inicial AI para cada componente (Día 35) | Z12: 0 | AB12: 45786 | AD12: 45786 | AE12: 1 | AF12: 1 | AG12: 0 | AH12: 0 | AI12: 0 | AJ12: 0
B13: HCONT-006 | C13: Hito 6: Metodología desarrollo de líneas de base ambiental (Día 35) | D13: 0 | F13: 45786 | H13: 45786 | I13: 1 | J13: 1 | K13: 0 | L13: 0 | M13: 0 | N13: 0 | O13: 0 | P13: 477-010-40-0015 | Q13: 477-010-40-0376, 477-010-40-0408, 477-010-40-0392, 477-010-40-0424 | R13: =+N13-L13 -> 0 | S13: =+R13/$K$5 -> 0 | U13: 0 | V13: =+S13-U13 -> 0 | X13: HCONT-006 | Y13: Hito 6: Metodología desarrollo de líneas de base ambiental (Día 35) | Z13: 0 | AB13: 45786 | AD13: 45786 | AE13: 1 | AF13: 1 | AG13: 0 | AH13: 0 | AI13: 0 | AJ13: 0
B14: HCONT-007 | C14: Hito 7: Inicio campañas de línea de base en terreno (Día 45) | D14: 0 | F14: 45799 | H14: 45799 | I14: 1 | J14: 1 | K14: 0 | L14: 0 | M14: 0 | N14: 0 | O14: 0 | P14: 477-010-40-0376 | Q14: 477-010-40-0377, 477-010-40-0393, 477-010-40-0409, 477-010-40-0425 | R14: =+N14-L14 -> 0 | S14: =+R14/$K$5 -> 0 | U14: 0 | V14: =+S14-U14 -> 0 | X14: HCONT-007 | Y14: Hito 7: Inicio campañas de línea de base en terreno (Día 45) | Z14: 0 | AB14: 45799 | AD14: 45799 | AE14: 1 | AF14: 1 | AG14: 0 | AH14: 0 | AI14: 0 | AJ14: 0
B15: HCONT-008 | C15: Hito 8: Ejecución taller de identificación de aspectos críticos del proyecto y estrategia para abordarlos (Día 75) | D15: 0 | F15: 45869 | H15: 45869 | I15: 1 | J15: 1 | K15: 0 | L15: 0 | M15: 0 | N15: 0 | O15: 0 | P15: 477-010-40-0022 | Q15: 477-010-40-0001, 477-010-40-0545 | R15: =+N15-L15 -> 0 | S15: =+R15/$K$5 -> 0 | U15: 0 | V15: =+S15-U15 -> 0 | X15: HCONT-008 | Y15: Hito 8: Ejecución taller de identificación de aspectos críticos del proyecto y estrategia para abordarlos (Día 75) | Z15: 0 | AB15: 45869 | AD15: 45869 | AE15: 1 | AF15: 1 | AG15: 0 | AH15: 0 | AI15: 0 | AJ15: 0
B16: HCONT-009 | C16: Hito 9: Análisis y verificación prop. compromisos Ambientales instrumentos anteriores (Día 90) | D16: 0 | F16: 45883 | H16: 45883 | I16: 1 | J16: 1 | K16: 0 | L16: 0 | M16: 0 | N16: 0 | O16: 0 | P16: 477-010-40-0030 | Q16: HCONT-010 | R16: =+N16-L16 -> 0 | S16: =+R16/$K$5 -> 0 | U16: 0 | V16: =+S16-U16 -> 0 | X16: HCONT-009 | Y16: Hito 9: Análisis y verificación prop. compromisos Ambientales instrumentos anteriores (Día 90) | Z16: 0 | AB16: 45883 | AD16: 45883 | AE16: 1 | AF16: 1 | AG16: 0 | AH16: 0 | AI16: 0 | AJ16: 0
B17: HCONT-010 | C17: Hito 10: Met. y criterios Ev. impactos identificación preliminar y estrategia para abordarlos (Día 120) | D17: 0 | F17: 45896 | H17: 45896 | I17: 1 | J17: 1 | K17: 0 | L17: 0 | M17: 0 | N17: 0 | O17: 0 | P17: 477-010-40-0034, HCONT-009 | Q17: 477-010-40-0506 | R17: =+N17-L17 -> 0 | S17: =+R17/$K$5 -> 0 | U17: 0 | V17: =+S17-U17 -> 0 | X17: HCONT-010 | Y17: Hito 10: Met. y criterios Ev. impactos identificación preliminar y estrategia para abordarlos (Día 120) | Z17: 0 | AB17: 45896 | AD17: 45896 | AE17: 1 | AF17: 1 | AG17: 0 | AH17: 0 | AI17: 0 | AJ17: 0
B18: HCONT-011 | C18: Hito 11: Término campañas de línea de base en terreno (exceptuando medio marino) (Día 410) | D18: 0 | F18: 46161 | H18: 46178 | I18: 0 | J18: 0 | K18: 0 | L18: 0 | M18: 0 | N18: 0 | O18: 0 | P18: 477-010-40-0370, 477-010-40-0386, 477-010-40-0402, 477-010-40-0418, 477-010-40-0432, 477-010-40-0456, 477-010-40-0479, 477-010-40-0001, 477-010-40-0011 | Q18: 477-010-40-0405 | R18: =+N18-L18 -> 0 | S18: =+R18/$K$5 -> 0 | U18: 0 | V18: =+S18-U18 -> 0 | X18: HCONT-011 | Y18: Hito 11: Término campañas de línea de base en terreno (exceptuando medio marino) (Día 410) | Z18: 0 | AB18: 46161 | AD18: 46178 | AE18: 0 | AF18: 0 | AG18: 0 | AH18: 0 | AI18: 0 | AJ18: 0
B19: HCONT-012 | C19: Hito 12: Término elaboración EIA (Rev.0) (Día 628) | D19: 0 | F19: 46378 | H19: 46378 | I19: 0 | J19: 0 | K19: 0 | L19: 0 | M19: 0 | N19: 0 | O19: 0 | P19: 477-010-40-0607, 477-010-40-0013, 477-010-40-0014 | Q19: 477-010-40-0612 | R19: =+N19-L19 -> 0 | S19: =+R19/$K$5 -> 0 | U19: 0 | V19: =+S19-U19 -> 0 | X19: HCONT-012 | Y19: Hito 12: Término elaboración EIA (Rev.0) (Día 628) | Z19: 0 | AB19: 46378 | AD19: 46378 | AE19: 0 | AF19: 0 | AG19: 0 | AH19: 0 | AI19: 0 | AJ19: 0
... B21: HCONT-014 | C21: Hito 14: Presentación del Proyecto (Día 642) | D21: 0 | F21: 46392 | H21: 46392 | I21: 0 | J21: 0 | K21: 0 | L21: 0 | M21: 0 | N21: 0 | O21: 0 | P21: 477-010-40-0003, 477-010-40-0007, 477-010-40-0618 | Q21: 477-010-40-0619 | R21: =+N21-L21 -> 0 | S21: =+R21/$K$5 -> 0 | U21: 0 | V21: =+S21-U21 -> 0 | X21: HCONT-014 | Y21: Hito 14: Presentación del Proyecto (Día 642) | Z21: 0 | AB21: 46392 | AD21: 46392 | AE21: 0 | AF21: 0 | AG21: 0 | AH21: 0 | AI21: 0 | AJ21: 0
B22: HCONT-015 | C22: Término del Servicio | D22: 0 | F22: 46660 | H22: 46660 | I22: 0 | J22: 0 | K22: 0 | L22: 0 | M22: 0 | N22: 0 | O22: 0 | P22: 477-010-40-0622, 477-010-40-0606, 477-010-40-0613, 477-010-40-0002, 477-010-40-0005 | R22: =+N22-L22 -> 0 | S22: =+R22/$K$5 -> 0 | U22: 0 | V22: =+S22-U22 -> 0 | X22: HCONT-015 | Y22: Término del Servicio | Z22: 0 | AB22: 46660 | AD22: 46660 | AE22: 0 | AF22: 0 | AG22: 0 | AH22: 0 | AI22: 0 | AJ22: 0
